Workbook
Name n_familias: 'Parámetros'!$B$5
Name cuota_mensual: 'Parámetros'!$B$6
Name tasa_desercion: 'Parámetros'!$B$7
Name familias_sorteo: 'Parámetros'!$B$8
Name precio_terreno: 'Parámetros'!$B$10
Name sup_terreno: 'Parámetros'!$B$11
Name viv_x_terreno: 'Parámetros'!$B$12
Name apreciacion_suelo: 'Parámetros'!$B$13
Name cap2_monto: 'Parámetros'!$B$15
Name cap2_ratio: 'Parámetros'!$B$16
Name cap2_retorno: 'Parámetros'!$B$17
Name plazo_anos: 'Parámetros'!$B$18
Name gracia_meses: 'Parámetros'!$B$19
Name subsidio_uf: 'Parámetros'!$B$21
Name valor_uf: 'Parámetros'!$B$22
Name pct_subsidio: 'Parámetros'!$B$23
Name subsidio_destino: 'Parámetros'!$B$24
Name canon_mensual: 'Parámetros'!$B$26
Name canon_crecimiento: 'Parámetros'!$B$27
Name costo_construccion: 'Parámetros'!$B$29
Name tasa_credito: 'Parámetros'!$B$30
Name plazo_credito: 'Parámetros'!$B$31

Sheet Parámetros
A1: FONDO MUTUALISTA DE SUELO URBANO — Parámetros del Modelo
A2: Las celdas amarillas son editables. Todos los cálculos se actualizan automáticamente.
A3: Parámetro | B3: Valor | C3: Unidad | D3: Nota
A4: ▌ 1. DEMANDA
A5: Número de familias participantes | B5: 500 | C5: familias | D5: Base del fondo
A6: Cuota mensual por familia | B6: 30000 | C6: CLP/mes | D6: Aporte mensual
A7: Tasa de deserción anual estimada | B7: 0.05 | C7: anual | D7: 5% base ajustada
A8: Familias por grupo de sorteo | B8: 25 | C8: familias | D8: Tamaño lote
A9: ▌ 2. SUELO
A10: Precio promedio terreno objetivo | B10: 120000000 | C10: CLP | D10: Por terreno completo
A11: Superficie promedio terreno | B11: 1000 | C11: m² | D11: Referencial
A12: Viviendas por terreno | B12: 25 | C12: unidades | D12: Densidad
A13: Apreciación anual estimada del suelo | B13: 0.05 | C13: anual | D13: Inflación suelo
A14: ▌ 3. CAPITAL PACIENTE — CAPA 2
A15: Monto comprometido total | B15: 500000000 | C15: CLP | D15: Capital paciente total
A16: Ratio desembolso Capa 2 / Capa 1 | B16: 3 | C16: x | D16: Por cada 1 CLP de Capa 1, desembolsa X de Capa 2
A17: Retorno anual exigido Capa 2 | B17: 0.05 | C17: anual | D17: Costo capital
A18: Plazo del fondo | B18: 15 | C18: años | D18: Horizonte total
A19: Período de gracia Capa 2 | B19: 12 | C19: meses | D19: Sin interés inicial
A20: ▌ 4. SUBSIDIO ESTATAL — CAPA 3
A21: Subsidio por familia | B21: 800 | C21: UF/familia | D21: Componente suelo
A22: Valor UF | B22: 38000 | C22: CLP/UF | D22: Actualizar periódicamente
A23: % familias que acceden a subsidio | B23: 0.6 | C23: % | D23: Cobertura estimada
A24: Destino del subsidio | B24: 1 | C24: % | D24: 100% a suelo CLT
A25: ▌ 5. CANON DE USO DE SUELO (GROUND LEASE)
A26: Canon mensual por familia en CLT | B26: 25000 | C26: CLP/mes | D26: Arrendamiento suelo
A27: Crecimiento anual del canon (IPC) | B27: 0.03 | C27: anual | D27: Indexación IPC
A28: ▌ 6. CONSTRUCCIÓN (referencial — no parte del fondo de suelo)
A29: Costo construcción por vivienda | B29: 1200 | C29: UF/vivienda | D29: Referencial mercado
A30: Tasa crédito bancario construcción | B30: 0.04 | C30: anual | D30: Tasa referencial
A31: Plazo crédito bancario | B31: 20 | C31: años | D31: Referencial
A32: ▌ 7. CELDAS AUXILIARES (usadas por tablas de sensibilidad)
A33: Input variable cuota (Tabla 1) | B33: =B5 | C33: CLP | D33: Variable de entrada para Tabla Sensibilidad 1
A34: Input variable familias (Tabla 1 y 3) | B34: =B4 | C34: familias | D34: Variable de entrada para Tabla Sensibilidad 1 y 3
A35: Input variable canon (Tabla 2) | B35: =B17 | C35: CLP | D35: Variable de entrada para Tabla Sensibilidad 2
A36: Input variable precio terreno (Tabla 3) | B36: =B8 | C36: CLP | D36: Variable de entrada para Tabla Sensibilidad 3

Sheet Flujo del Fondo
A1: FLUJO DEL FONDO — Horizonte 180 Meses (15 Años)
A2: Mes | B2: Año | C2: Fam. Activas | D2: Ap. Capa 1 | E2: Acum. Capa 1 | F2: Desemb. C2 | G2: Acum. C2 | H2: Acum. C3 | I2: Cap. Total | J2: Terrenos | K2: Fam. Ubic. | L2: En Espera | M2: Canon Mes. | N2: Acum. Canon | O2: Serv. C2 | P2: Flujo Neto | Q2: Acum. Neto
A3: Mes | B3: Año | C3: Familias Activas | D3: Aporte Mensual Capa 1 (CLP) | E3: Acumulado Capa 1 (CLP) | F3: Desembolso Capa 2 Mensual (CLP) | G3: Capital Capa 2 Acumulado (CLP) | H3: Subsidio Capa 3 Acumulado (CLP) | I3: Capital Total Disponible (CLP) | J3: Terrenos Adquiridos Acumulados | K3: Familias Ubicadas Acumuladas | L3: Familias en Espera | M3: Canon Mensual Recibido (CLP) | N3: Canon Acumulado (CLP) | O3: Servicio Deuda Capa 2 Mensual (CLP) | P3: Flujo Neto Mensual (CLP) | Q3: Flujo Neto Acumulado (CLP)
A4: 1 | B4: =INT((1-1)/12)+1 | C4: ='Parámetros'!$B$5 | D4: =C4*'Parámetros'!$B$6 | E4: =D4 | F4: =MIN('Parámetros'!$B$15, D4*'Parámetros'!$B$16) | G4: =F4 | H4: =0 | I4: =E4+G4+H4 | J4: =ENTERO(I4/('Parámetros'!$B$10*(1+'Parámetros'!$B$13)^((1-1)/12))) | K4: =J4*'Parámetros'!$B$12 | L4: =MAX(0,C4-K4) | M4: =K4*('Parámetros'!$B$26*(1+'Parámetros'!$B$27)^((1-1)/12)) | N4: =M4 | O4: =IF(1<='Parámetros'!$B$19,0,G4*'Parámetros'!$B$17/12) | P4: =D4+M4-O4 | Q4: =P4
A5: 2 | B5: =INT((2-1)/12)+1 | C5: =REDONDEAR(C4*(1-'Parámetros'!$B$7)^(1/12),0) | D5: =C5*'Parámetros'!$B$6 | E5: =E4+D5 | F5: =MAX(0, MIN('Parámetros'!$B$15-G4, D5*'Parámetros'!$B$16)) | G5: =G4+F5 | H5: =H4+IF(J5>J4,(J5-J4)*('Parámetros'!$B$12*'Parámetros'!$B$23*'Parámetros'!$B$21*'Parámetros'!$B$22*'Parámetros'!$B$24),0) | I5: =E5+G5+H5 | J5: =ENTERO(I5/('Parámetros'!$B$10*(1+'Parámetros'!$B$13)^((2-1)/12))) | K5: =J5*'Parámetros'!$B$12 | L5: =MAX(0,C5-K5) | M5: =K5*('Parámetros'!$B$26*(1+'Parámetros'!$B$27)^((2-1)/12)) | N5: =N4+M5 | O5: =IF(2<='Parámetros'!$B$19,0,G5*'Parámetros'!$B$17/12) | P5: =D5+M5-O5 | Q5: =Q4+P5
A6: 3 | B6: =INT((3-1)/12)+1 | C6: =REDONDEAR(C5*(1-'Parámetros'!$B$7)^(1/12),0) | D6: =C6*'Parámetros'!$B$6 | E6: =E5+D6 | F6: =MAX(0, MIN('Parámetros'!$B$15-G5, D6*'Parámetros'!$B$16)) | G6: =G5+F6 | H6: =H5+IF(J6>J5,(J6-J5)*('Parámetros'!$B$12*'Parámetros'!$B$23*'Parámetros'!$B$21*'Parámetros'!$B$22*'Parámetros'!$B$24),0) | I6: =E6+G6+H6 | J6: =ENTERO(I6/('Parámetros'!$B$10*(1+'Parámetros'!$B$13)^((3-1)/12))) | K6: =J6*'Parámetros'!$B$12 | L6: =MAX(0,C6-K6) | M6: =K6*('Parámetros'!$B$26*(1+'Parámetros'!$B$27)^((3-1)/12)) | N6: =N5+M6 | O6: =IF(3<='Parámetros'!$B$19,0,G6*'Parámetros'!$B$17/12) | P6: =D6+M6-O6 | Q6: =Q5+P6
A7: 4 | B7: =INT((4-1)/12)+1 | C7: =REDONDEAR(C6*(1-'Parámetros'!$B$7)^(1/12),0) | D7: =C7*'Parámetros'!$B$6 | E7: =E6+D7 | F7: =MAX(0, MIN('Parámetros'!$B$15-G6, D7*'Parámetros'!$B$16)) | G7: =G6+F7 | H7: =H6+IF(J7>J6,(J7-J6)*('Parámetros'!$B$12*'Parámetros'!$B$23*'Parámetros'!$B$21*'Parámetros'!$B$22*'Parámetros'!$B$24),0) | I7: =E7+G7+H7 | J7: =ENTERO(I7/('Parámetros'!$B$10*(1+'Parámetros'!$B$13)^((4-1)/12))) | K7: =J7*'Parámetros'!$B$12 | L7: =MAX(0,C7-K7) | M7: =K7*('Parámetros'!$B$26*(1+'Parámetros'!$B$27)^((4-1)/12)) | N7: =N6+M7 | O7: =IF(4<='Parámetros'!$B$19,0,G7*'Parámetros'!$B$17/12) | P7: =D7+M7-O7 | Q7: =Q6+P7
A8: 5 | B8: =INT((5-1)/12)+1 | C8: =REDONDEAR(C7*(1-'Parámetros'!$B$7)^(1/12),0) | D8: =C8*'Parámetros'!$B$6 | E8: =E7+D8 | F8: =MAX(0, MIN('Parámetros'!$B$15-G7, D8*'Parámetros'!$B$16)) | G8: =G7+F8 | H8: =H7+IF(J8>J7,(J8-J7)*('Parámetros'!$B$12*'Parámetros'!$B$23*'Parámetros'!$B$21*'Parámetros'!$B$22*'Parámetros'!$B$24),0) | I8: =E8+G8+H8 | J8: =ENTERO(I8/('Parámetros'!$B$10*(1+'Parámetros'!$B$13)^((5-1)/12))) | K8: =J8*'Parámetros'!$B$12 | L8: =MAX(0,C8-K8) | M8: =K8*('Parámetros'!$B$26*(1+'Parámetros'!$B$27)^((5-1)/12)) | N8: =N7+M8 | O8: =IF(5<='Parámetros'!$B$19,0,G8*'Parámetros'!$B$17/12) | P8: =D8+M8-O8 | Q8: =Q7+P8
A9: 6 | B9: =INT((6-1)/12)+1 | C9: =REDONDEAR(C8*(1-'Parámetros'!$B$7)^(1/12),0) | D9: =C9*'Parámetros'!$B$6 | E9: =E8+D9 | F9: =MAX(0, MIN('Parámetros'!$B$15-G8, D9*'Parámetros'!$B$16)) | G9: =G8+F9 | H9: =H8+IF(J9>J8,(J9-J8)*('Parámetros'!$B$12*'Parámetros'!$B$23*'Parámetros'!$B$21*'Parámetros'!$B$22*'Parámetros'!$B$24),0) | I9: =E9+G9+H9 | J9: =ENTERO(I9/('Parámetros'!$B$10*(1+'Parámetros'!$B$13)^((6-1)/12))) | K9: =J9*'Parámetros'!$B$12 | L9: =MAX(0,C9-K9) | M9: =K9*('Parámetros'!$B$26*(1+'Parámetros'!$B$27)^((6-1)/12)) | N9: =N8+M9 | O9: =IF(6<='Parámetros'!$B$19,0,G9*'Parámetros'!$B$17/12) | P9: =D9+M9-O9 | Q9: =Q8+P9
A10: 7 | B10: =INT((7-1)/12)+1 | C10: =REDONDEAR(C9*(1-'Parámetros'!$B$7)^(1/12),0) | D10: =C10*'Parámetros'!$B$6 | E10: =E9+D10 | F10: =MAX(0, MIN('Parámetros'!$B$15-G9, D10*'Parámetros'!$B$16)) | G10: =G9+F10 | H10: =H9+IF(J10>J9,(J10-J9)*('Parámetros'!$B$12*'Parámetros'!$B$23*'Parámetros'!$B$21*'Parámetros'!$B$22*'Parámetros'!$B$24),0) | I10: =E10+G10+H10 | J10: =ENTERO(I10/('Parámetros'!$B$10*(1+'Parámetros'!$B$13)^((7-1)/12))) | K10: =J10*'Parámetros'!$B$12 | L10: =MAX(0,C10-K10) | M10: =K10*('Parámetros'!$B$26*(1+'Parámetros'!$B$27)^((7-1)/12)) | N10: =N9+M10 | O10: =IF(7<='Parámetros'!$B$19,0,G10*'Parámetros'!$B$17/12) | P10: =D10+M10-O10 | Q10: =Q9+P10
A11: 8 | B11: =INT((8-1)/12)+1 | C11: =REDONDEAR(C10*(1-'Parámetros'!$B$7)^(1/12),0) | D11: =C11*'Parámetros'!$B$6 | E11: =E10+D11 | F11: =MAX(0, MIN('Parámetros'!$B$15-G10, D11*'Parámetros'!$B$16)) | G11: =G10+F11 | H11: =H10+IF(J11>J10,(J11-J10)*('Parámetros'!$B$12*'Parámetros'!$B$23*'Parámetros'!$B$21*'Parámetros'!$B$22*'Parámetros'!$B$24),0) | I11: =E11+G11+H11 | J11: =ENTERO(I11/('Parámetros'!$B$10*(1+'Parámetros'!$B$13)^((8-1)/12))) | K11: =J11*'Parámetros'!$B$12 | L11: =MAX(0,C11-K11) | M11: =K11*('Parámetros'!$B$26*(1+'Parámetros'!$B$27)^((8-1)/12)) | N11: =N10+M11 | O11: =IF(8<='Parámetros'!$B$19,0,G11*'Parámetros'!$B$17/12) | P11: =D11+M11-O11 | Q11: =Q10+P11
A12: 9 | B12: =INT((9-1)/12)+1 | C12: =REDONDEAR(C11*(1-'Parámetros'!$B$7)^(1/12),0) | D12: =C12*'Parámetros'!$B$6 | E12: =E11+D12 | F12: =MAX(0, MIN('Parámetros'!$B$15-G11, D12*'Parámetros'!$B$16)) | G12: =G11+F12 | H12: =H11+IF(J12>J11,(J12-J11)*('Parámetros'!$B$12*'Parámetros'!$B$23*'Parámetros'!$B$21*'Parámetros'!$B$22*'Parámetros'!$B$24),0) | I12: =E12+G12+H12 | J12: =ENTERO(I12/('Parámetros'!$B$10*(1+'Parámetros'!$B$13)^((9-1)/12))) | K12: =J12*'Parámetros'!$B$12 | L12: =MAX(0,C12-K12) | M12: =K12*('Parámetros'!$B$26*(1+'Parámetros'!$B$27)^((9-1)/12)) | N12: =N11+M12 | O12: =IF(9<='Parámetros'!$B$19,0,G12*'Parámetros'!$B$17/12) | P12: =D12+M12-O12 | Q12: =Q11+P12
A13: 10 | B13: =INT((10-1)/12)+1 | C13: =REDONDEAR(C12*(1-'Parámetros'!$B$7)^(1/12),0) | D13: =C13*'Parámetros'!$B$6 | E13: =E12+D13 | F13: =MAX(0, MIN('Parámetros'!$B$15-G12, D13*'Parámetros'!$B$16)) | G13: =G12+F13 | H13: =H12+IF(J13>J12,(J13-J12)*('Parámetros'!$B$12*'Parámetros'!$B$23*'Parámetros'!$B$21*'Parámetros'!$B$22*'Parámetros'!$B$24),0) | I13: =E13+G13+H13 | J13: =ENTERO(I13/('Parámetros'!$B$10*(1+'Parámetros'!$B$13)^((10-1)/12))) | K13: =J13*'Parámetros'!$B$12 | L13: =MAX(0,C13-K13) | M13: =K13*('Parámetros'!$B$26*(1+'Parámetros'!$B$27)^((10-1)/12)) | N13: =N12+M13 | O13: =IF(10<='Parámetros'!$B$19,0,G13*'Parámetros'!$B$17/12) | P13: =D13+M13-O13 | Q13: =Q12+P13
A14: 11 | B14: =INT((11-1)/12)+1 | C14: =REDONDEAR(C13*(1-'Parámetros'!$B$7)^(1/12),0) | D14: =C14*'Parámetros'!$B$6 | E14: =E13+D14 | F14: =MAX(0, MIN('Parámetros'!$B$15-G13, D14*'Parámetros'!$B$16)) | G14: =G13+F14 | H14: =H13+IF(J14>J13,(J14-J13)*('Parámetros'!$B$12*'Parámetros'!$B$23*'Parámetros'!$B$21*'Parámetros'!$B$22*'Parámetros'!$B$24),0) | I14: =E14+G14+H14 | J14: =ENTERO(I14/('Parámetros'!$B$10*(1+'Parámetros'!$B$13)^((11-1)/12))) | K14: =J14*'Parámetros'!$B$12 | L14: =MAX(0,C14-K14) | M14: =K14*('Parámetros'!$B$26*(1+'Parámetros'!$B$27)^((11-1)/12)) | N14: =N13+M14 | O14: =IF(11<='Parámetros'!$B$19,0,G14*'Parámetros'!$B$17/12) | P14: =D14+M14-O14 | Q14: =Q13+P14
A15: 12 | B15: =INT((12-1)/12)+1 | C15: =REDONDEAR(C14*(1-'Parámetros'!$B$7)^(1/12),0) | D15: =C15*'Parámetros'!$B$6 | E15: =E14+D15 | F15: =MAX(0, MIN('Parámetros'!$B$15-G14, D15*'Parámetros'!$B$16)) | G15: =G14+F15 | H15: =H14+IF(J15>J14,(J15-J14)*('Parámetros'!$B$12*'Parámetros'!$B$23*'Parámetros'!$B$21*'Parámetros'!$B$22*'Parámetros'!$B$24),0) | I15: =E15+G15+H15 | J15: =ENTERO(I15/('Parámetros'!$B$10*(1+'Parámetros'!$B$13)^((12-1)/12))) | K15: =J15*'Parámetros'!$B$12 | L15: =MAX(0,C15-K15) | M15: =K15*('Parámetros'!$B$26*(1+'Parámetros'!$B$27)^((12-1)/12)) | N15: =N14+M15 | O15: =IF(12<='Parámetros'!$B$19,0,G15*'Parámetros'!$B$17/12) | P15: =D15+M15-O15 | Q15: =Q14+P15
A16: 13 | B16: =INT((13-1)/12)+1 | C16: =REDONDEAR(C15*(1-'Parámetros'!$B$7)^(1/12),0) | D16: =C16*'Parámetros'!$B$6 | E16: =E15+D16 | F16: =MAX(0, MIN('Parámetros'!$B$15-G15, D16*'Parámetros'!$B$16)) | G16: =G15+F16 | H16: =H15+IF(J16>J15,(J16-J15)*('Parámetros'!$B$12*'Parámetros'!$B$23*'Parámetros'!$B$21*'Parámetros'!$B$22*'Parámetros'!$B$24),0) | I16: =E16+G16+H16 | J16: =ENTERO(I16/('Parámetros'!$B$10*(1+'Parámetros'!$B$13)^((13-1)/12))) | K16: =J16*'Parámetros'!$B$12 | L16: =MAX(0,C16-K16) | M16: =K16*('Parámetros'!$B$26*(1+'Parámetros'!$B$27)^((13-1)/12)) | N16: =N15+M16 | O16: =IF(13<='Parámetros'!$B$19,0,G16*'Parámetros'!$B$17/12) | P16: =D16+M16-O16 | Q16: =Q15+P16
A17: 14 | B17: =INT((14-1)/12)+1 | C17: =REDONDEAR(C16*(1-'Parámetros'!$B$7)^(1/12),0) | D17: =C17*'Parámetros'!$B$6 | E17: =E16+D17 | F17: =MAX(0, MIN('Parámetros'!$B$15-G16, D17*'Parámetros'!$B$16)) | G17: =G16+F17 | H17: =H16+IF(J17>J16,(J17-J16)*('Parámetros'!$B$12*'Parámetros'!$B$23*'Parámetros'!$B$21*'Parámetros'!$B$22*'Parámetros'!$B$24),0) | I17: =E17+G17+H17 | J17: =ENTERO(I17/('Parámetros'!$B$10*(1+'Parámetros'!$B$13)^((14-1)/12))) | K17: =J17*'Parámetros'!$B$12 | L17: =MAX(0,C17-K17) | M17: =K17*('Parámetros'!$B$26*(1+'Parámetros'!$B$27)^((14-1)/12)) | N17: =N16+M17 | O17: =IF(14<='Parámetros'!$B$19,0,G17*'Parámetros'!$B$17/12) | P17: =D17+M17-O17 | Q17: =Q16+P17
A18: 15 | B18: =INT((15-1)/12)+1 | C18: =REDONDEAR(C17*(1-'Parámetros'!$B$7)^(1/12),0) | D18: =C18*'Parámetros'!$B$6 | E18: =E17+D18 | F18: =MAX(0, MIN('Parámetros'!$B$15-G17, D18*'Parámetros'!$B$16)) | G18: =G17+F18 | H18: =H17+IF(J18>J17,(J18-J17)*('Parámetros'!$B$12*'Parámetros'!$B$23*'Parámetros'!$B$21*'Parámetros'!$B$22*'Parámetros'!$B$24),0) | I18: =E18+G18+H18 | J18: =ENTERO(I18/('Parámetros'!$B$10*(1+'Parámetros'!$B$13)^((15-1)/12))) | K18: =J18*'Parámetros'!$B$12 | L18: =MAX(0,C18-K18) | M18: =K18*('Parámetros'!$B$26*(1+'Parámetros'!$B$27)^((15-1)/12)) | N18: =N17+M18 | O18: =IF(15<='Parámetros'!$B$19,0,G18*'Parámetros'!$B$17/12) | P18: =D18+M18-O18 | Q18: =Q17+P18
A19: 16 | B19: =INT((16-1)/12)+1 | C19: =REDONDEAR(C18*(1-'Parámetros'!$B$7)^(1/12),0) | D19: =C19*'Parámetros'!$B$6 | E19: =E18+D19 | F19: =MAX(0, MIN('Parámetros'!$B$15-G18, D19*'Parámetros'!$B$16)) | G19: =G18+F19 | H19: =H18+IF(J19>J18,(J19-J18)*('Parámetros'!$B$12*'Parámetros'!$B$23*'Parámetros'!$B$21*'Parámetros'!$B$22*'Parámetros'!$B$24),0) | I19: =E19+G19+H19 | J19: =ENTERO(I19/('Parámetros'!$B$10*(1+'Parámetros'!$B$13)^((16-1)/12))) | K19: =J19*'Parámetros'!$B$12 | L19: =MAX(0,C19-K19) | M19: =K19*('Parámetros'!$B$26*(1+'Parámetros'!$B$27)^((16-1)/12)) | N19: =N18+M19 | O19: =IF(16<='Parámetros'!$B$19,0,G19*'Parámetros'!$B$17/12) | P19: =D19+M19-O19 | Q19: =Q18+P19
A20: 17 | B20: =INT((17-1)/12)+1 | C20: =REDONDEAR(C19*(1-'Parámetros'!$B$7)^(1/12),0) | D20: =C20*'Parámetros'!$B$6 | E20: =E19+D20 | F20: =MAX(0, MIN('Parámetros'!$B$15-G19, D20*'Parámetros'!$B$16)) | G20: =G19+F20 | H20: =H19+IF(J20>J19,(J20-J19)*('Parámetros'!$B$12*'Parámetros'!$B$23*'Parámetros'!$B$21*'Parámetros'!$B$22*'Parámetros'!$B$24),0) | I20: =E20+G20+H20 | J20: =ENTERO(I20/('Parámetros'!$B$10*(1+'Parámetros'!$B$13)^((17-1)/12))) | K20: =J20*'Parámetros'!$B$12 | L20: =MAX(0,C20-K20) | M20: =K20*('Parámetros'!$B$26*(1+'Parámetros'!$B$27)^((17-1)/12)) | N20: =N19+M20 | O20: =IF(17<='Parámetros'!$B$19,0,G20*'Parámetros'!$B$17/12) | P20: =D20+M20-O20 | Q20: =Q19+P20
A21: 18 | B21: =INT((18-1)/12)+1 | C21: =REDONDEAR(C20*(1-'Parámetros'!$B$7)^(1/12),0) | D21: =C21*'Parámetros'!$B$6 | E21: =E20+D21 | F21: =MAX(0, MIN('Parámetros'!$B$15-G20, D21*'Parámetros'!$B$16)) | G21: =G20+F21 | H21: =H20+IF(J21>J20,(J21-J20)*('Parámetros'!$B$12*'Parámetros'!$B$23*'Parámetros'!$B$21*'Parámetros'!$B$22*'Parámetros'!$B$24),0) | I21: =E21+G21+H21 | J21: =ENTERO(I21/('Parámetros'!$B$10*(1+'Parámetros'!$B$13)^((18-1)/12))) | K21: =J21*'Parámetros'!$B$12 | L21: =MAX(0,C21-K21) | M21: =K21*('Parámetros'!$B$26*(1+'Parámetros'!$B$27)^((18-1)/12)) | N21: =N20+M21 | O21: =IF(18<='Parámetros'!$B$19,0,G21*'Parámetros'!$B$17/12) | P21: =D21+M21-O21 | Q21: =Q20+P21
A22: 19 | B22: =INT((19-1)/12)+1 | C22: =REDONDEAR(C21*(1-'Parámetros'!$B$7)^(1/12),0) | D22: =C22*'Parámetros'!$B$6 | E22: =E21+D22 | F22: =MAX(0, MIN('Parámetros'!$B$15-G21, D22*'Parámetros'!$B$16)) | G22: =G21+F22 | H22: =H21+IF(J22>J21,(J22-J21)*('Parámetros'!$B$12*'Parámetros'!$B$23*'Parámetros'!$B$21*'Parámetros'!$B$22*'Parámetros'!$B$24),0) | I22: =E22+G22+H22 | J22: =ENTERO(I22/('Parámetros'!$B$10*(1+'Parámetros'!$B$13)^((19-1)/12))) | K22: =J22*'Parámetros'!$B$12 | L22: =MAX(0,C22-K22) | M22: =K22*('Parámetros'!$B$26*(1+'Parámetros'!$B$27)^((19-1)/12)) | N22: =N21+M22 | O22: =IF(19<='Parámetros'!$B$19,0,G22*'Parámetros'!$B$17/12) | P22: =D22+M22-O22 | Q22: =Q21+P22
A23: 20 | B23: =INT((20-1)/12)+1 | C23: =REDONDEAR(C22*(1-'Parámetros'!$B$7)^(1/12),0) | D23: =C23*'Parámetros'!$B$6 | E23: =E22+D23 | F23: =MAX(0, MIN('Parámetros'!$B$15-G22, D23*'Parámetros'!$B$16)) | G23: =G22+F23 | H23: =H22+IF(J23>J22,(J23-J22)*('Parámetros'!$B$12*'Parámetros'!$B$23*'Parámetros'!$B$21*'Parámetros'!$B$22*'Parámetros'!$B$24),0) | I23: =E23+G23+H23 | J23: =ENTERO(I23/('Parámetros'!$B$10*(1+'Parámetros'!$B$13)^((20-1)/12))) | K23: =J23*'Parámetros'!$B$12 | L23: =MAX(0,C23-K23) | M23: =K23*('Parámetros'!$B$26*(1+'Parámetros'!$B$27)^((20-1)/12)) | N23: =N22+M23 | O23: =IF(20<='Parámetros'!$B$19,0,G23*'Parámetros'!$B$17/12) | P23: =D23+M23-O23 | Q23: =Q22+P23
A24: 21 | B24: =INT((21-1)/12)+1 | C24: =REDONDEAR(C23*(1-'Parámetros'!$B$7)^(1/12),0) | D24: =C24*'Parámetros'!$B$6 | E24: =E23+D24 | F24: =MAX(0, MIN('Parámetros'!$B$15-G23, D24*'Parámetros'!$B$16)) | G24: =G23+F24 | H24: =H23+IF(J24>J23,(J24-J23)*('Parámetros'!$B$12*'Parámetros'!$B$23*'Parámetros'!$B$21*'Parámetros'!$B$22*'Parámetros'!$B$24),0) | I24: =E24+G24+H24 | J24: =ENTERO(I24/('Parámetros'!$B$10*(1+'Parámetros'!$B$13)^((21-1)/12))) | K24: =J24*'Parámetros'!$B$12 | L24: =MAX(0,C24-K24) | M24: =K24*('Parámetros'!$B$26*(1+'Parámetros'!$B$27)^((21-1)/12)) | N24: =N23+M24 | O24: =IF(21<='Parámetros'!$B$19,0,G24*'Parámetros'!$B$17/12) | P24: =D24+M24-O24 | Q24: =Q23+P24
A25: 22 | B25: =INT((22-1)/12)+1 | C25: =REDONDEAR(C24*(1-'Parámetros'!$B$7)^(1/12),0) | D25: =C25*'Parámetros'!$B$6 | E25: =E24+D25 | F25: =MAX(0, MIN('Parámetros'!$B$15-G24, D25*'Parámetros'!$B$16)) | G25: =G24+F25 | H25: =H24+IF(J25>J24,(J25-J24)*('Parámetros'!$B$12*'Parámetros'!$B$23*'Parámetros'!$B$21*'Parámetros'!$B$22*'Parámetros'!$B$24),0) | I25: =E25+G25+H25 | J25: =ENTERO(I25/('Parámetros'!$B$10*(1+'Parámetros'!$B$13)^((22-1)/12))) | K25: =J25*'Parámetros'!$B$12 | L25: =MAX(0,C25-K25) | M25: =K25*('Parámetros'!$B$26*(1+'Parámetros'!$B$27)^((22-1)/12)) | N25: =N24+M25 | O25: =IF(22<='Parámetros'!$B$19,0,G25*'Parámetros'!$B$17/12) | P25: =D25+M25-O25 | Q25: =Q24+P25
A26: 23 | B26: =INT((23-1)/12)+1 | C26: =REDONDEAR(C25*(1-'Parámetros'!$B$7)^(1/12),0) | D26: =C26*'Parámetros'!$B$6 | E26: =E25+D26 | F26: =MAX(0, MIN('Parámetros'!$B$15-G25, D26*'Parámetros'!$B$16)) | G26: =G25+F26 | H26: =H25+IF(J26>J25,(J26-J25)*('Parámetros'!$B$12*'Parámetros'!$B$23*'Parámetros'!$B$21*'Parámetros'!$B$22*'Parámetros'!$B$24),0) | I26: =E26+G26+H26 | J26: =ENTERO(I26/('Parámetros'!$B$10*(1+'Parámetros'!$B$13)^((23-1)/12))) | K26: =J26*'Parámetros'!$B$12 | L26: =MAX(0,C26-K26) | M26: =K26*('Parámetros'!$B$26*(1+'Parámetros'!$B$27)^((23-1)/12)) | N26: =N25+M26 | O26: =IF(23<='Parámetros'!$B$19,0,G26*'Parámetros'!$B$17/12) | P26: =D26+M26-O26 | Q26: =Q25+P26
A27: 24 | B27: =INT((24-1)/12)+1 | C27: =REDONDEAR(C26*(1-'Parámetros'!$B$7)^(1/12),0) | D27: =C27*'Parámetros'!$B$6 | E27: =E26+D27 | F27: =MAX(0, MIN('Parámetros'!$B$15-G26, D27*'Parámetros'!$B$16)) | G27: =G26+F27 | H27: =H26+IF(J27>J26,(J27-J26)*('Parámetros'!$B$12*'Parámetros'!$B$23*'Parámetros'!$B$21*'Parámetros'!$B$22*'Parámetros'!$B$24),0) | I27: =E27+G27+H27 | J27: =ENTERO(I27/('Parámetros'!$B$10*(1+'Parámetros'!$B$13)^((24-1)/12))) | K27: =J27*'Parámetros'!$B$12 | L27: =MAX(0,C27-K27) | M27: =K27*('Parámetros'!$B$26*(1+'Parámetros'!$B$27)^((24-1)/12)) | N27: =N26+M27 | O27: =IF(24<='Parámetros'!$B$19,0,G27*'Parámetros'!$B$17/12) | P27: =D27+M27-O27 | Q27: =Q26+P27
A28: 25 | B28: =INT((25-1)/12)+1 | C28: =REDONDEAR(C27*(1-'Parámetros'!$B$7)^(1/12),0) | D28: =C28*'Parámetros'!$B$6 | E28: =E27+D28 | F28: =MAX(0, MIN('Parámetros'!$B$15-G27, D28*'Parámetros'!$B$16)) | G28: =G27+F28 | H28: =H27+IF(J28>J27,(J28-J27)*('Parámetros'!$B$12*'Parámetros'!$B$23*'Parámetros'!$B$21*'Parámetros'!$B$22*'Parámetros'!$B$24),0) | I28: =E28+G28+H28 | J28: =ENTERO(I28/('Parámetros'!$B$10*(1+'Parámetros'!$B$13)^((25-1)/12))) | K28: =J28*'Parámetros'!$B$12 | L28: =MAX(0,C28-K28) | M28: =K28*('Parámetros'!$B$26*(1+'Parámetros'!$B$27)^((25-1)/12)) | N28: =N27+M28 | O28: =IF(25<='Parámetros'!$B$19,0,G28*'Parámetros'!$B$17/12) | P28: =D28+M28-O28 | Q28: =Q27+P28
A29: 26 | B29: =INT((26-1)/12)+1 | C29: =REDONDEAR(C28*(1-'Parámetros'!$B$7)^(1/12),0) | D29: =C29*'Parámetros'!$B$6 | E29: =E28+D29 | F29: =MAX(0, MIN('Parámetros'!$B$15-G28, D29*'Parámetros'!$B$16)) | G29: =G28+F29 | H29: =H28+IF(J29>J28,(J29-J28)*('Parámetros'!$B$12*'Parámetros'!$B$23*'Parámetros'!$B$21*'Parámetros'!$B$22*'Parámetros'!$B$24),0) | I29: =E29+G29+H29 | J29: =ENTERO(I29/('Parámetros'!$B$10*(1+'Parámetros'!$B$13)^((26-1)/12))) | K29: =J29*'Parámetros'!$B$12 | L29: =MAX(0,C29-K29) | M29: =K29*('Parámetros'!$B$26*(1+'Parámetros'!$B$27)^((26-1)/12)) | N29: =N28+M29 | O29: =IF(26<='Parámetros'!$B$19,0,G29*'Parámetros'!$B$17/12) | P29: =D29+M29-O29 | Q29: =Q28+P29
A30: 27 | B30: =INT((27-1)/12)+1 | C30: =REDONDEAR(C29*(1-'Parámetros'!$B$7)^(1/12),0) | D30: =C30*'Parámetros'!$B$6 | E30: =E29+D30 | F30: =MAX(0, MIN('Parámetros'!$B$15-G29, D30*'Parámetros'!$B$16)) | G30: =G29+F30 | H30: =H29+IF(J30>J29,(J30-J29)*('Parámetros'!$B$12*'Parámetros'!$B$23*'Parámetros'!$B$21*'Parámetros'!$B$22*'Parámetros'!$B$24),0) | I30: =E30+G30+H30 | J30: =ENTERO(I30/('Parámetros'!$B$10*(1+'Parámetros'!$B$13)^((27-1)/12))) | K30: =J30*'Parámetros'!$B$12 | L30: =MAX(0,C30-K30) | M30: =K30*('Parámetros'!$B$26*(1+'Parámetros'!$B$27)^((27-1)/12)) | N30: =N29+M30 | O30: =IF(27<='Parámetros'!$B$19,0,G30*'Parámetros'!$B$17/12) | P30: =D30+M30-O30 | Q30: =Q29+P30
A31: 28 | B31: =INT((28-1)/12)+1 | C31: =REDONDEAR(C30*(1-'Parámetros'!$B$7)^(1/12),0) | D31: =C31*'Parámetros'!$B$6 | E31: =E30+D31 | F31: =MAX(0, MIN('Parámetros'!$B$15-G30, D31*'Parámetros'!$B$16)) | G31: =G30+F31 | H31: =H30+IF(J31>J30,(J31-J30)*('Parámetros'!$B$12*'Parámetros'!$B$23*'Parámetros'!$B$21*'Parámetros'!$B$22*'Parámetros'!$B$24),0) | I31: =E31+G31+H31 | J31: =ENTERO(I31/('Parámetros'!$B$10*(1+'Parámetros'!$B$13)^((28-1)/12))) | K31: =J31*'Parámetros'!$B$12 | L31: =MAX(0,C31-K31) | M31: =K31*('Parámetros'!$B$26*(1+'Parámetros'!$B$27)^((28-1)/12)) | N31: =N30+M31 | O31: =IF(28<='Parámetros'!$B$19,0,G31*'Parámetros'!$B$17/12) | P31: =D31+M31-O31 | Q31: =Q30+P31
A32: 29 | B32: =INT((29-1)/12)+1 | C32: =REDONDEAR(C31*(1-'Parámetros'!$B$7)^(1/12),0) | D32: =C32*'Parámetros'!$B$6 | E32: =E31+D32 | F32: =MAX(0, MIN('Parámetros'!$B$15-G31, D32*'Parámetros'!$B$16)) | G32: =G31+F32 | H32: =H31+IF(J32>J31,(J32-J31)*('Parámetros'!$B$12*'Parámetros'!$B$23*'Parámetros'!$B$21*'Parámetros'!$B$22*'Parámetros'!$B$24),0) | I32: =E32+G32+H32 | J32: =ENTERO(I32/('Parámetros'!$B$10*(1+'Parámetros'!$B$13)^((29-1)/12))) | K32: =J32*'Parámetros'!$B$12 | L32: =MAX(0,C32-K32) | M32: =K32*('Parámetros'!$B$26*(1+'Parámetros'!$B$27)^((29-1)/12)) | N32: =N31+M32 | O32: =IF(29<='Parámetros'!$B$19,0,G32*'Parámetros'!$B$17/12) | P32: =D32+M32-O32 | Q32: =Q31+P32
A33: 30 | B33: =INT((30-1)/12)+1 | C33: =REDONDEAR(C32*(1-'Parámetros'!$B$7)^(1/12),0) | D33: =C33*'Parámetros'!$B$6 | E33: =E32+D33 | F33: =MAX(0, MIN('Parámetros'!$B$15-G32, D33*'Parámetros'!$B$16)) | G33: =G32+F33 | H33: =H32+IF(J33>J32,(J33-J32)*('Parámetros'!$B$12*'Parámetros'!$B$23*'Parámetros'!$B$21*'Parámetros'!$B$22*'Parámetros'!$B$24),0) | I33: =E33+G33+H33 | J33: =ENTERO(I33/('Parámetros'!$B$10*(1+'Parámetros'!$B$13)^((30-1)/12))) | K33: =J33*'Parámetros'!$B$12 | L33: =MAX(0,C33-K33) | M33: =K33*('Parámetros'!$B$26*(1+'Parámetros'!$B$27)^((30-1)/12)) | N33: =N32+M33 | O33: =IF(30<='Parámetros'!$B$19,0,G33*'Parámetros'!$B$17/12) | P33: =D33+M33-O33 | Q33: =Q32+P33
A34: 31 | B34: =INT((31-1)/12)+1 | C34: =REDONDEAR(C33*(1-'Parámetros'!$B$7)^(1/12),0) | D34: =C34*'Parámetros'!$B$6 | E34: =E33+D34 | F34: =MAX(0, MIN('Parámetros'!$B$15-G33, D34*'Parámetros'!$B$16)) | G34: =G33+F34 | H34: =H33+IF(J34>J33,(J34-J33)*('Parámetros'!$B$12*'Parámetros'!$B$23*'Parámetros'!$B$21*'Parámetros'!$B$22*'Parámetros'!$B$24),0) | I34: =E34+G34+H34 | J34: =ENTERO(I34/('Parámetros'!$B$10*(1+'Parámetros'!$B$13)^((31-1)/12))) | K34: =J34*'Parámetros'!$B$12 | L34: =MAX(0,C34-K34) | M34: =K34*('Parámetros'!$B$26*(1+'Parámetros'!$B$27)^((31-1)/12)) | N34: =N33+M34 | O34: =IF(31<='Parámetros'!$B$19,0,G34*'Parámetros'!$B$17/12) | P34: =D34+M34-O34 | Q34: =Q33+P34
A35: 32 | B35: =INT((32-1)/12)+1 | C35: =REDONDEAR(C34*(1-'Parámetros'!$B$7)^(1/12),0) | D35: =C35*'Parámetros'!$B$6 | E35: =E34+D35 | F35: =MAX(0, MIN('Parámetros'!$B$15-G34, D35*'Parámetros'!$B$16)) | G35: =G34+F35 | H35: =H34+IF(J35>J34,(J35-J34)*('Parámetros'!$B$12*'Parámetros'!$B$23*'Parámetros'!$B$21*'Parámetros'!$B$22*'Parámetros'!$B$24),0) | I35: =E35+G35+H35 | J35: =ENTERO(I35/('Parámetros'!$B$10*(1+'Parámetros'!$B$13)^((32-1)/12))) | K35: =J35*'Parámetros'!$B$12 | L35: =MAX(0,C35-K35) | M35: =K35*('Parámetros'!$B$26*(1+'Parámetros'!$B$27)^((32-1)/12)) | N35: =N34+M35 | O35: =IF(32<='Parámetros'!$B$19,0,G35*'Parámetros'!$B$17/12) | P35: =D35+M35-O35 | Q35: =Q34+P35
A36: 33 | B36: =INT((33-1)/12)+1 | C36: =REDONDEAR(C35*(1-'Parámetros'!$B$7)^(1/12),0) | D36: =C36*'Parámetros'!$B$6 | E36: =E35+D36 | F36: =MAX(0, MIN('Parámetros'!$B$15-G35, D36*'Parámetros'!$B$16)) | G36: =G35+F36 | H36: =H35+IF(J36>J35,(J36-J35)*('Parámetros'!$B$12*'Parámetros'!$B$23*'Parámetros'!$B$21*'Parámetros'!$B$22*'Parámetros'!$B$24),0) | I36: =E36+G36+H36 | J36: =ENTERO(I36/('Parámetros'!$B$10*(1+'Parámetros'!$B$13)^((33-1)/12))) | K36: =J36*'Parámetros'!$B$12 | L36: =MAX(0,C36-K36) | M36: =K36*('Parámetros'!$B$26*(1+'Parámetros'!$B$27)^((33-1)/12)) | N36: =N35+M36 | O36: =IF(33<='Parámetros'!$B$19,0,G36*'Parámetros'!$B$17/12) | P36: =D36+M36-O36 | Q36: =Q35+P36
A37: 34 | B37: =INT((34-1)/12)+1 | C37: =REDONDEAR(C36*(1-'Parámetros'!$B$7)^(1/12),0) | D37: =C37*'Parámetros'!$B$6 | E37: =E36+D37 | F37: =MAX(0, MIN('Parámetros'!$B$15-G36, D37*'Parámetros'!$B$16)) | G37: =G36+F37 | H37: =H36+IF(J37>J36,(J37-J36)*('Parámetros'!$B$12*'Parámetros'!$B$23*'Parámetros'!$B$21*'Parámetros'!$B$22*'Parámetros'!$B$24),0) | I37: =E37+G37+H37 | J37: =ENTERO(I37/('Parámetros'!$B$10*(1+'Parámetros'!$B$13)^((34-1)/12))) | K37: =J37*'Parámetros'!$B$12 | L37: =MAX(0,C37-K37) | M37: =K37*('Parámetros'!$B$26*(1+'Parámetros'!$B$27)^((34-1)/12)) | N37: =N36+M37 | O37: =IF(34<='Parámetros'!$B$19,0,G37*'Parámetros'!$B$17/12) | P37: =D37+M37-O37 | Q37: =Q36+P37
A38: 35 | B38: =INT((35-1)/12)+1 | C38: =REDONDEAR(C37*(1-'Parámetros'!$B$7)^(1/12),0) | D38: =C38*'Parámetros'!$B$6 | E38: =E37+D38 | F38: =MAX(0, MIN('Parámetros'!$B$15-G37, D38*'Parámetros'!$B$16)) | G38: =G37+F38 | H38: =H37+IF(J38>J37,(J38-J37)*('Parámetros'!$B$12*'Parámetros'!$B$23*'Parámetros'!$B$21*'Parámetros'!$B$22*'Parámetros'!$B$24),0) | I38: =E38+G38+H38 | J38: =ENTERO(I38/('Parámetros'!$B$10*(1+'Parámetros'!$B$13)^((35-1)/12))) | K38: =J38*'Parámetros'!$B$12 | L38: =MAX(0,C38-K38) | M38: =K38*('Parámetros'!$B$26*(1+'Parámetros'!$B$27)^((35-1)/12)) | N38: =N37+M38 | O38: =IF(35<='Parámetros'!$B$19,0,G38*'Parámetros'!$B$17/12) | P38: =D38+M38-O38 | Q38: =Q37+P38
A39: 36 | B39: =INT((36-1)/12)+1 | C39: =REDONDEAR(C38*(1-'Parámetros'!$B$7)^(1/12),0) | D39: =C39*'Parámetros'!$B$6 | E39: =E38+D39 | F39: =MAX(0, MIN('Parámetros'!$B$15-G38, D39*'Parámetros'!$B$16)) | G39: =G38+F39 | H39: =H38+IF(J39>J38,(J39-J38)*('Parámetros'!$B$12*'Parámetros'!$B$23*'Parámetros'!$B$21*'Parámetros'!$B$22*'Parámetros'!$B$24),0) | I39: =E39+G39+H39 | J39: =ENTERO(I39/('Parámetros'!$B$10*(1+'Parámetros'!$B$13)^((36-1)/12))) | K39: =J39*'Parámetros'!$B$12 | L39: =MAX(0,C39-K39) | M39: =K39*('Parámetros'!$B$26*(1+'Parámetros'!$B$27)^((36-1)/12)) | N39: =N38+M39 | O39: =IF(36<='Parámetros'!$B$19,0,G39*'Parámetros'!$B$17/12) | P39: =D39+M39-O39 | Q39: =Q38+P39
A40: 37 | B40: =INT((37-1)/12)+1 | C40: =REDONDEAR(C39*(1-'Parámetros'!$B$7)^(1/12),0) | D40: =C40*'Parámetros'!$B$6 | E40: =E39+D40 | F40: =MAX(0, MIN('Parámetros'!$B$15-G39, D40*'Parámetros'!$B$16)) | G40: =G39+F40 | H40: =H39+IF(J40>J39,(J40-J39)*('Parámetros'!$B$12*'Parámetros'!$B$23*'Parámetros'!$B$21*'Parámetros'!$B$22*'Parámetros'!$B$24),0) | I40: =E40+G40+H40 | J40: =ENTERO(I40/('Parámetros'!$B$10*(1+'Parámetros'!$B$13)^((37-1)/12))) | K40: =J40*'Parámetros'!$B$12 | L40: =MAX(0,C40-K40) | M40: =K40*('Parámetros'!$B$26*(1+'Parámetros'!$B$27)^((37-1)/12)) | N40: =N39+M40 | O40: =IF(37<='Parámetros'!$B$19,0,G40*'Parámetros'!$B$17/12) | P40: =D40+M40-O40 | Q40: =Q39+P40
A41: 38 | B41: =INT((38-1)/12)+1 | C41: =REDONDEAR(C40*(1-'Parámetros'!$B$7)^(1/12),0) | D41: =C41*'Parámetros'!$B$6 | E41: =E40+D41 | F41: =MAX(0, MIN('Parámetros'!$B$15-G40, D41*'Parámetros'!$B$16)) | G41: =G40+F41 | H41: =H40+IF(J41>J40,(J41-J40)*('Parámetros'!$B$12*'Parámetros'!$B$23*'Parámetros'!$B$21*'Parámetros'!$B$22*'Parámetros'!$B$24),0) | I41: =E41+G41+H41 | J41: =ENTERO(I41/('Parámetros'!$B$10*(1+'Parámetros'!$B$13)^((38-1)/12))) | K41: =J41*'Parámetros'!$B$12 | L41: =MAX(0,C41-K41) | M41: =K41*('Parámetros'!$B$26*(1+'Parámetros'!$B$27)^((38-1)/12)) | N41: =N40+M41 | O41: =IF(38<='Parámetros'!$B$19,0,G41*'Parámetros'!$B$17/12) | P41: =D41+M41-O41 | Q41: =Q40+P41
A42: 39 | B42: =INT((39-1)/12)+1 | C42: =REDONDEAR(C41*(1-'Parámetros'!$B$7)^(1/12),0) | D42: =C42*'Parámetros'!$B$6 | E42: =E41+D42 | F42: =MAX(0, MIN('Parámetros'!$B$15-G41, D42*'Parámetros'!$B$16)) | G42: =G41+F42 | H42: =H41+IF(J42>J41,(J42-J41)*('Parámetros'!$B$12*'Parámetros'!$B$23*'Parámetros'!$B$21*'Parámetros'!$B$22*'Parámetros'!$B$24),0) | I42: =E42+G42+H42 | J42: =ENTERO(I42/('Parámetros'!$B$10*(1+'Parámetros'!$B$13)^((39-1)/12))) | K42: =J42*'Parámetros'!$B$12 | L42: =MAX(0,C42-K42) | M42: =K42*('Parámetros'!$B$26*(1+'Parámetros'!$B$27)^((39-1)/12)) | N42: =N41+M42 | O42: =IF(39<='Parámetros'!$B$19,0,G42*'Parámetros'!$B$17/12) | P42: =D42+M42-O42 | Q42: =Q41+P42
A43: 40 | B43: =INT((40-1)/12)+1 | C43: =REDONDEAR(C42*(1-'Parámetros'!$B$7)^(1/12),0) | D43: =C43*'Parámetros'!$B$6 | E43: =E42+D43 | F43: =MAX(0, MIN('Parámetros'!$B$15-G42, D43*'Parámetros'!$B$16)) | G43: =G42+F43 | H43: =H42+IF(J43>J42,(J43-J42)*('Parámetros'!$B$12*'Parámetros'!$B$23*'Parámetros'!$B$21*'Parámetros'!$B$22*'Parámetros'!$B$24),0) | I43: =E43+G43+H43 | J43: =ENTERO(I43/('Parámetros'!$B$10*(1+'Parámetros'!$B$13)^((40-1)/12))) | K43: =J43*'Parámetros'!$B$12 | L43: =MAX(0,C43-K43) | M43: =K43*('Parámetros'!$B$26*(1+'Parámetros'!$B$27)^((40-1)/12)) | N43: =N42+M43 | O43: =IF(40<='Parámetros'!$B$19,0,G43*'Parámetros'!$B$17/12) | P43: =D43+M43-O43 | Q43: =Q42+P43
A44: 41 | B44: =INT((41-1)/12)+1 | C44: =REDONDEAR(C43*(1-'Parámetros'!$B$7)^(1/12),0) | D44: =C44*'Parámetros'!$B$6 | E44: =E43+D44 | F44: =MAX(0, MIN('Parámetros'!$B$15-G43, D44*'Parámetros'!$B$16)) | G44: =G43+F44 | H44: =H43+IF(J44>J43,(J44-J43)*('Parámetros'!$B$12*'Parámetros'!$B$23*'Parámetros'!$B$21*'Parámetros'!$B$22*'Parámetros'!$B$24),0) | I44: =E44+G44+H44 | J44: =ENTERO(I44/('Parámetros'!$B$10*(1+'Parámetros'!$B$13)^((41-1)/12))) | K44: =J44*'Parámetros'!$B$12 | L44: =MAX(0,C44-K44) | M44: =K44*('Parámetros'!$B$26*(1+'Parámetros'!$B$27)^((41-1)/12)) | N44: =N43+M44 | O44: =IF(41<='Parámetros'!$B$19,0,G44*'Parámetros'!$B$17/12) | P44: =D44+M44-O44 | Q44: =Q43+P44
A45: 42 | B45: =INT((42-1)/12)+1 | C45: =REDONDEAR(C44*(1-'Parámetros'!$B$7)^(1/12),0) | D45: =C45*'Parámetros'!$B$6 | E45: =E44+D45 | F45: =MAX(0, MIN('Parámetros'!$B$15-G44, D45*'Parámetros'!$B$16)) | G45: =G44+F45 | H45: =H44+IF(J45>J44,(J45-J44)*('Parámetros'!$B$12*'Parámetros'!$B$23*'Parámetros'!$B$21*'Parámetros'!$B$22*'Parámetros'!$B$24),0) | I45: =E45+G45+H45 | J45: =ENTERO(I45/('Parámetros'!$B$10*(1+'Parámetros'!$B$13)^((42-1)/12))) | K45: =J45*'Parámetros'!$B$12 | L45: =MAX(0,C45-K45) | M45: =K45*('Parámetros'!$B$26*(1+'Parámetros'!$B$27)^((42-1)/12)) | N45: =N44+M45 | O45: =IF(42<='Parámetros'!$B$19,0,G45*'Parámetros'!$B$17/12) | P45: =D45+M45-O45 | Q45: =Q44+P45
A46: 43 | B46: =INT((43-1)/12)+1 | C46: =REDONDEAR(C45*(1-'Parámetros'!$B$7)^(1/12),0) | D46: =C46*'Parámetros'!$B$6 | E46: =E45+D46 | F46: =MAX(0, MIN('Parámetros'!$B$15-G45, D46*'Parámetros'!$B$16)) | G46: =G45+F46 | H46: =H45+IF(J46>J45,(J46-J45)*('Parámetros'!$B$12*'Parámetros'!$B$23*'Parámetros'!$B$21*'Parámetros'!$B$22*'Parámetros'!$B$24),0) | I46: =E46+G46+H46 | J46: =ENTERO(I46/('Parámetros'!$B$10*(1+'Parámetros'!$B$13)^((43-1)/12))) | K46: =J46*'Parámetros'!$B$12 | L46: =MAX(0,C46-K46) | M46: =K46*('Parámetros'!$B$26*(1+'Parámetros'!$B$27)^((43-1)/12)) | N46: =N45+M46 | O46: =IF(43<='Parámetros'!$B$19,0,G46*'Parámetros'!$B$17/12) | P46: =D46+M46-O46 | Q46: =Q45+P46
A47: 44 | B47: =INT((44-1)/12)+1 | C47: =REDONDEAR(C46*(1-'Parámetros'!$B$7)^(1/12),0) | D47: =C47*'Parámetros'!$B$6 | E47: =E46+D47 | F47: =MAX(0, MIN('Parámetros'!$B$15-G46, D47*'Parámetros'!$B$16)) | G47: =G46+F47 | H47: =H46+IF(J47>J46,(J47-J46)*('Parámetros'!$B$12*'Parámetros'!$B$23*'Parámetros'!$B$21*'Parámetros'!$B$22*'Parámetros'!$B$24),0) | I47: =E47+G47+H47 | J47: =ENTERO(I47/('Parámetros'!$B$10*(1+'Parámetros'!$B$13)^((44-1)/12))) | K47: =J47*'Parámetros'!$B$12 | L47: =MAX(0,C47-K47) | M47: =K47*('Parámetros'!$B$26*(1+'Parámetros'!$B$27)^((44-1)/12)) | N47: =N46+M47 | O47: =IF(44<='Parámetros'!$B$19,0,G47*'Parámetros'!$B$17/12) | P47: =D47+M47-O47 | Q47: =Q46+P47
A48: 45 | B48: =INT((45-1)/12)+1 | C48: =REDONDEAR(C47*(1-'Parámetros'!$B$7)^(1/12),0) | D48: =C48*'Parámetros'!$B$6 | E48: =E47+D48 | F48: =MAX(0, MIN('Parámetros'!$B$15-G47, D48*'Parámetros'!$B$16)) | G48: =G47+F48 | H48: =H47+IF(J48>J47,(J48-J47)*('Parámetros'!$B$12*'Parámetros'!$B$23*'Parámetros'!$B$21*'Parámetros'!$B$22*'Parámetros'!$B$24),0) | I48: =E48+G48+H48 | J48: =ENTERO(I48/('Parámetros'!$B$10*(1+'Parámetros'!$B$13)^((45-1)/12))) | K48: =J48*'Parámetros'!$B$12 | L48: =MAX(0,C48-K48) | M48: =K48*('Parámetros'!$B$26*(1+'Parámetros'!$B$27)^((45-1)/12)) | N48: =N47+M48 | O48: =IF(45<='Parámetros'!$B$19,0,G48*'Parámetros'!$B$17/12) | P48: =D48+M48-O48 | Q48: =Q47+P48
A49: 46 | B49: =INT((46-1)/12)+1 | C49: =REDONDEAR(C48*(1-'Parámetros'!$B$7)^(1/12),0) | D49: =C49*'Parámetros'!$B$6 | E49: =E48+D49 | F49: =MAX(0, MIN('Parámetros'!$B$15-G48, D49*'Parámetros'!$B$16)) | G49: =G48+F49 | H49: =H48+IF(J49>J48,(J49-J48)*('Parámetros'!$B$12*'Parámetros'!$B$23*'Parámetros'!$B$21*'Parámetros'!$B$22*'Parámetros'!$B$24),0) | I49: =E49+G49+H49 | J49: =ENTERO(I49/('Parámetros'!$B$10*(1+'Parámetros'!$B$13)^((46-1)/12))) | K49: =J49*'Parámetros'!$B$12 | L49: =MAX(0,C49-K49) | M49: =K49*('Parámetros'!$B$26*(1+'Parámetros'!$B$27)^((46-1)/12)) | N49: =N48+M49 | O49: =IF(46<='Parámetros'!$B$19,0,G49*'Parámetros'!$B$17/12) | P49: =D49+M49-O49 | Q49: =Q48+P49
A50: 47 | B50: =INT((47-1)/12)+1 | C50: =REDONDEAR(C49*(1-'Parámetros'!$B$7)^(1/12),0) | D50: =C50*'Parámetros'!$B$6 | E50: =E49+D50 | F50: =MAX(0, MIN('Parámetros'!$B$15-G49, D50*'Parámetros'!$B$16)) | G50: =G49+F50 | H50: =H49+IF(J50>J49,(J50-J49)*('Parámetros'!$B$12*'Parámetros'!$B$23*'Parámetros'!$B$21*'Parámetros'!$B$22*'Parámetros'!$B$24),0) | I50: =E50+G50+H50 | J50: =ENTERO(I50/('Parámetros'!$B$10*(1+'Parámetros'!$B$13)^((47-1)/12))) | K50: =J50*'Parámetros'!$B$12 | L50: =MAX(0,C50-K50) | M50: =K50*('Parámetros'!$B$26*(1+'Parámetros'!$B$27)^((47-1)/12)) | N50: =N49+M50 | O50: =IF(47<='Parámetros'!$B$19,0,G50*'Parámetros'!$B$17/12) | P50: =D50+M50-O50 | Q50: =Q49+P50
A51: 48 | B51: =INT((48-1)/12)+1 | C51: =REDONDEAR(C50*(1-'Parámetros'!$B$7)^(1/12),0) | D51: =C51*'Parámetros'!$B$6 | E51: =E50+D51 | F51: =MAX(0, MIN('Parámetros'!$B$15-G50, D51*'Parámetros'!$B$16)) | G51: =G50+F51 | H51: =H50+IF(J51>J50,(J51-J50)*('Parámetros'!$B$12*'Parámetros'!$B$23*'Parámetros'!$B$21*'Parámetros'!$B$22*'Parámetros'!$B$24),0) | I51: =E51+G51+H51 | J51: =ENTERO(I51/('Parámetros'!$B$10*(1+'Parámetros'!$B$13)^((48-1)/12))) | K51: =J51*'Parámetros'!$B$12 | L51: =MAX(0,C51-K51) | M51: =K51*('Parámetros'!$B$26*(1+'Parámetros'!$B$27)^((48-1)/12)) | N51: =N50+M51 | O51: =IF(48<='Parámetros'!$B$19,0,G51*'Parámetros'!$B$17/12) | P51: =D51+M51-O51 | Q51: =Q50+P51
A52: 49 | B52: =INT((49-1)/12)+1 | C52: =REDONDEAR(C51*(1-'Parámetros'!$B$7)^(1/12),0) | D52: =C52*'Parámetros'!$B$6 | E52: =E51+D52 | F52: =MAX(0, MIN('Parámetros'!$B$15-G51, D52*'Parámetros'!$B$16)) | G52: =G51+F52 | H52: =H51+IF(J52>J51,(J52-J51)*('Parámetros'!$B$12*'Parámetros'!$B$23*'Parámetros'!$B$21*'Parámetros'!$B$22*'Parámetros'!$B$24),0) | I52: =E52+G52+H52 | J52: =ENTERO(I52/('Parámetros'!$B$10*(1+'Parámetros'!$B$13)^((49-1)/12))) | K52: =J52*'Parámetros'!$B$12 | L52: =MAX(0,C52-K52) | M52: =K52*('Parámetros'!$B$26*(1+'Parámetros'!$B$27)^((49-1)/12)) | N52: =N51+M52 | O52: =IF(49<='Parámetros'!$B$19,0,G52*'Parámetros'!$B$17/12) | P52: =D52+M52-O52 | Q52: =Q51+P52
A53: 50 | B53: =INT((50-1)/12)+1 | C53: =REDONDEAR(C52*(1-'Parámetros'!$B$7)^(1/12),0) | D53: =C53*'Parámetros'!$B$6 | E53: =E52+D53 | F53: =MAX(0, MIN('Parámetros'!$B$15-G52, D53*'Parámetros'!$B$16)) | G53: =G52+F53 | H53: =H52+IF(J53>J52,(J53-J52)*('Parámetros'!$B$12*'Parámetros'!$B$23*'Parámetros'!$B$21*'Parámetros'!$B$22*'Parámetros'!$B$24),0) | I53: =E53+G53+H53 | J53: =ENTERO(I53/('Parámetros'!$B$10*(1+'Parámetros'!$B$13)^((50-1)/12))) | K53: =J53*'Parámetros'!$B$12 | L53: =MAX(0,C53-K53) | M53: =K53*('Parámetros'!$B$26*(1+'Parámetros'!$B$27)^((50-1)/12)) | N53: =N52+M53 | O53: =IF(50<='Parámetros'!$B$19,0,G53*'Parámetros'!$B$17/12) | P53: =D53+M53-O53 | Q53: =Q52+P53
A54: 51 | B54: =INT((51-1)/12)+1 | C54: =REDONDEAR(C53*(1-'Parámetros'!$B$7)^(1/12),0) | D54: =C54*'Parámetros'!$B$6 | E54: =E53+D54 | F54: =MAX(0, MIN('Parámetros'!$B$15-G53, D54*'Parámetros'!$B$16)) | G54: =G53+F54 | H54: =H53+IF(J54>J53,(J54-J53)*('Parámetros'!$B$12*'Parámetros'!$B$23*'Parámetros'!$B$21*'Parámetros'!$B$22*'Parámetros'!$B$24),0) | I54: =E54+G54+H54 | J54: =ENTERO(I54/('Parámetros'!$B$10*(1+'Parámetros'!$B$13)^((51-1)/12))) | K54: =J54*'Parámetros'!$B$12 | L54: =MAX(0,C54-K54) | M54: =K54*('Parámetros'!$B$26*(1+'Parámetros'!$B$27)^((51-1)/12)) | N54: =N53+M54 | O54: =IF(51<='Parámetros'!$B$19,0,G54*'Parámetros'!$B$17/12) | P54: =D54+M54-O54 | Q54: =Q53+P54
A55: 52 | B55: =INT((52-1)/12)+1 | C55: =REDONDEAR(C54*(1-'Parámetros'!$B$7)^(1/12),0) | D55: =C55*'Parámetros'!$B$6 | E55: =E54+D55 | F55: =MAX(0, MIN('Parámetros'!$B$15-G54, D55*'Parámetros'!$B$16)) | G55: =G54+F55 | H55: =H54+IF(J55>J54,(J55-J54)*('Parámetros'!$B$12*'Parámetros'!$B$23*'Parámetros'!$B$21*'Parámetros'!$B$22*'Parámetros'!$B$24),0) | I55: =E55+G55+H55 | J55: =ENTERO(I55/('Parámetros'!$B$10*(1+'Parámetros'!$B$13)^((52-1)/12))) | K55: =J55*'Parámetros'!$B$12 | L55: =MAX(0,C55-K55) | M55: =K55*('Parámetros'!$B$26*(1+'Parámetros'!$B$27)^((52-1)/12)) | N55: =N54+M55 | O55: =IF(52<='Parámetros'!$B$19,0,G55*'Parámetros'!$B$17/12) | P55: =D55+M55-O55 | Q55: =Q54+P55
A56: 53 | B56: =INT((53-1)/12)+1 | C56: =REDONDEAR(C55*(1-'Parámetros'!$B$7)^(1/12),0) | D56: =C56*'Parámetros'!$B$6 | E56: =E55+D56 | F56: =MAX(0, MIN('Parámetros'!$B$15-G55, D56*'Parámetros'!$B$16)) | G56: =G55+F56 | H56: =H55+IF(J56>J55,(J56-J55)*('Parámetros'!$B$12*'Parámetros'!$B$23*'Parámetros'!$B$21*'Parámetros'!$B$22*'Parámetros'!$B$24),0) | I56: =E56+G56+H56 | J56: =ENTERO(I56/('Parámetros'!$B$10*(1+'Parámetros'!$B$13)^((53-1)/12))) | K56: =J56*'Parámetros'!$B$12 | L56: =MAX(0,C56-K56) | M56: =K56*('Parámetros'!$B$26*(1+'Parámetros'!$B$27)^((53-1)/12)) | N56: =N55+M56 | O56: =IF(53<='Parámetros'!$B$19,0,G56*'Parámetros'!$B$17/12) | P56: =D56+M56-O56 | Q56: =Q55+P56
A57: 54 | B57: =INT((54-1)/12)+1 | C57: =REDONDEAR(C56*(1-'Parámetros'!$B$7)^(1/12),0) | D57: =C57*'Parámetros'!$B$6 | E57: =E56+D57 | F57: =MAX(0, MIN('Parámetros'!$B$15-G56, D57*'Parámetros'!$B$16)) | G57: =G56+F57 | H57: =H56+IF(J57>J56,(J57-J56)*('Parámetros'!$B$12*'Parámetros'!$B$23*'Parámetros'!$B$21*'Parámetros'!$B$22*'Parámetros'!$B$24),0) | I57: =E57+G57+H57 | J57: =ENTERO(I57/('Parámetros'!$B$10*(1+'Parámetros'!$B$13)^((54-1)/12))) | K57: =J57*'Parámetros'!$B$12 | L57: =MAX(0,C57-K57) | M57: =K57*('Parámetros'!$B$26*(1+'Parámetros'!$B$27)^((54-1)/12)) | N57: =N56+M57 | O57: =IF(54<='Parámetros'!$B$19,0,G57*'Parámetros'!$B$17/12) | P57: =D57+M57-O57 | Q57: =Q56+P57
A58: 55 | B58: =INT((55-1)/12)+1 | C58: =REDONDEAR(C57*(1-'Parámetros'!$B$7)^(1/12),0) | D58: =C58*'Parámetros'!$B$6 | E58: =E57+D58 | F58: =MAX(0, MIN('Parámetros'!$B$15-G57, D58*'Parámetros'!$B$16)) | G58: =G57+F58 | H58: =H57+IF(J58>J57,(J58-J57)*('Parámetros'!$B$12*'Parámetros'!$B$23*'Parámetros'!$B$21*'Parámetros'!$B$22*'Parámetros'!$B$24),0) | I58: =E58+G58+H58 | J58: =ENTERO(I58/('Parámetros'!$B$10*(1+'Parámetros'!$B$13)^((55-1)/12))) | K58: =J58*'Parámetros'!$B$12 | L58: =MAX(0,C58-K58) | M58: =K58*('Parámetros'!$B$26*(1+'Parámetros'!$B$27)^((55-1)/12)) | N58: =N57+M58 | O58: =IF(55<='Parámetros'!$B$19,0,G58*'Parámetros'!$B$17/12) | P58: =D58+M58-O58 | Q58: =Q57+P58
A59: 56 | B59: =INT((56-1)/12)+1 | C59: =REDONDEAR(C58*(1-'Parámetros'!$B$7)^(1/12),0) | D59: =C59*'Parámetros'!$B$6 | E59: =E58+D59 | F59: =MAX(0, MIN('Parámetros'!$B$15-G58, D59*'Parámetros'!$B$16)) | G59: =G58+F59 | H59: =H58+IF(J59>J58,(J59-J58)*('Parámetros'!$B$12*'Parámetros'!$B$23*'Parámetros'!$B$21*'Parámetros'!$B$22*'Parámetros'!$B$24),0) | I59: =E59+G59+H59 | J59: =ENTERO(I59/('Parámetros'!$B$10*(1+'Parámetros'!$B$13)^((56-1)/12))) | K59: =J59*'Parámetros'!$B$12 | L59: =MAX(0,C59-K59) | M59: =K59*('Parámetros'!$B$26*(1+'Parámetros'!$B$27)^((56-1)/12)) | N59: =N58+M59 | O59: =IF(56<='Parámetros'!$B$19,0,G59*'Parámetros'!$B$17/12) | P59: =D59+M59-O59 | Q59: =Q58+P59
A60: 57 | B60: =INT((57-1)/12)+1 | C60: =REDONDEAR(C59*(1-'Parámetros'!$B$7)^(1/12),0) | D60: =C60*'Parámetros'!$B$6 | E60: =E59+D60 | F60: =MAX(0, MIN('Parámetros'!$B$15-G59, D60*'Parámetros'!$B$16)) | G60: =G59+F60 | H60: =H59+IF(J60>J59,(J60-J59)*('Parámetros'!$B$12*'Parámetros'!$B$23*'Parámetros'!$B$21*'Parámetros'!$B$22*'Parámetros'!$B$24),0) | I60: =E60+G60+H60 | J60: =ENTERO(I60/('Parámetros'!$B$10*(1+'Parámetros'!$B$13)^((57-1)/12))) | K60: =J60*'Parámetros'!$B$12 | L60: =MAX(0,C60-K60) | M60: =K60*('Parámetros'!$B$26*(1+'Parámetros'!$B$27)^((57-1)/12)) | N60: =N59+M60 | O60: =IF(57<='Parámetros'!$B$19,0,G60*'Parámetros'!$B$17/12) | P60: =D60+M60-O60 | Q60: =Q59+P60
A61: 58 | B61: =INT((58-1)/12)+1 | C61: =REDONDEAR(C60*(1-'Parámetros'!$B$7)^(1/12),0) | D61: =C61*'Parámetros'!$B$6 | E61: =E60+D61 | F61: =MAX(0, MIN('Parámetros'!$B$15-G60, D61*'Parámetros'!$B$16)) | G61: =G60+F61 | H61: =H60+IF(J61>J60,(J61-J60)*('Parámetros'!$B$12*'Parámetros'!$B$23*'Parámetros'!$B$21*'Parámetros'!$B$22*'Parámetros'!$B$24),0) | I61: =E61+G61+H61 | J61: =ENTERO(I61/('Parámetros'!$B$10*(1+'Parámetros'!$B$13)^((58-1)/12))) | K61: =J61*'Parámetros'!$B$12 | L61: =MAX(0,C61-K61) | M61: =K61*('Parámetros'!$B$26*(1+'Parámetros'!$B$27)^((58-1)/12)) | N61: =N60+M61 | O61: =IF(58<='Parámetros'!$B$19,0,G61*'Parámetros'!$B$17/12) | P61: =D61+M61-O61 | Q61: =Q60+P61
A62: 59 | B62: =INT((59-1)/12)+1 | C62: =REDONDEAR(C61*(1-'Parámetros'!$B$7)^(1/12),0) | D62: =C62*'Parámetros'!$B$6 | E62: =E61+D62 | F62: =MAX(0, MIN('Parámetros'!$B$15-G61, D62*'Parámetros'!$B$16)) | G62: =G61+F62 | H62: =H61+IF(J62>J61,(J62-J61)*('Parámetros'!$B$12*'Parámetros'!$B$23*'Parámetros'!$B$21*'Parámetros'!$B$22*'Parámetros'!$B$24),0) | I62: =E62+G62+H62 | J62: =ENTERO(I62/('Parámetros'!$B$10*(1+'Parámetros'!$B$13)^((59-1)/12))) | K62: =J62*'Parámetros'!$B$12 | L62: =MAX(0,C62-K62) | M62: =K62*('Parámetros'!$B$26*(1+'Parámetros'!$B$27)^((59-1)/12)) | N62: =N61+M62 | O62: =IF(59<='Parámetros'!$B$19,0,G62*'Parámetros'!$B$17/12) | P62: =D62+M62-O62 | Q62: =Q61+P62
A63: 60 | B63: =INT((60-1)/12)+1 | C63: =REDONDEAR(C62*(1-'Parámetros'!$B$7)^(1/12),0) | D63: =C63*'Parámetros'!$B$6 | E63: =E62+D63 | F63: =MAX(0, MIN('Parámetros'!$B$15-G62, D63*'Parámetros'!$B$16)) | G63: =G62+F63 | H63: =H62+IF(J63>J62,(J63-J62)*('Parámetros'!$B$12*'Parámetros'!$B$23*'Parámetros'!$B$21*'Parámetros'!$B$22*'Parámetros'!$B$24),0) | I63: =E63+G63+H63 | J63: =ENTERO(I63/('Parámetros'!$B$10*(1+'Parámetros'!$B$13)^((60-1)/12))) | K63: =J63*'Parámetros'!$B$12 | L63: =MAX(0,C63-K63) | M63: =K63*('Parámetros'!$B$26*(1+'Parámetros'!$B$27)^((60-1)/12)) | N63: =N62+M63 | O63: =IF(60<='Parámetros'!$B$19,0,G63*'Parámetros'!$B$17/12) | P63: =D63+M63-O63 | Q63: =Q62+P63
A64: 61 | B64: =INT((61-1)/12)+1 | C64: =REDONDEAR(C63*(1-'Parámetros'!$B$7)^(1/12),0) | D64: =C64*'Parámetros'!$B$6 | E64: =E63+D64 | F64: =MAX(0, MIN('Parámetros'!$B$15-G63, D64*'Parámetros'!$B$16)) | G64: =G63+F64 | H64: =H63+IF(J64>J63,(J64-J63)*('Parámetros'!$B$12*'Parámetros'!$B$23*'Parámetros'!$B$21*'Parámetros'!$B$22*'Parámetros'!$B$24),0) | I64: =E64+G64+H64 | J64: =ENTERO(I64/('Parámetros'!$B$10*(1+'Parámetros'!$B$13)^((61-1)/12))) | K64: =J64*'Parámetros'!$B$12 | L64: =MAX(0,C64-K64) | M64: =K64*('Parámetros'!$B$26*(1+'Parámetros'!$B$27)^((61-1)/12)) | N64: =N63+M64 | O64: =IF(61<='Parámetros'!$B$19,0,G64*'Parámetros'!$B$17/12) | P64: =D64+M64-O64 | Q64: =Q63+P64
A65: 62 | B65: =INT((62-1)/12)+1 | C65: =REDONDEAR(C64*(1-'Parámetros'!$B$7)^(1/12),0) | D65: =C65*'Parámetros'!$B$6 | E65: =E64+D65 | F65: =MAX(0, MIN('Parámetros'!$B$15-G64, D65*'Parámetros'!$B$16)) | G65: =G64+F65 | H65: =H64+IF(J65>J64,(J65-J64)*('Parámetros'!$B$12*'Parámetros'!$B$23*'Parámetros'!$B$21*'Parámetros'!$B$22*'Parámetros'!$B$24),0) | I65: =E65+G65+H65 | J65: =ENTERO(I65/('Parámetros'!$B$10*(1+'Parámetros'!$B$13)^((62-1)/12))) | K65: =J65*'Parámetros'!$B$12 | L65: =MAX(0,C65-K65) | M65: =K65*('Parámetros'!$B$26*(1+'Parámetros'!$B$27)^((62-1)/12)) | N65: =N64+M65 | O65: =IF(62<='Parámetros'!$B$19,0,G65*'Parámetros'!$B$17/12) | P65: =D65+M65-O65 | Q65: =Q64+P65
A66: 63 | B66: =INT((63-1)/12)+1 | C66: =REDONDEAR(C65*(1-'Parámetros'!$B$7)^(1/12),0) | D66: =C66*'Parámetros'!$B$6 | E66: =E65+D66 | F66: =MAX(0, MIN('Parámetros'!$B$15-G65, D66*'Parámetros'!$B$16)) | G66: =G65+F66 | H66: =H65+IF(J66>J65,(J66-J65)*('Parámetros'!$B$12*'Parámetros'!$B$23*'Parámetros'!$B$21*'Parámetros'!$B$22*'Parámetros'!$B$24),0) | I66: =E66+G66+H66 | J66: =ENTERO(I66/('Parámetros'!$B$10*(1+'Parámetros'!$B$13)^((63-1)/12))) | K66: =J66*'Parámetros'!$B$12 | L66: =MAX(0,C66-K66) | M66: =K66*('Parámetros'!$B$26*(1+'Parámetros'!$B$27)^((63-1)/12)) | N66: =N65+M66 | O66: =IF(63<='Parámetros'!$B$19,0,G66*'Parámetros'!$B$17/12) | P66: =D66+M66-O66 | Q66: =Q65+P66
A67: 64 | B67: =INT((64-1)/12)+1 | C67: =REDONDEAR(C66*(1-'Parámetros'!$B$7)^(1/12),0) | D67: =C67*'Parámetros'!$B$6 | E67: =E66+D67 | F67: =MAX(0, MIN('Parámetros'!$B$15-G66, D67*'Parámetros'!$B$16)) | G67: =G66+F67 | H67: =H66+IF(J67>J66,(J67-J66)*('Parámetros'!$B$12*'Parámetros'!$B$23*'Parámetros'!$B$21*'Parámetros'!$B$22*'Parámetros'!$B$24),0) | I67: =E67+G67+H67 | J67: =ENTERO(I67/('Parámetros'!$B$10*(1+'Parámetros'!$B$13)^((64-1)/12))) | K67: =J67*'Parámetros'!$B$12 | L67: =MAX(0,C67-K67) | M67: =K67*('Parámetros'!$B$26*(1+'Parámetros'!$B$27)^((64-1)/12)) | N67: =N66+M67 | O67: =IF(64<='Parámetros'!$B$19,0,G67*'Parámetros'!$B$17/12) | P67: =D67+M67-O67 | Q67: =Q66+P67
A68: 65 | B68: =INT((65-1)/12)+1 | C68: =REDONDEAR(C67*(1-'Parámetros'!$B$7)^(1/12),0) | D68: =C68*'Parámetros'!$B$6 | E68: =E67+D68 | F68: =MAX(0, MIN('Parámetros'!$B$15-G67, D68*'Parámetros'!$B$16)) | G68: =G67+F68 | H68: =H67+IF(J68>J67,(J68-J67)*('Parámetros'!$B$12*'Parámetros'!$B$23*'Parámetros'!$B$21*'Parámetros'!$B$22*'Parámetros'!$B$24),0) | I68: =E68+G68+H68 | J68: =ENTERO(I68/('Parámetros'!$B$10*(1+'Parámetros'!$B$13)^((65-1)/12))) | K68: =J68*'Parámetros'!$B$12 | L68: =MAX(0,C68-K68) | M68: =K68*('Parámetros'!$B$26*(1+'Parámetros'!$B$27)^((65-1)/12)) | N68: =N67+M68 | O68: =IF(65<='Parámetros'!$B$19,0,G68*'Parámetros'!$B$17/12) | P68: =D68+M68-O68 | Q68: =Q67+P68
A69: 66 | B69: =INT((66-1)/12)+1 | C69: =REDONDEAR(C68*(1-'Parámetros'!$B$7)^(1/12),0) | D69: =C69*'Parámetros'!$B$6 | E69: =E68+D69 | F69: =MAX(0, MIN('Parámetros'!$B$15-G68, D69*'Parámetros'!$B$16)) | G69: =G68+F69 | H69: =H68+IF(J69>J68,(J69-J68)*('Parámetros'!$B$12*'Parámetros'!$B$23*'Parámetros'!$B$21*'Parámetros'!$B$22*'Parámetros'!$B$24),0) | I69: =E69+G69+H69 | J69: =ENTERO(I69/('Parámetros'!$B$10*(1+'Parámetros'!$B$13)^((66-1)/12))) | K69: =J69*'Parámetros'!$B$12 | L69: =MAX(0,C69-K69) | M69: =K69*('Parámetros'!$B$26*(1+'Parámetros'!$B$27)^((66-1)/12)) | N69: =N68+M69 | O69: =IF(66<='Parámetros'!$B$19,0,G69*'Parámetros'!$B$17/12) | P69: =D69+M69-O69 | Q69: =Q68+P69
A70: 67 | B70: =INT((67-1)/12)+1 | C70: =REDONDEAR(C69*(1-'Parámetros'!$B$7)^(1/12),0) | D70: =C70*'Parámetros'!$B$6 | E70: =E69+D70 | F70: =MAX(0, MIN('Parámetros'!$B$15-G69, D70*'Parámetros'!$B$16)) | G70: =G69+F70 | H70: =H69+IF(J70>J69,(J70-J69)*('Parámetros'!$B$12*'Parámetros'!$B$23*'Parámetros'!$B$21*'Parámetros'!$B$22*'Parámetros'!$B$24),0) | I70: =E70+G70+H70 | J70: =ENTERO(I70/('Parámetros'!$B$10*(1+'Parámetros'!$B$13)^((67-1)/12))) | K70: =J70*'Parámetros'!$B$12 | L70: =MAX(0,C70-K70) | M70: =K70*('Parámetros'!$B$26*(1+'Parámetros'!$B$27)^((67-1)/12)) | N70: =N69+M70 | O70: =IF(67<='Parámetros'!$B$19,0,G70*'Parámetros'!$B$17/12) | P70: =D70+M70-O70 | Q70: =Q69+P70
A71: 68 | B71: =INT((68-1)/12)+1 | C71: =REDONDEAR(C70*(1-'Parámetros'!$B$7)^(1/12),0) | D71: =C71*'Parámetros'!$B$6 | E71: =E70+D71 | F71: =MAX(0, MIN('Parámetros'!$B$15-G70, D71*'Parámetros'!$B$16)) | G71: =G70+F71 | H71: =H70+IF(J71>J70,(J71-J70)*('Parámetros'!$B$12*'Parámetros'!$B$23*'Parámetros'!$B$21*'Parámetros'!$B$22*'Parámetros'!$B$24),0) | I71: =E71+G71+H71 | J71: =ENTERO(I71/('Parámetros'!$B$10*(1+'Parámetros'!$B$13)^((68-1)/12))) | K71: =J71*'Parámetros'!$B$12 | L71: =MAX(0,C71-K71) | M71: =K71*('Parámetros'!$B$26*(1+'Parámetros'!$B$27)^((68-1)/12)) | N71: =N70+M71 | O71: =IF(68<='Parámetros'!$B$19,0,G71*'Parámetros'!$B$17/12) | P71: =D71+M71-O71 | Q71: =Q70+P71
A72: 69 | B72: =INT((69-1)/12)+1 | C72: =REDONDEAR(C71*(1-'Parámetros'!$B$7)^(1/12),0) | D72: =C72*'Parámetros'!$B$6 | E72: =E71+D72 | F72: =MAX(0, MIN('Parámetros'!$B$15-G71, D72*'Parámetros'!$B$16)) | G72: =G71+F72 | H72: =H71+IF(J72>J71,(J72-J71)*('Parámetros'!$B$12*'Parámetros'!$B$23*'Parámetros'!$B$21*'Parámetros'!$B$22*'Parámetros'!$B$24),0) | I72: =E72+G72+H72 | J72: =ENTERO(I72/('Parámetros'!$B$10*(1+'Parámetros'!$B$13)^((69-1)/12))) | K72: =J72*'Parámetros'!$B$12 | L72: =MAX(0,C72-K72) | M72: =K72*('Parámetros'!$B$26*(1+'Parámetros'!$B$27)^((69-1)/12)) | N72: =N71+M72 | O72: =IF(69<='Parámetros'!$B$19,0,G72*'Parámetros'!$B$17/12) | P72: =D72+M72-O72 | Q72: =Q71+P72
A73: 70 | B73: =INT((70-1)/12)+1 | C73: =REDONDEAR(C72*(1-'Parámetros'!$B$7)^(1/12),0) | D73: =C73*'Parámetros'!$B$6 | E73: =E72+D73 | F73: =MAX(0, MIN('Parámetros'!$B$15-G72, D73*'Parámetros'!$B$16)) | G73: =G72+F73 | H73: =H72+IF(J73>J72,(J73-J72)*('Parámetros'!$B$12*'Parámetros'!$B$23*'Parámetros'!$B$21*'Parámetros'!$B$22*'Parámetros'!$B$24),0) | I73: =E73+G73+H73 | J73: =ENTERO(I73/('Parámetros'!$B$10*(1+'Parámetros'!$B$13)^((70-1)/12))) | K73: =J73*'Parámetros'!$B$12 | L73: =MAX(0,C73-K73) | M73: =K73*('Parámetros'!$B$26*(1+'Parámetros'!$B$27)^((70-1)/12)) | N73: =N72+M73 | O73: =IF(70<='Parámetros'!$B$19,0,G73*'Parámetros'!$B$17/12) | P73: =D73+M73-O73 | Q73: =Q72+P73
A74: 71 | B74: =INT((71-1)/12)+1 | C74: =REDONDEAR(C73*(1-'Parámetros'!$B$7)^(1/12),0) | D74: =C74*'Parámetros'!$B$6 | E74: =E73+D74 | F74: =MAX(0, MIN('Parámetros'!$B$15-G73, D74*'Parámetros'!$B$16)) | G74: =G73+F74 | H74: =H73+IF(J74>J73,(J74-J73)*('Parámetros'!$B$12*'Parámetros'!$B$23*'Parámetros'!$B$21*'Parámetros'!$B$22*'Parámetros'!$B$24),0) | I74: =E74+G74+H74 | J74: =ENTERO(I74/('Parámetros'!$B$10*(1+'Parámetros'!$B$13)^((71-1)/12))) | K74: =J74*'Parámetros'!$B$12 | L74: =MAX(0,C74-K74) | M74: =K74*('Parámetros'!$B$26*(1+'Parámetros'!$B$27)^((71-1)/12)) | N74: =N73+M74 | O74: =IF(71<='Parámetros'!$B$19,0,G74*'Parámetros'!$B$17/12) | P74: =D74+M74-O74 | Q74: =Q73+P74
A75: 72 | B75: =INT((72-1)/12)+1 | C75: =REDONDEAR(C74*(1-'Parámetros'!$B$7)^(1/12),0) | D75: =C75*'Parámetros'!$B$6 | E75: =E74+D75 | F75: =MAX(0, MIN('Parámetros'!$B$15-G74, D75*'Parámetros'!$B$16)) | G75: =G74+F75 | H75: =H74+IF(J75>J74,(J75-J74)*('Parámetros'!$B$12*'Parámetros'!$B$23*'Parámetros'!$B$21*'Parámetros'!$B$22*'Parámetros'!$B$24),0) | I75: =E75+G75+H75 | J75: =ENTERO(I75/('Parámetros'!$B$10*(1+'Parámetros'!$B$13)^((72-1)/12))) | K75: =J75*'Parámetros'!$B$12 | L75: =MAX(0,C75-K75) | M75: =K75*('Parámetros'!$B$26*(1+'Parámetros'!$B$27)^((72-1)/12)) | N75: =N74+M75 | O75: =IF(72<='Parámetros'!$B$19,0,G75*'Parámetros'!$B$17/12) | P75: =D75+M75-O75 | Q75: =Q74+P75
A76: 73 | B76: =INT((73-1)/12)+1 | C76: =REDONDEAR(C75*(1-'Parámetros'!$B$7)^(1/12),0) | D76: =C76*'Parámetros'!$B$6 | E76: =E75+D76 | F76: =MAX(0, MIN('Parámetros'!$B$15-G75, D76*'Parámetros'!$B$16)) | G76: =G75+F76 | H76: =H75+IF(J76>J75,(J76-J75)*('Parámetros'!$B$12*'Parámetros'!$B$23*'Parámetros'!$B$21*'Parámetros'!$B$22*'Parámetros'!$B$24),0) | I76: =E76+G76+H76 | J76: =ENTERO(I76/('Parámetros'!$B$10*(1+'Parámetros'!$B$13)^((73-1)/12))) | K76: =J76*'Parámetros'!$B$12 | L76: =MAX(0,C76-K76) | M76: =K76*('Parámetros'!$B$26*(1+'Parámetros'!$B$27)^((73-1)/12)) | N76: =N75+M76 | O76: =IF(73<='Parámetros'!$B$19,0,G76*'Parámetros'!$B$17/12) | P76: =D76+M76-O76 | Q76: =Q75+P76
A77: 74 | B77: =INT((74-1)/12)+1 | C77: =REDONDEAR(C76*(1-'Parámetros'!$B$7)^(1/12),0) | D77: =C77*'Parámetros'!$B$6 | E77: =E76+D77 | F77: =MAX(0, MIN('Parámetros'!$B$15-G76, D77*'Parámetros'!$B$16)) | G77: =G76+F77 | H77: =H76+IF(J77>J76,(J77-J76)*('Parámetros'!$B$12*'Parámetros'!$B$23*'Parámetros'!$B$21*'Parámetros'!$B$22*'Parámetros'!$B$24),0) | I77: =E77+G77+H77 | J77: =ENTERO(I77/('Parámetros'!$B$10*(1+'Parámetros'!$B$13)^((74-1)/12))) | K77: =J77*'Parámetros'!$B$12 | L77: =MAX(0,C77-K77) | M77: =K77*('Parámetros'!$B$26*(1+'Parámetros'!$B$27)^((74-1)/12)) | N77: =N76+M77 | O77: =IF(74<='Parámetros'!$B$19,0,G77*'Parámetros'!$B$17/12) | P77: =D77+M77-O77 | Q77: =Q76+P77
A78: 75 | B78: =INT((75-1)/12)+1 | C78: =REDONDEAR(C77*(1-'Parámetros'!$B$7)^(1/12),0) | D78: =C78*'Parámetros'!$B$6 | E78: =E77+D78 | F78: =MAX(0, MIN('Parámetros'!$B$15-G77, D78*'Parámetros'!$B$16)) | G78: =G77+F78 | H78: =H77+IF(J78>J77,(J78-J77)*('Parámetros'!$B$12*'Parámetros'!$B$23*'Parámetros'!$B$21*'Parámetros'!$B$22*'Parámetros'!$B$24),0) | I78: =E78+G78+H78 | J78: =ENTERO(I78/('Parámetros'!$B$10*(1+'Parámetros'!$B$13)^((75-1)/12))) | K78: =J78*'Parámetros'!$B$12 | L78: =MAX(0,C78-K78) | M78: =K78*('Parámetros'!$B$26*(1+'Parámetros'!$B$27)^((75-1)/12)) | N78: =N77+M78 | O78: =IF(75<='Parámetros'!$B$19,0,G78*'Parámetros'!$B$17/12) | P78: =D78+M78-O78 | Q78: =Q77+P78
A79: 76 | B79: =INT((76-1)/12)+1 | C79: =REDONDEAR(C78*(1-'Parámetros'!$B$7)^(1/12),0) | D79: =C79*'Parámetros'!$B$6 | E79: =E78+D79 | F79: =MAX(0, MIN('Parámetros'!$B$15-G78, D79*'Parámetros'!$B$16)) | G79: =G78+F79 | H79: =H78+IF(J79>J78,(J79-J78)*('Parámetros'!$B$12*'Parámetros'!$B$23*'Parámetros'!$B$21*'Parámetros'!$B$22*'Parámetros'!$B$24),0) | I79: =E79+G79+H79 | J79: =ENTERO(I79/('Parámetros'!$B$10*(1+'Parámetros'!$B$13)^((76-1)/12))) | K79: =J79*'Parámetros'!$B$12 | L79: =MAX(0,C79-K79) | M79: =K79*('Parámetros'!$B$26*(1+'Parámetros'!$B$27)^((76-1)/12)) | N79: =N78+M79 | O79: =IF(76<='Parámetros'!$B$19,0,G79*'Parámetros'!$B$17/12) | P79: =D79+M79-O79 | Q79: =Q78+P79
A80: 77 | B80: =INT((77-1)/12)+1 | C80: =REDONDEAR(C79*(1-'Parámetros'!$B$7)^(1/12),0) | D80: =C80*'Parámetros'!$B$6 | E80: =E79+D80 | F80: =MAX(0, MIN('Parámetros'!$B$15-G79, D80*'Parámetros'!$B$16)) | G80: =G79+F80 | H80: =H79+IF(J80>J79,(J80-J79)*('Parámetros'!$B$12*'Parámetros'!$B$23*'Parámetros'!$B$21*'Parámetros'!$B$22*'Parámetros'!$B$24),0) | I80: =E80+G80+H80 | J80: =ENTERO(I80/('Parámetros'!$B$10*(1+'Parámetros'!$B$13)^((77-1)/12))) | K80: =J80*'Parámetros'!$B$12 | L80: =MAX(0,C80-K80) | M80: =K80*('Parámetros'!$B$26*(1+'Parámetros'!$B$27)^((77-1)/12)) | N80: =N79+M80 | O80: =IF(77<='Parámetros'!$B$19,0,G80*'Parámetros'!$B$17/12) | P80: =D80+M80-O80 | Q80: =Q79+P80
A81: 78 | B81: =INT((78-1)/12)+1 | C81: =REDONDEAR(C80*(1-'Parámetros'!$B$7)^(1/12),0) | D81: =C81*'Parámetros'!$B$6 | E81: =E80+D81 | F81: =MAX(0, MIN('Parámetros'!$B$15-G80, D81*'Parámetros'!$B$16)) | G81: =G80+F81 | H81: =H80+IF(J81>J80,(J81-J80)*('Parámetros'!$B$12*'Parámetros'!$B$23*'Parámetros'!$B$21*'Parámetros'!$B$22*'Parámetros'!$B$24),0) | I81: =E81+G81+H81 | J81: =ENTERO(I81/('Parámetros'!$B$10*(1+'Parámetros'!$B$13)^((78-1)/12))) | K81: =J81*'Parámetros'!$B$12 | L81: =MAX(0,C81-K81) | M81: =K81*('Parámetros'!$B$26*(1+'Parámetros'!$B$27)^((78-1)/12)) | N81: =N80+M81 | O81: =IF(78<='Parámetros'!$B$19,0,G81*'Parámetros'!$B$17/12) | P81: =D81+M81-O81 | Q81: =Q80+P81
A82: 79 | B82: =INT((79-1)/12)+1 | C82: =REDONDEAR(C81*(1-'Parámetros'!$B$7)^(1/12),0) | D82: =C82*'Parámetros'!$B$6 | E82: =E81+D82 | F82: =MAX(0, MIN('Parámetros'!$B$15-G81, D82*'Parámetros'!$B$16)) | G82: =G81+F82 | H82: =H81+IF(J82>J81,(J82-J81)*('Parámetros'!$B$12*'Parámetros'!$B$23*'Parámetros'!$B$21*'Parámetros'!$B$22*'Parámetros'!$B$24),0) | I82: =E82+G82+H82 | J82: =ENTERO(I82/('Parámetros'!$B$10*(1+'Parámetros'!$B$13)^((79-1)/12))) | K82: =J82*'Parámetros'!$B$12 | L82: =MAX(0,C82-K82) | M82: =K82*('Parámetros'!$B$26*(1+'Parámetros'!$B$27)^((79-1)/12)) | N82: =N81+M82 | O82: =IF(79<='Parámetros'!$B$19,0,G82*'Parámetros'!$B$17/12) | P82: =D82+M82-O82 | Q82: =Q81+P82
A83: 80 | B83: =INT((80-1)/12)+1 | C83: =REDONDEAR(C82*(1-'Parámetros'!$B$7)^(1/12),0) | D83: =C83*'Parámetros'!$B$6 | E83: =E82+D83 | F83: =MAX(0, MIN('Parámetros'!$B$15-G82, D83*'Parámetros'!$B$16)) | G83: =G82+F83 | H83: =H82+IF(J83>J82,(J83-J82)*('Parámetros'!$B$12*'Parámetros'!$B$23*'Parámetros'!$B$21*'Parámetros'!$B$22*'Parámetros'!$B$24),0) | I83: =E83+G83+H83 | J83: =ENTERO(I83/('Parámetros'!$B$10*(1+'Parámetros'!$B$13)^((80-1)/12))) | K83: =J83*'Parámetros'!$B$12 | L83: =MAX(0,C83-K83) | M83: =K83*('Parámetros'!$B$26*(1+'Parámetros'!$B$27)^((80-1)/12)) | N83: =N82+M83 | O83: =IF(80<='Parámetros'!$B$19,0,G83*'Parámetros'!$B$17/12) | P83: =D83+M83-O83 | Q83: =Q82+P83
A84: 81 | B84: =INT((81-1)/12)+1 | C84: =REDONDEAR(C83*(1-'Parámetros'!$B$7)^(1/12),0) | D84: =C84*'Parámetros'!$B$6 | E84: =E83+D84 | F84: =MAX(0, MIN('Parámetros'!$B$15-G83, D84*'Parámetros'!$B$16)) | G84: =G83+F84 | H84: =H83+IF(J84>J83,(J84-J83)*('Parámetros'!$B$12*'Parámetros'!$B$23*'Parámetros'!$B$21*'Parámetros'!$B$22*'Parámetros'!$B$24),0) | I84: =E84+G84+H84 | J84: =ENTERO(I84/('Parámetros'!$B$10*(1+'Parámetros'!$B$13)^((81-1)/12))) | K84: =J84*'Parámetros'!$B$12 | L84: =MAX(0,C84-K84) | M84: =K84*('Parámetros'!$B$26*(1+'Parámetros'!$B$27)^((81-1)/12)) | N84: =N83+M84 | O84: =IF(81<='Parámetros'!$B$19,0,G84*'Parámetros'!$B$17/12) | P84: =D84+M84-O84 | Q84: =Q83+P84
A85: 82 | B85: =INT((82-1)/12)+1 | C85: =REDONDEAR(C84*(1-'Parámetros'!$B$7)^(1/12),0) | D85: =C85*'Parámetros'!$B$6 | E85: =E84+D85 | F85: =MAX(0, MIN('Parámetros'!$B$15-G84, D85*'Parámetros'!$B$16)) | G85: =G84+F85 | H85: =H84+IF(J85>J84,(J85-J84)*('Parámetros'!$B$12*'Parámetros'!$B$23*'Parámetros'!$B$21*'Parámetros'!$B$22*'Parámetros'!$B$24),0) | I85: =E85+G85+H85 | J85: =ENTERO(I85/('Parámetros'!$B$10*(1+'Parámetros'!$B$13)^((82-1)/12))) | K85: =J85*'Parámetros'!$B$12 | L85: =MAX(0,C85-K85) | M85: =K85*('Parámetros'!$B$26*(1+'Parámetros'!$B$27)^((82-1)/12)) | N85: =N84+M85 | O85: =IF(82<='Parámetros'!$B$19,0,G85*'Parámetros'!$B$17/12) | P85: =D85+M85-O85 | Q85: =Q84+P85
A86: 83 | B86: =INT((83-1)/12)+1 | C86: =REDONDEAR(C85*(1-'Parámetros'!$B$7)^(1/12),0) | D86: =C86*'Parámetros'!$B$6 | E86: =E85+D86 | F86: =MAX(0, MIN('Parámetros'!$B$15-G85, D86*'Parámetros'!$B$16)) | G86: =G85+F86 | H86: =H85+IF(J86>J85,(J86-J85)*('Parámetros'!$B$12*'Parámetros'!$B$23*'Parámetros'!$B$21*'Parámetros'!$B$22*'Parámetros'!$B$24),0) | I86: =E86+G86+H86 | J86: =ENTERO(I86/('Parámetros'!$B$10*(1+'Parámetros'!$B$13)^((83-1)/12))) | K86: =J86*'Parámetros'!$B$12 | L86: =MAX(0,C86-K86) | M86: =K86*('Parámetros'!$B$26*(1+'Parámetros'!$B$27)^((83-1)/12)) | N86: =N85+M86 | O86: =IF(83<='Parámetros'!$B$19,0,G86*'Parámetros'!$B$17/12) | P86: =D86+M86-O86 | Q86: =Q85+P86
A87: 84 | B87: =INT((84-1)/12)+1 | C87: =REDONDEAR(C86*(1-'Parámetros'!$B$7)^(1/12),0) | D87: =C87*'Parámetros'!$B$6 | E87: =E86+D87 | F87: =MAX(0, MIN('Parámetros'!$B$15-G86, D87*'Parámetros'!$B$16)) | G87: =G86+F87 | H87: =H86+IF(J87>J86,(J87-J86)*('Parámetros'!$B$12*'Parámetros'!$B$23*'Parámetros'!$B$21*'Parámetros'!$B$22*'Parámetros'!$B$24),0) | I87: =E87+G87+H87 | J87: =ENTERO(I87/('Parámetros'!$B$10*(1+'Parámetros'!$B$13)^((84-1)/12))) | K87: =J87*'Parámetros'!$B$12 | L87: =MAX(0,C87-K87) | M87: =K87*('Parámetros'!$B$26*(1+'Parámetros'!$B$27)^((84-1)/12)) | N87: =N86+M87 | O87: =IF(84<='Parámetros'!$B$19,0,G87*'Parámetros'!$B$17/12) | P87: =D87+M87-O87 | Q87: =Q86+P87
A88: 85 | B88: =INT((85-1)/12)+1 | C88: =REDONDEAR(C87*(1-'Parámetros'!$B$7)^(1/12),0) | D88: =C88*'Parámetros'!$B$6 | E88: =E87+D88 | F88: =MAX(0, MIN('Parámetros'!$B$15-G87, D88*'Parámetros'!$B$16)) | G88: =G87+F88 | H88: =H87+IF(J88>J87,(J88-J87)*('Parámetros'!$B$12*'Parámetros'!$B$23*'Parámetros'!$B$21*'Parámetros'!$B$22*'Parámetros'!$B$24),0) | I88: =E88+G88+H88 | J88: =ENTERO(I88/('Parámetros'!$B$10*(1+'Parámetros'!$B$13)^((85-1)/12))) | K88: =J88*'Parámetros'!$B$12 | L88: =MAX(0,C88-K88) | M88: =K88*('Parámetros'!$B$26*(1+'Parámetros'!$B$27)^((85-1)/12)) | N88: =N87+M88 | O88: =IF(85<='Parámetros'!$B$19,0,G88*'Parámetros'!$B$17/12) | P88: =D88+M88-O88 | Q88: =Q87+P88
A89: 86 | B89: =INT((86-1)/12)+1 | C89: =REDONDEAR(C88*(1-'Parámetros'!$B$7)^(1/12),0) | D89: =C89*'Parámetros'!$B$6 | E89: =E88+D89 | F89: =MAX(0, MIN('Parámetros'!$B$15-G88, D89*'Parámetros'!$B$16)) | G89: =G88+F89 | H89: =H88+IF(J89>J88,(J89-J88)*('Parámetros'!$B$12*'Parámetros'!$B$23*'Parámetros'!$B$21*'Parámetros'!$B$22*'Parámetros'!$B$24),0) | I89: =E89+G89+H89 | J89: =ENTERO(I89/('Parámetros'!$B$10*(1+'Parámetros'!$B$13)^((86-1)/12))) | K89: =J89*'Parámetros'!$B$12 | L89: =MAX(0,C89-K89) | M89: =K89*('Parámetros'!$B$26*(1+'Parámetros'!$B$27)^((86-1)/12)) | N89: =N88+M89 | O89: =IF(86<='Parámetros'!$B$19,0,G89*'Parámetros'!$B$17/12) | P89: =D89+M89-O89 | Q89: =Q88+P89
A90: 87 | B90: =INT((87-1)/12)+1 | C90: =REDONDEAR(C89*(1-'Parámetros'!$B$7)^(1/12),0) | D90: =C90*'Parámetros'!$B$6 | E90: =E89+D90 | F90: =MAX(0, MIN('Parámetros'!$B$15-G89, D90*'Parámetros'!$B$16)) | G90: =G89+F90 | H90: =H89+IF(J90>J89,(J90-J89)*('Parámetros'!$B$12*'Parámetros'!$B$23*'Parámetros'!$B$21*'Parámetros'!$B$22*'Parámetros'!$B$24),0) | I90: =E90+G90+H90 | J90: =ENTERO(I90/('Parámetros'!$B$10*(1+'Parámetros'!$B$13)^((87-1)/12))) | K90: =J90*'Parámetros'!$B$12 | L90: =MAX(0,C90-K90) | M90: =K90*('Parámetros'!$B$26*(1+'Parámetros'!$B$27)^((87-1)/12)) | N90: =N89+M90 | O90: =IF(87<='Parámetros'!$B$19,0,G90*'Parámetros'!$B$17/12) | P90: =D90+M90-O90 | Q90: =Q89+P90
A91: 88 | B91: =INT((88-1)/12)+1 | C91: =REDONDEAR(C90*(1-'Parámetros'!$B$7)^(1/12),0) | D91: =C91*'Parámetros'!$B$6 | E91: =E90+D91 | F91: =MAX(0, MIN('Parámetros'!$B$15-G90, D91*'Parámetros'!$B$16)) | G91: =G90+F91 | H91: =H90+IF(J91>J90,(J91-J90)*('Parámetros'!$B$12*'Parámetros'!$B$23*'Parámetros'!$B$21*'Parámetros'!$B$22*'Parámetros'!$B$24),0) | I91: =E91+G91+H91 | J91: =ENTERO(I91/('Parámetros'!$B$10*(1+'Parámetros'!$B$13)^((88-1)/12))) | K91: =J91*'Parámetros'!$B$12 | L91: =MAX(0,C91-K91) | M91: =K91*('Parámetros'!$B$26*(1+'Parámetros'!$B$27)^((88-1)/12)) | N91: =N90+M91 | O91: =IF(88<='Parámetros'!$B$19,0,G91*'Parámetros'!$B$17/12) | P91: =D91+M91-O91 | Q91: =Q90+P91
A92: 89 | B92: =INT((89-1)/12)+1 | C92: =REDONDEAR(C91*(1-'Parámetros'!$B$7)^(1/12),0) | D92: =C92*'Parámetros'!$B$6 | E92: =E91+D92 | F92: =MAX(0, MIN('Parámetros'!$B$15-G91, D92*'Parámetros'!$B$16)) | G92: =G91+F92 | H92: =H91+IF(J92>J91,(J92-J91)*('Parámetros'!$B$12*'Parámetros'!$B$23*'Parámetros'!$B$21*'Parámetros'!$B$22*'Parámetros'!$B$24),0) | I92: =E92+G92+H92 | J92: =ENTERO(I92/('Parámetros'!$B$10*(1+'Parámetros'!$B$13)^((89-1)/12))) | K92: =J92*'Parámetros'!$B$12 | L92: =MAX(0,C92-K92) | M92: =K92*('Parámetros'!$B$26*(1+'Parámetros'!$B$27)^((89-1)/12)) | N92: =N91+M92 | O92: =IF(89<='Parámetros'!$B$19,0,G92*'Parámetros'!$B$17/12) | P92: =D92+M92-O92 | Q92: =Q91+P92
A93: 90 | B93: =INT((90-1)/12)+1 | C93: =REDONDEAR(C92*(1-'Parámetros'!$B$7)^(1/12),0) | D93: =C93*'Parámetros'!$B$6 | E93: =E92+D93 | F93: =MAX(0, MIN('Parámetros'!$B$15-G92, D93*'Parámetros'!$B$16)) | G93: =G92+F93 | H93: =H92+IF(J93>J92,(J93-J92)*('Parámetros'!$B$12*'Parámetros'!$B$23*'Parámetros'!$B$21*'Parámetros'!$B$22*'Parámetros'!$B$24),0) | I93: =E93+G93+H93 | J93: =ENTERO(I93/('Parámetros'!$B$10*(1+'Parámetros'!$B$13)^((90-1)/12))) | K93: =J93*'Parámetros'!$B$12 | L93: =MAX(0,C93-K93) | M93: =K93*('Parámetros'!$B$26*(1+'Parámetros'!$B$27)^((90-1)/12)) | N93: =N92+M93 | O93: =IF(90<='Parámetros'!$B$19,0,G93*'Parámetros'!$B$17/12) | P93: =D93+M93-O93 | Q93: =Q92+P93
A94: 91 | B94: =INT((91-1)/12)+1 | C94: =REDONDEAR(C93*(1-'Parámetros'!$B$7)^(1/12),0) | D94: =C94*'Parámetros'!$B$6 | E94: =E93+D94 | F94: =MAX(0, MIN('Parámetros'!$B$15-G93, D94*'Parámetros'!$B$16)) | G94: =G93+F94 | H94: =H93+IF(J94>J93,(J94-J93)*('Parámetros'!$B$12*'Parámetros'!$B$23*'Parámetros'!$B$21*'Parámetros'!$B$22*'Parámetros'!$B$24),0) | I94: =E94+G94+H94 | J94: =ENTERO(I94/('Parámetros'!$B$10*(1+'Parámetros'!$B$13)^((91-1)/12))) | K94: =J94*'Parámetros'!$B$12 | L94: =MAX(0,C94-K94) | M94: =K94*('Parámetros'!$B$26*(1+'Parámetros'!$B$27)^((91-1)/12)) | N94: =N93+M94 | O94: =IF(91<='Parámetros'!$B$19,0,G94*'Parámetros'!$B$17/12) | P94: =D94+M94-O94 | Q94: =Q93+P94
A95: 92 | B95: =INT((92-1)/12)+1 | C95: =REDONDEAR(C94*(1-'Parámetros'!$B$7)^(1/12),0) | D95: =C95*'Parámetros'!$B$6 | E95: =E94+D95 | F95: =MAX(0, MIN('Parámetros'!$B$15-G94, D95*'Parámetros'!$B$16)) | G95: =G94+F95 | H95: =H94+IF(J95>J94,(J95-J94)*('Parámetros'!$B$12*'Parámetros'!$B$23*'Parámetros'!$B$21*'Parámetros'!$B$22*'Parámetros'!$B$24),0) | I95: =E95+G95+H95 | J95: =ENTERO(I95/('Parámetros'!$B$10*(1+'Parámetros'!$B$13)^((92-1)/12))) | K95: =J95*'Parámetros'!$B$12 | L95: =MAX(0,C95-K95) | M95: =K95*('Parámetros'!$B$26*(1+'Parámetros'!$B$27)^((92-1)/12)) | N95: =N94+M95 | O95: =IF(92<='Parámetros'!$B$19,0,G95*'Parámetros'!$B$17/12) | P95: =D95+M95-O95 | Q95: =Q94+P95
A96: 93 | B96: =INT((93-1)/12)+1 | C96: =REDONDEAR(C95*(1-'Parámetros'!$B$7)^(1/12),0) | D96: =C96*'Parámetros'!$B$6 | E96: =E95+D96 | F96: =MAX(0, MIN('Parámetros'!$B$15-G95, D96*'Parámetros'!$B$16)) | G96: =G95+F96 | H96: =H95+IF(J96>J95,(J96-J95)*('Parámetros'!$B$12*'Parámetros'!$B$23*'Parámetros'!$B$21*'Parámetros'!$B$22*'Parámetros'!$B$24),0) | I96: =E96+G96+H96 | J96: =ENTERO(I96/('Parámetros'!$B$10*(1+'Parámetros'!$B$13)^((93-1)/12))) | K96: =J96*'Parámetros'!$B$12 | L96: =MAX(0,C96-K96) | M96: =K96*('Parámetros'!$B$26*(1+'Parámetros'!$B$27)^((93-1)/12)) | N96: =N95+M96 | O96: =IF(93<='Parámetros'!$B$19,0,G96*'Parámetros'!$B$17/12) | P96: =D96+M96-O96 | Q96: =Q95+P96
A97: 94 | B97: =INT((94-1)/12)+1 | C97: =REDONDEAR(C96*(1-'Parámetros'!$B$7)^(1/12),0) | D97: =C97*'Parámetros'!$B$6 | E97: =E96+D97 | F97: =MAX(0, MIN('Parámetros'!$B$15-G96, D97*'Parámetros'!$B$16)) | G97: =G96+F97 | H97: =H96+IF(J97>J96,(J97-J96)*('Parámetros'!$B$12*'Parámetros'!$B$23*'Parámetros'!$B$21*'Parámetros'!$B$22*'Parámetros'!$B$24),0) | I97: =E97+G97+H97 | J97: =ENTERO(I97/('Parámetros'!$B$10*(1+'Parámetros'!$B$13)^((94-1)/12))) | K97: =J97*'Parámetros'!$B$12 | L97: =MAX(0,C97-K97) | M97: =K97*('Parámetros'!$B$26*(1+'Parámetros'!$B$27)^((94-1)/12)) | N97: =N96+M97 | O97: =IF(94<='Parámetros'!$B$19,0,G97*'Parámetros'!$B$17/12) | P97: =D97+M97-O97 | Q97: =Q96+P97
A98: 95 | B98: =INT((95-1)/12)+1 | C98: =REDONDEAR(C97*(1-'Parámetros'!$B$7)^(1/12),0) | D98: =C98*'Parámetros'!$B$6 | E98: =E97+D98 | F98: =MAX(0, MIN('Parámetros'!$B$15-G97, D98*'Parámetros'!$B$16)) | G98: =G97+F98 | H98: =H97+IF(J98>J97,(J98-J97)*('Parámetros'!$B$12*'Parámetros'!$B$23*'Parámetros'!$B$21*'Parámetros'!$B$22*'Parámetros'!$B$24),0) | I98: =E98+G98+H98 | J98: =ENTERO(I98/('Parámetros'!$B$10*(1+'Parámetros'!$B$13)^((95-1)/12))) | K98: =J98*'Parámetros'!$B$12 | L98: =MAX(0,C98-K98) | M98: =K98*('Parámetros'!$B$26*(1+'Parámetros'!$B$27)^((95-1)/12)) | N98: =N97+M98 | O98: =IF(95<='Parámetros'!$B$19,0,G98*'Parámetros'!$B$17/12) | P98: =D98+M98-O98 | Q98: =Q97+P98
A99: 96 | B99: =INT((96-1)/12)+1 | C99: =REDONDEAR(C98*(1-'Parámetros'!$B$7)^(1/12),0) | D99: =C99*'Parámetros'!$B$6 | E99: =E98+D99 | F99: =MAX(0, MIN('Parámetros'!$B$15-G98, D99*'Parámetros'!$B$16)) | G99: =G98+F99 | H99: =H98+IF(J99>J98,(J99-J98)*('Parámetros'!$B$12*'Parámetros'!$B$23*'Parámetros'!$B$21*'Parámetros'!$B$22*'Parámetros'!$B$24),0) | I99: =E99+G99+H99 | J99: =ENTERO(I99/('Parámetros'!$B$10*(1+'Parámetros'!$B$13)^((96-1)/12))) | K99: =J99*'Parámetros'!$B$12 | L99: =MAX(0,C99-K99) | M99: =K99*('Parámetros'!$B$26*(1+'Parámetros'!$B$27)^((96-1)/12)) | N99: =N98+M99 | O99: =IF(96<='Parámetros'!$B$19,0,G99*'Parámetros'!$B$17/12) | P99: =D99+M99-O99 | Q99: =Q98+P99
A100: 97 | B100: =INT((97-1)/12)+1 | C100: =REDONDEAR(C99*(1-'Parámetros'!$B$7)^(1/12),0) | D100: =C100*'Parámetros'!$B$6 | E100: =E99+D100 | F100: =MAX(0, MIN('Parámetros'!$B$15-G99, D100*'Parámetros'!$B$16)) | G100: =G99+F100 | H100: =H99+IF(J100>J99,(J100-J99)*('Parámetros'!$B$12*'Parámetros'!$B$23*'Parámetros'!$B$21*'Parámetros'!$B$22*'Parámetros'!$B$24),0) | I100: =E100+G100+H100 | J100: =ENTERO(I100/('Parámetros'!$B$10*(1+'Parámetros'!$B$13)^((97-1)/12))) | K100: =J100*'Parámetros'!$B$12 | L100: =MAX(0,C100-K100) | M100: =K100*('Parámetros'!$B$26*(1+'Parámetros'!$B$27)^((97-1)/12)) | N100: =N99+M100 | O100: =IF(97<='Parámetros'!$B$19,0,G100*'Parámetros'!$B$17/12) | P100: =D100+M100-O100 | Q100: =Q99+P100
...

Sheet Análisis de Sensibilidad
A1: ANÁLISIS DE SENSIBILIDAD — Tablas Bidimensionales
A2: Nota: Las tablas de sensibilidad muestran cálculos directos basados en las fórmulas del modelo. Cambiar los parámetros en la hoja 'Parámetros' actualiza todos los resultados.
A4: TABLA 1 — Terrenos Adquiridos a 5 Años (mes 60)
A5: Familias \ Cuota | B5: 20000 | C5: 25000 | D5: 30000 | E5: 35000 | F5: 40000
A6: 100 | B6: =LET(des_mes,(1-'Parámetros'!$B$7)^(1/12),acum_c1,20000*100*(1-des_mes^60)/(1-des_mes),acum_c2,MIN('Parámetros'!$B$15,acum_c1*'Parámetros'!$B$16),sub_por_t,'Parámetros'!$B$12*'Parámetros'!$B$23*'Parámetros'!$B$21*'Parámetros'!$B$22*'Parámetros'!$B$24,cap_total,acum_c1+acum_c2,precio_adj,'Parámetros'!$B$10*(1+'Parámetros'!$B$13)^(60/12),terrenos_aprox,MAX(0,ENTERO(cap_total/precio_adj)),ENTERO((cap_total+terrenos_aprox*sub_por_t)/precio_adj)) | C6: =LET(des_mes,(1-'Parámetros'!$B$7)^(1/12),acum_c1,25000*100*(1-des_mes^60)/(1-des_mes),acum_c2,MIN('Parámetros'!$B$15,acum_c1*'Parámetros'!$B$16),sub_por_t,'Parámetros'!$B$12*'Parámetros'!$B$23*'Parámetros'!$B$21*'Parámetros'!$B$22*'Parámetros'!$B$24,cap_total,acum_c1+acum_c2,precio_adj,'Parámetros'!$B$10*(1+'Parámetros'!$B$13)^(60/12),terrenos_aprox,MAX(0,ENTERO(cap_total/precio_adj)),ENTERO((cap_total+terrenos_aprox*sub_por_t)/precio_adj)) | D6: =LET(des_mes,(1-'Parámetros'!$B$7)^(1/12),acum_c1,30000*100*(1-des_mes^60)/(1-des_mes),acum_c2,MIN('Parámetros'!$B$15,acum_c1*'Parámetros'!$B$16),sub_por_t,'Parámetros'!$B$12*'Parámetros'!$B$23*'Parámetros'!$B$21*'Parámetros'!$B$22*'Parámetros'!$B$24,cap_total,acum_c1+acum_c2,precio_adj,'Parámetros'!$B$10*(1+'Parámetros'!$B$13)^(60/12),terrenos_aprox,MAX(0,ENTERO(cap_total/precio_adj)),ENTERO((cap_total+terrenos_aprox*sub_por_t)/precio_adj)) | E6: =LET(des_mes,(1-'Parámetros'!$B$7)^(1/12),acum_c1,35000*100*(1-des_mes^60)/(1-des_mes),acum_c2,MIN('Parámetros'!$B$15,acum_c1*'Parámetros'!$B$16),sub_por_t,'Parámetros'!$B$12*'Parámetros'!$B$23*'Parámetros'!$B$21*'Parámetros'!$B$22*'Parámetros'!$B$24,cap_total,acum_c1+acum_c2,precio_adj,'Parámetros'!$B$10*(1+'Parámetros'!$B$13)^(60/12),terrenos_aprox,MAX(0,ENTERO(cap_total/precio_adj)),ENTERO((cap_total+terrenos_aprox*sub_por_t)/precio_adj)) | F6: =LET(des_mes,(1-'Parámetros'!$B$7)^(1/12),acum_c1,40000*100*(1-des_mes^60)/(1-des_mes),acum_c2,MIN('Parámetros'!$B$15,acum_c1*'Parámetros'!$B$16),sub_por_t,'Parámetros'!$B$12*'Parámetros'!$B$23*'Parámetros'!$B$21*'Parámetros'!$B$22*'Parámetros'!$B$24,cap_total,acum_c1+acum_c2,precio_adj,'Parámetros'!$B$10*(1+'Parámetros'!$B$13)^(60/12),terrenos_aprox,MAX(0,ENTERO(cap_total/precio_adj)),ENTERO((cap_total+terrenos_aprox*sub_por_t)/precio_adj))
A7: 200 | B7: =LET(des_mes,(1-'Parámetros'!$B$7)^(1/12),acum_c1,20000*200*(1-des_mes^60)/(1-des_mes),acum_c2,MIN('Parámetros'!$B$15,acum_c1*'Parámetros'!$B$16),sub_por_t,'Parámetros'!$B$12*'Parámetros'!$B$23*'Parámetros'!$B$21*'Parámetros'!$B$22*'Parámetros'!$B$24,cap_total,acum_c1+acum_c2,precio_adj,'Parámetros'!$B$10*(1+'Parámetros'!$B$13)^(60/12),terrenos_aprox,MAX(0,ENTERO(cap_total/precio_adj)),ENTERO((cap_total+terrenos_aprox*sub_por_t)/precio_adj)) | C7: =LET(des_mes,(1-'Parámetros'!$B$7)^(1/12),acum_c1,25000*200*(1-des_mes^60)/(1-des_mes),acum_c2,MIN('Parámetros'!$B$15,acum_c1*'Parámetros'!$B$16),sub_por_t,'Parámetros'!$B$12*'Parámetros'!$B$23*'Parámetros'!$B$21*'Parámetros'!$B$22*'Parámetros'!$B$24,cap_total,acum_c1+acum_c2,precio_adj,'Parámetros'!$B$10*(1+'Parámetros'!$B$13)^(60/12),terrenos_aprox,MAX(0,ENTERO(cap_total/precio_adj)),ENTERO((cap_total+terrenos_aprox*sub_por_t)/precio_adj)) | D7: =LET(des_mes,(1-'Parámetros'!$B$7)^(1/12),acum_c1,30000*200*(1-des_mes^60)/(1-des_mes),acum_c2,MIN('Parámetros'!$B$15,acum_c1*'Parámetros'!$B$16),sub_por_t,'Parámetros'!$B$12*'Parámetros'!$B$23*'Parámetros'!$B$21*'Parámetros'!$B$22*'Parámetros'!$B$24,cap_total,acum_c1+acum_c2,precio_adj,'Parámetros'!$B$10*(1+'Parámetros'!$B$13)^(60/12),terrenos_aprox,MAX(0,ENTERO(cap_total/precio_adj)),ENTERO((cap_total+terrenos_aprox*sub_por_t)/precio_adj)) | E7: =LET(des_mes,(1-'Parámetros'!$B$7)^(1/12),acum_c1,35000*200*(1-des_mes^60)/(1-des_mes),acum_c2,MIN('Parámetros'!$B$15,acum_c1*'Parámetros'!$B$16),sub_por_t,'Parámetros'!$B$12*'Parámetros'!$B$23*'Parámetros'!$B$21*'Parámetros'!$B$22*'Parámetros'!$B$24,cap_total,acum_c1+acum_c2,precio_adj,'Parámetros'!$B$10*(1+'Parámetros'!$B$13)^(60/12),terrenos_aprox,MAX(0,ENTERO(cap_total/precio_adj)),ENTERO((cap_total+terrenos_aprox*sub_por_t)/precio_adj)) | F7: =LET(des_mes,(1-'Parámetros'!$B$7)^(1/12),acum_c1,40000*200*(1-des_mes^60)/(1-des_mes),acum_c2,MIN('Parámetros'!$B$15,acum_c1*'Parámetros'!$B$16),sub_por_t,'Parámetros'!$B$12*'Parámetros'!$B$23*'Parámetros'!$B$21*'Parámetros'!$B$22*'Parámetros'!$B$24,cap_total,acum_c1+acum_c2,precio_adj,'Parámetros'!$B$10*(1+'Parámetros'!$B$13)^(60/12),terrenos_aprox,MAX(0,ENTERO(cap_total/precio_adj)),ENTERO((cap_total+terrenos_aprox*sub_por_t)/precio_adj))
A8: 300 | B8: =LET(des_mes,(1-'Parámetros'!$B$7)^(1/12),acum_c1,20000*300*(1-des_mes^60)/(1-des_mes),acum_c2,MIN('Parámetros'!$B$15,acum_c1*'Parámetros'!$B$16),sub_por_t,'Parámetros'!$B$12*'Parámetros'!$B$23*'Parámetros'!$B$21*'Parámetros'!$B$22*'Parámetros'!$B$24,cap_total,acum_c1+acum_c2,precio_adj,'Parámetros'!$B$10*(1+'Parámetros'!$B$13)^(60/12),terrenos_aprox,MAX(0,ENTERO(cap_total/precio_adj)),ENTERO((cap_total+terrenos_aprox*sub_por_t)/precio_adj)) | C8: =LET(des_mes,(1-'Parámetros'!$B$7)^(1/12),acum_c1,25000*300*(1-des_mes^60)/(1-des_mes),acum_c2,MIN('Parámetros'!$B$15,acum_c1*'Parámetros'!$B$16),sub_por_t,'Parámetros'!$B$12*'Parámetros'!$B$23*'Parámetros'!$B$21*'Parámetros'!$B$22*'Parámetros'!$B$24,cap_total,acum_c1+acum_c2,precio_adj,'Parámetros'!$B$10*(1+'Parámetros'!$B$13)^(60/12),terrenos_aprox,MAX(0,ENTERO(cap_total/precio_adj)),ENTERO((cap_total+terrenos_aprox*sub_por_t)/precio_adj)) | D8: =LET(des_mes,(1-'Parámetros'!$B$7)^(1/12),acum_c1,30000*300*(1-des_mes^60)/(1-des_mes),acum_c2,MIN('Parámetros'!$B$15,acum_c1*'Parámetros'!$B$16),sub_por_t,'Parámetros'!$B$12*'Parámetros'!$B$23*'Parámetros'!$B$21*'Parámetros'!$B$22*'Parámetros'!$B$24,cap_total,acum_c1+acum_c2,precio_adj,'Parámetros'!$B$10*(1+'Parámetros'!$B$13)^(60/12),terrenos_aprox,MAX(0,ENTERO(cap_total/precio_adj)),ENTERO((cap_total+terrenos_aprox*sub_por_t)/precio_adj)) | E8: =LET(des_mes,(1-'Parámetros'!$B$7)^(1/12),acum_c1,35000*300*(1-des_mes^60)/(1-des_mes),acum_c2,MIN('Parámetros'!$B$15,acum_c1*'Parámetros'!$B$16),sub_por_t,'Parámetros'!$B$12*'Parámetros'!$B$23*'Parámetros'!$B$21*'Parámetros'!$B$22*'Parámetros'!$B$24,cap_total,acum_c1+acum_c2,precio_adj,'Parámetros'!$B$10*(1+'Parámetros'!$B$13)^(60/12),terrenos_aprox,MAX(0,ENTERO(cap_total/precio_adj)),ENTERO((cap_total+terrenos_aprox*sub_por_t)/precio_adj)) | F8: =LET(des_mes,(1-'Parámetros'!$B$7)^(1/12),acum_c1,40000*300*(1-des_mes^60)/(1-des_mes),acum_c2,MIN('Parámetros'!$B$15,acum_c1*'Parámetros'!$B$16),sub_por_t,'Parámetros'!$B$12*'Parámetros'!$B$23*'Parámetros'!$B$21*'Parámetros'!$B$22*'Parámetros'!$B$24,cap_total,acum_c1+acum_c2,precio_adj,'Parámetros'!$B$10*(1+'Parámetros'!$B$13)^(60/12),terrenos_aprox,MAX(0,ENTERO(cap_total/precio_adj)),ENTERO((cap_total+terrenos_aprox*sub_por_t)/precio_adj))
A9: 500 | B9: =LET(des_mes,(1-'Parámetros'!$B$7)^(1/12),acum_c1,20000*500*(1-des_mes^60)/(1-des_mes),acum_c2,MIN('Parámetros'!$B$15,acum_c1*'Parámetros'!$B$16),sub_por_t,'Parámetros'!$B$12*'Parámetros'!$B$23*'Parámetros'!$B$21*'Parámetros'!$B$22*'Parámetros'!$B$24,cap_total,acum_c1+acum_c2,precio_adj,'Parámetros'!$B$10*(1+'Parámetros'!$B$13)^(60/12),terrenos_aprox,MAX(0,ENTERO(cap_total/precio_adj)),ENTERO((cap_total+terrenos_aprox*sub_por_t)/precio_adj)) | C9: =LET(des_mes,(1-'Parámetros'!$B$7)^(1/12),acum_c1,25000*500*(1-des_mes^60)/(1-des_mes),acum_c2,MIN('Parámetros'!$B$15,acum_c1*'Parámetros'!$B$16),sub_por_t,'Parámetros'!$B$12*'Parámetros'!$B$23*'Parámetros'!$B$21*'Parámetros'!$B$22*'Parámetros'!$B$24,cap_total,acum_c1+acum_c2,precio_adj,'Parámetros'!$B$10*(1+'Parámetros'!$B$13)^(60/12),terrenos_aprox,MAX(0,ENTERO(cap_total/precio_adj)),ENTERO((cap_total+terrenos_aprox*sub_por_t)/precio_adj)) | D9: =LET(des_mes,(1-'Parámetros'!$B$7)^(1/12),acum_c1,30000*500*(1-des_mes^60)/(1-des_mes),acum_c2,MIN('Parámetros'!$B$15,acum_c1*'Parámetros'!$B$16),sub_por_t,'Parámetros'!$B$12*'Parámetros'!$B$23*'Parámetros'!$B$21*'Parámetros'!$B$22*'Parámetros'!$B$24,cap_total,acum_c1+acum_c2,precio_adj,'Parámetros'!$B$10*(1+'Parámetros'!$B$13)^(60/12),terrenos_aprox,MAX(0,ENTERO(cap_total/precio_adj)),ENTERO((cap_total+terrenos_aprox*sub_por_t)/precio_adj)) | E9: =LET(des_mes,(1-'Parámetros'!$B$7)^(1/12),acum_c1,35000*500*(1-des_mes^60)/(1-des_mes),acum_c2,MIN('Parámetros'!$B$15,acum_c1*'Parámetros'!$B$16),sub_por_t,'Parámetros'!$B$12*'Parámetros'!$B$23*'Parámetros'!$B$21*'Parámetros'!$B$22*'Parámetros'!$B$24,cap_total,acum_c1+acum_c2,precio_adj,'Parámetros'!$B$10*(1+'Parámetros'!$B$13)^(60/12),terrenos_aprox,MAX(0,ENTERO(cap_total/precio_adj)),ENTERO((cap_total+terrenos_aprox*sub_por_t)/precio_adj)) | F9: =LET(des_mes,(1-'Parámetros'!$B$7)^(1/12),acum_c1,40000*500*(1-des_mes^60)/(1-des_mes),acum_c2,MIN('Parámetros'!$B$15,acum_c1*'Parámetros'!$B$16),sub_por_t,'Parámetros'!$B$12*'Parámetros'!$B$23*'Parámetros'!$B$21*'Parámetros'!$B$22*'Parámetros'!$B$24,cap_total,acum_c1+acum_c2,precio_adj,'Parámetros'!$B$10*(1+'Parámetros'!$B$13)^(60/12),terrenos_aprox,MAX(0,ENTERO(cap_total/precio_adj)),ENTERO((cap_total+terrenos_aprox*sub_por_t)/precio_adj))
A10: 1000 | B10: =LET(des_mes,(1-'Parámetros'!$B$7)^(1/12),acum_c1,20000*1000*(1-des_mes^60)/(1-des_mes),acum_c2,MIN('Parámetros'!$B$15,acum_c1*'Parámetros'!$B$16),sub_por_t,'Parámetros'!$B$12*'Parámetros'!$B$23*'Parámetros'!$B$21*'Parámetros'!$B$22*'Parámetros'!$B$24,cap_total,acum_c1+acum_c2,precio_adj,'Parámetros'!$B$10*(1+'Parámetros'!$B$13)^(60/12),terrenos_aprox,MAX(0,ENTERO(cap_total/precio_adj)),ENTERO((cap_total+terrenos_aprox*sub_por_t)/precio_adj)) | C10: =LET(des_mes,(1-'Parámetros'!$B$7)^(1/12),acum_c1,25000*1000*(1-des_mes^60)/(1-des_mes),acum_c2,MIN('Parámetros'!$B$15,acum_c1*'Parámetros'!$B$16),sub_por_t,'Parámetros'!$B$12*'Parámetros'!$B$23*'Parámetros'!$B$21*'Parámetros'!$B$22*'Parámetros'!$B$24,cap_total,acum_c1+acum_c2,precio_adj,'Parámetros'!$B$10*(1+'Parámetros'!$B$13)^(60/12),terrenos_aprox,MAX(0,ENTERO(cap_total/precio_adj)),ENTERO((cap_total+terrenos_aprox*sub_por_t)/precio_adj)) | D10: =LET(des_mes,(1-'Parámetros'!$B$7)^(1/12),acum_c1,30000*1000*(1-des_mes^60)/(1-des_mes),acum_c2,MIN('Parámetros'!$B$15,acum_c1*'Parámetros'!$B$16),sub_por_t,'Parámetros'!$B$12*'Parámetros'!$B$23*'Parámetros'!$B$21*'Parámetros'!$B$22*'Parámetros'!$B$24,cap_total,acum_c1+acum_c2,precio_adj,'Parámetros'!$B$10*(1+'Parámetros'!$B$13)^(60/12),terrenos_aprox,MAX(0,ENTERO(cap_total/precio_adj)),ENTERO((cap_total+terrenos_aprox*sub_por_t)/precio_adj)) | E10: =LET(des_mes,(1-'Parámetros'!$B$7)^(1/12),acum_c1,35000*1000*(1-des_mes^60)/(1-des_mes),acum_c2,MIN('Parámetros'!$B$15,acum_c1*'Parámetros'!$B$16),sub_por_t,'Parámetros'!$B$12*'Parámetros'!$B$23*'Parámetros'!$B$21*'Parámetros'!$B$22*'Parámetros'!$B$24,cap_total,acum_c1+acum_c2,precio_adj,'Parámetros'!$B$10*(1+'Parámetros'!$B$13)^(60/12),terrenos_aprox,MAX(0,ENTERO(cap_total/precio_adj)),ENTERO((cap_total+terrenos_aprox*sub_por_t)/precio_adj)) | F10: =LET(des_mes,(1-'Parámetros'!$B$7)^(1/12),acum_c1,40000*1000*(1-des_mes^60)/(1-des_mes),acum_c2,MIN('Parámetros'!$B$15,acum_c1*'Parámetros'!$B$16),sub_por_t,'Parámetros'!$B$12*'Parámetros'!$B$23*'Parámetros'!$B$21*'Parámetros'!$B$22*'Parámetros'!$B$24,cap_total,acum_c1+acum_c2,precio_adj,'Parámetros'!$B$10*(1+'Parámetros'!$B$13)^(60/12),terrenos_aprox,MAX(0,ENTERO(cap_total/precio_adj)),ENTERO((cap_total+terrenos_aprox*sub_por_t)/precio_adj))
A13: TABLA 2 — Ratio Cobertura Deuda Capa 2 a 15 Años (Canon / Servicio Deuda)
A14: Ret.C2 \ Canon | B14: 15000 | C14: 20000 | D14: 25000 | E14: 30000 | F14: 35000
A15: 0.03 | B15: =LET(des_mes,(1-'Parámetros'!$B$7)^(1/12),acum_c1,'Parámetros'!$B$6*'Parámetros'!$B$5*(1-des_mes^180)/(1-des_mes),acum_c2,MIN('Parámetros'!$B$15,acum_c1*'Parámetros'!$B$16),sub_por_t,'Parámetros'!$B$12*'Parámetros'!$B$23*'Parámetros'!$B$21*'Parámetros'!$B$22*'Parámetros'!$B$24,cap_total,acum_c1+acum_c2,precio_adj,'Parámetros'!$B$10*(1+'Parámetros'!$B$13)^(180/12),terrenos,MAX(0,ENTERO(cap_total/precio_adj)),fam_ubic,terrenos*'Parámetros'!$B$12,canon_anual,fam_ubic*15000*(1+'Parámetros'!$B$27)^(180/12)*12,serv_deuda,acum_c2*0.03,IF(serv_deuda=0,999,REDONDEAR(canon_anual/serv_deuda,2))) | C15: =LET(des_mes,(1-'Parámetros'!$B$7)^(1/12),acum_c1,'Parámetros'!$B$6*'Parámetros'!$B$5*(1-des_mes^180)/(1-des_mes),acum_c2,MIN('Parámetros'!$B$15,acum_c1*'Parámetros'!$B$16),sub_por_t,'Parámetros'!$B$12*'Parámetros'!$B$23*'Parámetros'!$B$21*'Parámetros'!$B$22*'Parámetros'!$B$24,cap_total,acum_c1+acum_c2,precio_adj,'Parámetros'!$B$10*(1+'Parámetros'!$B$13)^(180/12),terrenos,MAX(0,ENTERO(cap_total/precio_adj)),fam_ubic,terrenos*'Parámetros'!$B$12,canon_anual,fam_ubic*20000*(1+'Parámetros'!$B$27)^(180/12)*12,serv_deuda,acum_c2*0.03,IF(serv_deuda=0,999,REDONDEAR(canon_anual/serv_deuda,2))) | D15: =LET(des_mes,(1-'Parámetros'!$B$7)^(1/12),acum_c1,'Parámetros'!$B$6*'Parámetros'!$B$5*(1-des_mes^180)/(1-des_mes),acum_c2,MIN('Parámetros'!$B$15,acum_c1*'Parámetros'!$B$16),sub_por_t,'Parámetros'!$B$12*'Parámetros'!$B$23*'Parámetros'!$B$21*'Parámetros'!$B$22*'Parámetros'!$B$24,cap_total,acum_c1+acum_c2,precio_adj,'Parámetros'!$B$10*(1+'Parámetros'!$B$13)^(180/12),terrenos,MAX(0,ENTERO(cap_total/precio_adj)),fam_ubic,terrenos*'Parámetros'!$B$12,canon_anual,fam_ubic*25000*(1+'Parámetros'!$B$27)^(180/12)*12,serv_deuda,acum_c2*0.03,IF(serv_deuda=0,999,REDONDEAR(canon_anual/serv_deuda,2))) | E15: =LET(des_mes,(1-'Parámetros'!$B$7)^(1/12),acum_c1,'Parámetros'!$B$6*'Parámetros'!$B$5*(1-des_mes^180)/(1-des_mes),acum_c2,MIN('Parámetros'!$B$15,acum_c1*'Parámetros'!$B$16),sub_por_t,'Parámetros'!$B$12*'Parámetros'!$B$23*'Parámetros'!$B$21*'Parámetros'!$B$22*'Parámetros'!$B$24,cap_total,acum_c1+acum_c2,precio_adj,'Parámetros'!$B$10*(1+'Parámetros'!$B$13)^(180/12),terrenos,MAX(0,ENTERO(cap_total/precio_adj)),fam_ubic,terrenos*'Parámetros'!$B$12,canon_anual,fam_ubic*30000*(1+'Parámetros'!$B$27)^(180/12)*12,serv_deuda,acum_c2*0.03,IF(serv_deuda=0,999,REDONDEAR(canon_anual/serv_deuda,2))) | F15: =LET(des_mes,(1-'Parámetros'!$B$7)^(1/12),acum_c1,'Parámetros'!$B$6*'Parámetros'!$B$5*(1-des_mes^180)/(1-des_mes),acum_c2,MIN('Parámetros'!$B$15,acum_c1*'Parámetros'!$B$16),sub_por_t,'Parámetros'!$B$12*'Parámetros'!$B$23*'Parámetros'!$B$21*'Parámetros'!$B$22*'Parámetros'!$B$24,cap_total,acum_c1+acum_c2,precio_adj,'Parámetros'!$B$10*(1+'Parámetros'!$B$13)^(180/12),terrenos,MAX(0,ENTERO(cap_total/precio_adj)),fam_ubic,terrenos*'Parámetros'!$B$12,canon_anual,fam_ubic*35000*(1+'Parámetros'!$B$27)^(180/12)*12,serv_deuda,acum_c2*0.03,IF(serv_deuda=0,999,REDONDEAR(canon_anual/serv_deuda,2)))
A16: 0.04 | B16: =LET(des_mes,(1-'Parámetros'!$B$7)^(1/12),acum_c1,'Parámetros'!$B$6*'Parámetros'!$B$5*(1-des_mes^180)/(1-des_mes),acum_c2,MIN('Parámetros'!$B$15,acum_c1*'Parámetros'!$B$16),sub_por_t,'Parámetros'!$B$12*'Parámetros'!$B$23*'Parámetros'!$B$21*'Parámetros'!$B$22*'Parámetros'!$B$24,cap_total,acum_c1+acum_c2,precio_adj,'Parámetros'!$B$10*(1+'Parámetros'!$B$13)^(180/12),terrenos,MAX(0,ENTERO(cap_total/precio_adj)),fam_ubic,terrenos*'Parámetros'!$B$12,canon_anual,fam_ubic*15000*(1+'Parámetros'!$B$27)^(180/12)*12,serv_deuda,acum_c2*0.04,IF(serv_deuda=0,999,REDONDEAR(canon_anual/serv_deuda,2))) | C16: =LET(des_mes,(1-'Parámetros'!$B$7)^(1/12),acum_c1,'Parámetros'!$B$6*'Parámetros'!$B$5*(1-des_mes^180)/(1-des_mes),acum_c2,MIN('Parámetros'!$B$15,acum_c1*'Parámetros'!$B$16),sub_por_t,'Parámetros'!$B$12*'Parámetros'!$B$23*'Parámetros'!$B$21*'Parámetros'!$B$22*'Parámetros'!$B$24,cap_total,acum_c1+acum_c2,precio_adj,'Parámetros'!$B$10*(1+'Parámetros'!$B$13)^(180/12),terrenos,MAX(0,ENTERO(cap_total/precio_adj)),fam_ubic,terrenos*'Parámetros'!$B$12,canon_anual,fam_ubic*20000*(1+'Parámetros'!$B$27)^(180/12)*12,serv_deuda,acum_c2*0.04,IF(serv_deuda=0,999,REDONDEAR(canon_anual/serv_deuda,2))) | D16: =LET(des_mes,(1-'Parámetros'!$B$7)^(1/12),acum_c1,'Parámetros'!$B$6*'Parámetros'!$B$5*(1-des_mes^180)/(1-des_mes),acum_c2,MIN('Parámetros'!$B$15,acum_c1*'Parámetros'!$B$16),sub_por_t,'Parámetros'!$B$12*'Parámetros'!$B$23*'Parámetros'!$B$21*'Parámetros'!$B$22*'Parámetros'!$B$24,cap_total,acum_c1+acum_c2,precio_adj,'Parámetros'!$B$10*(1+'Parámetros'!$B$13)^(180/12),terrenos,MAX(0,ENTERO(cap_total/precio_adj)),fam_ubic,terrenos*'Parámetros'!$B$12,canon_anual,fam_ubic*25000*(1+'Parámetros'!$B$27)^(180/12)*12,serv_deuda,acum_c2*0.04,IF(serv_deuda=0,999,REDONDEAR(canon_anual/serv_deuda,2))) | E16: =LET(des_mes,(1-'Parámetros'!$B$7)^(1/12),acum_c1,'Parámetros'!$B$6*'Parámetros'!$B$5*(1-des_mes^180)/(1-des_mes),acum_c2,MIN('Parámetros'!$B$15,acum_c1*'Parámetros'!$B$16),sub_por_t,'Parámetros'!$B$12*'Parámetros'!$B$23*'Parámetros'!$B$21*'Parámetros'!$B$22*'Parámetros'!$B$24,cap_total,acum_c1+acum_c2,precio_adj,'Parámetros'!$B$10*(1+'Parámetros'!$B$13)^(180/12),terrenos,MAX(0,ENTERO(cap_total/precio_adj)),fam_ubic,terrenos*'Parámetros'!$B$12,canon_anual,fam_ubic*30000*(1+'Parámetros'!$B$27)^(180/12)*12,serv_deuda,acum_c2*0.04,IF(serv_deuda=0,999,REDONDEAR(canon_anual/serv_deuda,2))) | F16: =LET(des_mes,(1-'Parámetros'!$B$7)^(1/12),acum_c1,'Parámetros'!$B$6*'Parámetros'!$B$5*(1-des_mes^180)/(1-des_mes),acum_c2,MIN('Parámetros'!$B$15,acum_c1*'Parámetros'!$B$16),sub_por_t,'Parámetros'!$B$12*'Parámetros'!$B$23*'Parámetros'!$B$21*'Parámetros'!$B$22*'Parámetros'!$B$24,cap_total,acum_c1+acum_c2,precio_adj,'Parámetros'!$B$10*(1+'Parámetros'!$B$13)^(180/12),terrenos,MAX(0,ENTERO(cap_total/precio_adj)),fam_ubic,terrenos*'Parámetros'!$B$12,canon_anual,fam_ubic*35000*(1+'Parámetros'!$B$27)^(180/12)*12,serv_deuda,acum_c2*0.04,IF(serv_deuda=0,999,REDONDEAR(canon_anual/serv_deuda,2)))
A17: 0.05 | B17: =LET(des_mes,(1-'Parámetros'!$B$7)^(1/12),acum_c1,'Parámetros'!$B$6*'Parámetros'!$B$5*(1-des_mes^180)/(1-des_mes),acum_c2,MIN('Parámetros'!$B$15,acum_c1*'Parámetros'!$B$16),sub_por_t,'Parámetros'!$B$12*'Parámetros'!$B$23*'Parámetros'!$B$21*'Parámetros'!$B$22*'Parámetros'!$B$24,cap_total,acum_c1+acum_c2,precio_adj,'Parámetros'!$B$10*(1+'Parámetros'!$B$13)^(180/12),terrenos,MAX(0,ENTERO(cap_total/precio_adj)),fam_ubic,terrenos*'Parámetros'!$B$12,canon_anual,fam_ubic*15000*(1+'Parámetros'!$B$27)^(180/12)*12,serv_deuda,acum_c2*0.05,IF(serv_deuda=0,999,REDONDEAR(canon_anual/serv_deuda,2))) | C17: =LET(des_mes,(1-'Parámetros'!$B$7)^(1/12),acum_c1,'Parámetros'!$B$6*'Parámetros'!$B$5*(1-des_mes^180)/(1-des_mes),acum_c2,MIN('Parámetros'!$B$15,acum_c1*'Parámetros'!$B$16),sub_por_t,'Parámetros'!$B$12*'Parámetros'!$B$23*'Parámetros'!$B$21*'Parámetros'!$B$22*'Parámetros'!$B$24,cap_total,acum_c1+acum_c2,precio_adj,'Parámetros'!$B$10*(1+'Parámetros'!$B$13)^(180/12),terrenos,MAX(0,ENTERO(cap_total/precio_adj)),fam_ubic,terrenos*'Parámetros'!$B$12,canon_anual,fam_ubic*20000*(1+'Parámetros'!$B$27)^(180/12)*12,serv_deuda,acum_c2*0.05,IF(serv_deuda=0,999,REDONDEAR(canon_anual/serv_deuda,2))) | D17: =LET(des_mes,(1-'Parámetros'!$B$7)^(1/12),acum_c1,'Parámetros'!$B$6*'Parámetros'!$B$5*(1-des_mes^180)/(1-des_mes),acum_c2,MIN('Parámetros'!$B$15,acum_c1*'Parámetros'!$B$16),sub_por_t,'Parámetros'!$B$12*'Parámetros'!$B$23*'Parámetros'!$B$21*'Parámetros'!$B$22*'Parámetros'!$B$24,cap_total,acum_c1+acum_c2,precio_adj,'Parámetros'!$B$10*(1+'Parámetros'!$B$13)^(180/12),terrenos,MAX(0,ENTERO(cap_total/precio_adj)),fam_ubic,terrenos*'Parámetros'!$B$12,canon_anual,fam_ubic*25000*(1+'Parámetros'!$B$27)^(180/12)*12,serv_deuda,acum_c2*0.05,IF(serv_deuda=0,999,REDONDEAR(canon_anual/serv_deuda,2))) | E17: =LET(des_mes,(1-'Parámetros'!$B$7)^(1/12),acum_c1,'Parámetros'!$B$6*'Parámetros'!$B$5*(1-des_mes^180)/(1-des_mes),acum_c2,MIN('Parámetros'!$B$15,acum_c1*'Parámetros'!$B$16),sub_por_t,'Parámetros'!$B$12*'Parámetros'!$B$23*'Parámetros'!$B$21*'Parámetros'!$B$22*'Parámetros'!$B$24,cap_total,acum_c1+acum_c2,precio_adj,'Parámetros'!$B$10*(1+'Parámetros'!$B$13)^(180/12),terrenos,MAX(0,ENTERO(cap_total/precio_adj)),fam_ubic,terrenos*'Parámetros'!$B$12,canon_anual,fam_ubic*30000*(1+'Parámetros'!$B$27)^(180/12)*12,serv_deuda,acum_c2*0.05,IF(serv_deuda=0,999,REDONDEAR(canon_anual/serv_deuda,2))) | F17: =LET(des_mes,(1-'Parámetros'!$B$7)^(1/12),acum_c1,'Parámetros'!$B$6*'Parámetros'!$B$5*(1-des_mes^180)/(1-des_mes),acum_c2,MIN('Parámetros'!$B$15,acum_c1*'Parámetros'!$B$16),sub_por_t,'Parámetros'!$B$12*'Parámetros'!$B$23*'Parámetros'!$B$21*'Parámetros'!$B$22*'Parámetros'!$B$24,cap_total,acum_c1+acum_c2,precio_adj,'Parámetros'!$B$10*(1+'Parámetros'!$B$13)^(180/12),terrenos,MAX(0,ENTERO(cap_total/precio_adj)),fam_ubic,terrenos*'Parámetros'!$B$12,canon_anual,fam_ubic*35000*(1+'Parámetros'!$B$27)^(180/12)*12,serv_deuda,acum_c2*0.05,IF(serv_deuda=0,999,REDONDEAR(canon_anual/serv_deuda,2)))
A18: 0.06 | B18: =LET(des_mes,(1-'Parámetros'!$B$7)^(1/12),acum_c1,'Parámetros'!$B$6*'Parámetros'!$B$5*(1-des_mes^180)/(1-des_mes),acum_c2,MIN('Parámetros'!$B$15,acum_c1*'Parámetros'!$B$16),sub_por_t,'Parámetros'!$B$12*'Parámetros'!$B$23*'Parámetros'!$B$21*'Parámetros'!$B$22*'Parámetros'!$B$24,cap_total,acum_c1+acum_c2,precio_adj,'Parámetros'!$B$10*(1+'Parámetros'!$B$13)^(180/12),terrenos,MAX(0,ENTERO(cap_total/precio_adj)),fam_ubic,terrenos*'Parámetros'!$B$12,canon_anual,fam_ubic*15000*(1+'Parámetros'!$B$27)^(180/12)*12,serv_deuda,acum_c2*0.06,IF(serv_deuda=0,999,REDONDEAR(canon_anual/serv_deuda,2))) | C18: =LET(des_mes,(1-'Parámetros'!$B$7)^(1/12),acum_c1,'Parámetros'!$B$6*'Parámetros'!$B$5*(1-des_mes^180)/(1-des_mes),acum_c2,MIN('Parámetros'!$B$15,acum_c1*'Parámetros'!$B$16),sub_por_t,'Parámetros'!$B$12*'Parámetros'!$B$23*'Parámetros'!$B$21*'Parámetros'!$B$22*'Parámetros'!$B$24,cap_total,acum_c1+acum_c2,precio_adj,'Parámetros'!$B$10*(1+'Parámetros'!$B$13)^(180/12),terrenos,MAX(0,ENTERO(cap_total/precio_adj)),fam_ubic,terrenos*'Parámetros'!$B$12,canon_anual,fam_ubic*20000*(1+'Parámetros'!$B$27)^(180/12)*12,serv_deuda,acum_c2*0.06,IF(serv_deuda=0,999,REDONDEAR(canon_anual/serv_deuda,2))) | D18: =LET(des_mes,(1-'Parámetros'!$B$7)^(1/12),acum_c1,'Parámetros'!$B$6*'Parámetros'!$B$5*(1-des_mes^180)/(1-des_mes),acum_c2,MIN('Parámetros'!$B$15,acum_c1*'Parámetros'!$B$16),sub_por_t,'Parámetros'!$B$12*'Parámetros'!$B$23*'Parámetros'!$B$21*'Parámetros'!$B$22*'Parámetros'!$B$24,cap_total,acum_c1+acum_c2,precio_adj,'Parámetros'!$B$10*(1+'Parámetros'!$B$13)^(180/12),terrenos,MAX(0,ENTERO(cap_total/precio_adj)),fam_ubic,terrenos*'Parámetros'!$B$12,canon_anual,fam_ubic*25000*(1+'Parámetros'!$B$27)^(180/12)*12,serv_deuda,acum_c2*0.06,IF(serv_deuda=0,999,REDONDEAR(canon_anual/serv_deuda,2))) | E18: =LET(des_mes,(1-'Parámetros'!$B$7)^(1/12),acum_c1,'Parámetros'!$B$6*'Parámetros'!$B$5*(1-des_mes^180)/(1-des_mes),acum_c2,MIN('Parámetros'!$B$15,acum_c1*'Parámetros'!$B$16),sub_por_t,'Parámetros'!$B$12*'Parámetros'!$B$23*'Parámetros'!$B$21*'Parámetros'!$B$22*'Parámetros'!$B$24,cap_total,acum_c1+acum_c2,precio_adj,'Parámetros'!$B$10*(1+'Parámetros'!$B$13)^(180/12),terrenos,MAX(0,ENTERO(cap_total/precio_adj)),fam_ubic,terrenos*'Parámetros'!$B$12,canon_anual,fam_ubic*30000*(1+'Parámetros'!$B$27)^(180/12)*12,serv_deuda,acum_c2*0.06,IF(serv_deuda=0,999,REDONDEAR(canon_anual/serv_deuda,2))) | F18: =LET(des_mes,(1-'Parámetros'!$B$7)^(1/12),acum_c1,'Parámetros'!$B$6*'Parámetros'!$B$5*(1-des_mes^180)/(1-des_mes),acum_c2,MIN('Parámetros'!$B$15,acum_c1*'Parámetros'!$B$16),sub_por_t,'Parámetros'!$B$12*'Parámetros'!$B$23*'Parámetros'!$B$21*'Parámetros'!$B$22*'Parámetros'!$B$24,cap_total,acum_c1+acum_c2,precio_adj,'Parámetros'!$B$10*(1+'Parámetros'!$B$13)^(180/12),terrenos,MAX(0,ENTERO(cap_total/precio_adj)),fam_ubic,terrenos*'Parámetros'!$B$12,canon_anual,fam_ubic*35000*(1+'Parámetros'!$B$27)^(180/12)*12,serv_deuda,acum_c2*0.06,IF(serv_deuda=0,999,REDONDEAR(canon_anual/serv_deuda,2)))
A19: 0.07 | B19: =LET(des_mes,(1-'Parámetros'!$B$7)^(1/12),acum_c1,'Parámetros'!$B$6*'Parámetros'!$B$5*(1-des_mes^180)/(1-des_mes),acum_c2,MIN('Parámetros'!$B$15,acum_c1*'Parámetros'!$B$16),sub_por_t,'Parámetros'!$B$12*'Parámetros'!$B$23*'Parámetros'!$B$21*'Parámetros'!$B$22*'Parámetros'!$B$24,cap_total,acum_c1+acum_c2,precio_adj,'Parámetros'!$B$10*(1+'Parámetros'!$B$13)^(180/12),terrenos,MAX(0,ENTERO(cap_total/precio_adj)),fam_ubic,terrenos*'Parámetros'!$B$12,canon_anual,fam_ubic*15000*(1+'Parámetros'!$B$27)^(180/12)*12,serv_deuda,acum_c2*0.07,IF(serv_deuda=0,999,REDONDEAR(canon_anual/serv_deuda,2))) | C19: =LET(des_mes,(1-'Parámetros'!$B$7)^(1/12),acum_c1,'Parámetros'!$B$6*'Parámetros'!$B$5*(1-des_mes^180)/(1-des_mes),acum_c2,MIN('Parámetros'!$B$15,acum_c1*'Parámetros'!$B$16),sub_por_t,'Parámetros'!$B$12*'Parámetros'!$B$23*'Parámetros'!$B$21*'Parámetros'!$B$22*'Parámetros'!$B$24,cap_total,acum_c1+acum_c2,precio_adj,'Parámetros'!$B$10*(1+'Parámetros'!$B$13)^(180/12),terrenos,MAX(0,ENTERO(cap_total/precio_adj)),fam_ubic,terrenos*'Parámetros'!$B$12,canon_anual,fam_ubic*20000*(1+'Parámetros'!$B$27)^(180/12)*12,serv_deuda,acum_c2*0.07,IF(serv_deuda=0,999,REDONDEAR(canon_anual/serv_deuda,2))) | D19: =LET(des_mes,(1-'Parámetros'!$B$7)^(1/12),acum_c1,'Parámetros'!$B$6*'Parámetros'!$B$5*(1-des_mes^180)/(1-des_mes),acum_c2,MIN('Parámetros'!$B$15,acum_c1*'Parámetros'!$B$16),sub_por_t,'Parámetros'!$B$12*'Parámetros'!$B$23*'Parámetros'!$B$21*'Parámetros'!$B$22*'Parámetros'!$B$24,cap_total,acum_c1+acum_c2,precio_adj,'Parámetros'!$B$10*(1+'Parámetros'!$B$13)^(180/12),terrenos,MAX(0,ENTERO(cap_total/precio_adj)),fam_ubic,terrenos*'Parámetros'!$B$12,canon_anual,fam_ubic*25000*(1+'Parámetros'!$B$27)^(180/12)*12,serv_deuda,acum_c2*0.07,IF(serv_deuda=0,999,REDONDEAR(canon_anual/serv_deuda,2))) | E19: =LET(des_mes,(1-'Parámetros'!$B$7)^(1/12),acum_c1,'Parámetros'!$B$6*'Parámetros'!$B$5*(1-des_mes^180)/(1-des_mes),acum_c2,MIN('Parámetros'!$B$15,acum_c1*'Parámetros'!$B$16),sub_por_t,'Parámetros'!$B$12*'Parámetros'!$B$23*'Parámetros'!$B$21*'Parámetros'!$B$22*'Parámetros'!$B$24,cap_total,acum_c1+acum_c2,precio_adj,'Parámetros'!$B$10*(1+'Parámetros'!$B$13)^(180/12),terrenos,MAX(0,ENTERO(cap_total/precio_adj)),fam_ubic,terrenos*'Parámetros'!$B$12,canon_anual,fam_ubic*30000*(1+'Parámetros'!$B$27)^(180/12)*12,serv_deuda,acum_c2*0.07,IF(serv_deuda=0,999,REDONDEAR(canon_anual/serv_deuda,2))) | F19: =LET(des_mes,(1-'Parámetros'!$B$7)^(1/12),acum_c1,'Parámetros'!$B$6*'Parámetros'!$B$5*(1-des_mes^180)/(1-des_mes),acum_c2,MIN('Parámetros'!$B$15,acum_c1*'Parámetros'!$B$16),sub_por_t,'Parámetros'!$B$12*'Parámetros'!$B$23*'Parámetros'!$B$21*'Parámetros'!$B$22*'Parámetros'!$B$24,cap_total,acum_c1+acum_c2,precio_adj,'Parámetros'!$B$10*(1+'Parámetros'!$B$13)^(180/12),terrenos,MAX(0,ENTERO(cap_total/precio_adj)),fam_ubic,terrenos*'Parámetros'!$B$12,canon_anual,fam_ubic*35000*(1+'Parámetros'!$B$27)^(180/12)*12,serv_deuda,acum_c2*0.07,IF(serv_deuda=0,999,REDONDEAR(canon_anual/serv_deuda,2)))
A27: TABLA 3 — Meses Hasta Primer Sorteo (primer terreno adquirido)
A28: Familias \ Precio | B28: 80000000 | C28: 100000000 | D28: 120000000 | E28: 150000000 | F28: 200000000
A29: 100 | B29: =LET(des_mes,(1-'Parámetros'!$B$7)^(1/12),meses,SECUENCIA(180),acum_c1,'Parámetros'!$B$6*100*(1-des_mes^meses)/(1-des_mes),acum_c2,MIN('Parámetros'!$B$15,acum_c1*'Parámetros'!$B$16),cap_total,acum_c1+acum_c2,precio_adj,80000000*(1+'Parámetros'!$B$13)^((meses-1)/12),puede,cap_total>=precio_adj,idx,COINCIDIR(VERDADERO,puede,0),IF(ESERROR(idx),">180",idx)) | C29: =LET(des_mes,(1-'Parámetros'!$B$7)^(1/12),meses,SECUENCIA(180),acum_c1,'Parámetros'!$B$6*100*(1-des_mes^meses)/(1-des_mes),acum_c2,MIN('Parámetros'!$B$15,acum_c1*'Parámetros'!$B$16),cap_total,acum_c1+acum_c2,precio_adj,100000000*(1+'Parámetros'!$B$13)^((meses-1)/12),puede,cap_total>=precio_adj,idx,COINCIDIR(VERDADERO,puede,0),IF(ESERROR(idx),">180",idx)) | D29: =LET(des_mes,(1-'Parámetros'!$B$7)^(1/12),meses,SECUENCIA(180),acum_c1,'Parámetros'!$B$6*100*(1-des_mes^meses)/(1-des_mes),acum_c2,MIN('Parámetros'!$B$15,acum_c1*'Parámetros'!$B$16),cap_total,acum_c1+acum_c2,precio_adj,120000000*(1+'Parámetros'!$B$13)^((meses-1)/12),puede,cap_total>=precio_adj,idx,COINCIDIR(VERDADERO,puede,0),IF(ESERROR(idx),">180",idx)) | E29: =LET(des_mes,(1-'Parámetros'!$B$7)^(1/12),meses,SECUENCIA(180),acum_c1,'Parámetros'!$B$6*100*(1-des_mes^meses)/(1-des_mes),acum_c2,MIN('Parámetros'!$B$15,acum_c1*'Parámetros'!$B$16),cap_total,acum_c1+acum_c2,precio_adj,150000000*(1+'Parámetros'!$B$13)^((meses-1)/12),puede,cap_total>=precio_adj,idx,COINCIDIR(VERDADERO,puede,0),IF(ESERROR(idx),">180",idx)) | F29: =LET(des_mes,(1-'Parámetros'!$B$7)^(1/12),meses,SECUENCIA(180),acum_c1,'Parámetros'!$B$6*100*(1-des_mes^meses)/(1-des_mes),acum_c2,MIN('Parámetros'!$B$15,acum_c1*'Parámetros'!$B$16),cap_total,acum_c1+acum_c2,precio_adj,200000000*(1+'Parámetros'!$B$13)^((meses-1)/12),puede,cap_total>=precio_adj,idx,COINCIDIR(VERDADERO,puede,0),IF(ESERROR(idx),">180",idx))
A30: 200 | B30: =LET(des_mes,(1-'Parámetros'!$B$7)^(1/12),meses,SECUENCIA(180),acum_c1,'Parámetros'!$B$6*200*(1-des_mes^meses)/(1-des_mes),acum_c2,MIN('Parámetros'!$B$15,acum_c1*'Parámetros'!$B$16),cap_total,acum_c1+acum_c2,precio_adj,80000000*(1+'Parámetros'!$B$13)^((meses-1)/12),puede,cap_total>=precio_adj,idx,COINCIDIR(VERDADERO,puede,0),IF(ESERROR(idx),">180",idx)) | C30: =LET(des_mes,(1-'Parámetros'!$B$7)^(1/12),meses,SECUENCIA(180),acum_c1,'Parámetros'!$B$6*200*(1-des_mes^meses)/(1-des_mes),acum_c2,MIN('Parámetros'!$B$15,acum_c1*'Parámetros'!$B$16),cap_total,acum_c1+acum_c2,precio_adj,100000000*(1+'Parámetros'!$B$13)^((meses-1)/12),puede,cap_total>=precio_adj,idx,COINCIDIR(VERDADERO,puede,0),IF(ESERROR(idx),">180",idx)) | D30: =LET(des_mes,(1-'Parámetros'!$B$7)^(1/12),meses,SECUENCIA(180),acum_c1,'Parámetros'!$B$6*200*(1-des_mes^meses)/(1-des_mes),acum_c2,MIN('Parámetros'!$B$15,acum_c1*'Parámetros'!$B$16),cap_total,acum_c1+acum_c2,precio_adj,120000000*(1+'Parámetros'!$B$13)^((meses-1)/12),puede,cap_total>=precio_adj,idx,COINCIDIR(VERDADERO,puede,0),IF(ESERROR(idx),">180",idx)) | E30: =LET(des_mes,(1-'Parámetros'!$B$7)^(1/12),meses,SECUENCIA(180),acum_c1,'Parámetros'!$B$6*200*(1-des_mes^meses)/(1-des_mes),acum_c2,MIN('Parámetros'!$B$15,acum_c1*'Parámetros'!$B$16),cap_total,acum_c1+acum_c2,precio_adj,150000000*(1+'Parámetros'!$B$13)^((meses-1)/12),puede,cap_total>=precio_adj,idx,COINCIDIR(VERDADERO,puede,0),IF(ESERROR(idx),">180",idx)) | F30: =LET(des_mes,(1-'Parámetros'!$B$7)^(1/12),meses,SECUENCIA(180),acum_c1,'Parámetros'!$B$6*200*(1-des_mes^meses)/(1-des_mes),acum_c2,MIN('Parámetros'!$B$15,acum_c1*'Parámetros'!$B$16),cap_total,acum_c1+acum_c2,precio_adj,200000000*(1+'Parámetros'!$B$13)^((meses-1)/12),puede,cap_total>=precio_adj,idx,COINCIDIR(VERDADERO,puede,0),IF(ESERROR(idx),">180",idx))
A31: 300 | B31: =LET(des_mes,(1-'Parámetros'!$B$7)^(1/12),meses,SECUENCIA(180),acum_c1,'Parámetros'!$B$6*300*(1-des_mes^meses)/(1-des_mes),acum_c2,MIN('Parámetros'!$B$15,acum_c1*'Parámetros'!$B$16),cap_total,acum_c1+acum_c2,precio_adj,80000000*(1+'Parámetros'!$B$13)^((meses-1)/12),puede,cap_total>=precio_adj,idx,COINCIDIR(VERDADERO,puede,0),IF(ESERROR(idx),">180",idx)) | C31: =LET(des_mes,(1-'Parámetros'!$B$7)^(1/12),meses,SECUENCIA(180),acum_c1,'Parámetros'!$B$6*300*(1-des_mes^meses)/(1-des_mes),acum_c2,MIN('Parámetros'!$B$15,acum_c1*'Parámetros'!$B$16),cap_total,acum_c1+acum_c2,precio_adj,100000000*(1+'Parámetros'!$B$13)^((meses-1)/12),puede,cap_total>=precio_adj,idx,COINCIDIR(VERDADERO,puede,0),IF(ESERROR(idx),">180",idx)) | D31: =LET(des_mes,(1-'Parámetros'!$B$7)^(1/12),meses,SECUENCIA(180),acum_c1,'Parámetros'!$B$6*300*(1-des_mes^meses)/(1-des_mes),acum_c2,MIN('Parámetros'!$B$15,acum_c1*'Parámetros'!$B$16),cap_total,acum_c1+acum_c2,precio_adj,120000000*(1+'Parámetros'!$B$13)^((meses-1)/12),puede,cap_total>=precio_adj,idx,COINCIDIR(VERDADERO,puede,0),IF(ESERROR(idx),">180",idx)) | E31: =LET(des_mes,(1-'Parámetros'!$B$7)^(1/12),meses,SECUENCIA(180),acum_c1,'Parámetros'!$B$6*300*(1-des_mes^meses)/(1-des_mes),acum_c2,MIN('Parámetros'!$B$15,acum_c1*'Parámetros'!$B$16),cap_total,acum_c1+acum_c2,precio_adj,150000000*(1+'Parámetros'!$B$13)^((meses-1)/12),puede,cap_total>=precio_adj,idx,COINCIDIR(VERDADERO,puede,0),IF(ESERROR(idx),">180",idx)) | F31: =LET(des_mes,(1-'Parámetros'!$B$7)^(1/12),meses,SECUENCIA(180),acum_c1,'Parámetros'!$B$6*300*(1-des_mes^meses)/(1-des_mes),acum_c2,MIN('Parámetros'!$B$15,acum_c1*'Parámetros'!$B$16),cap_total,acum_c1+acum_c2,precio_adj,200000000*(1+'Parámetros'!$B$13)^((meses-1)/12),puede,cap_total>=precio_adj,idx,COINCIDIR(VERDADERO,puede,0),IF(ESERROR(idx),">180",idx))
A32: 500 | B32: =LET(des_mes,(1-'Parámetros'!$B$7)^(1/12),meses,SECUENCIA(180),acum_c1,'Parámetros'!$B$6*500*(1-des_mes^meses)/(1-des_mes),acum_c2,MIN('Parámetros'!$B$15,acum_c1*'Parámetros'!$B$16),cap_total,acum_c1+acum_c2,precio_adj,80000000*(1+'Parámetros'!$B$13)^((meses-1)/12),puede,cap_total>=precio_adj,idx,COINCIDIR(VERDADERO,puede,0),IF(ESERROR(idx),">180",idx)) | C32: =LET(des_mes,(1-'Parámetros'!$B$7)^(1/12),meses,SECUENCIA(180),acum_c1,'Parámetros'!$B$6*500*(1-des_mes^meses)/(1-des_mes),acum_c2,MIN('Parámetros'!$B$15,acum_c1*'Parámetros'!$B$16),cap_total,acum_c1+acum_c2,precio_adj,100000000*(1+'Parámetros'!$B$13)^((meses-1)/12),puede,cap_total>=precio_adj,idx,COINCIDIR(VERDADERO,puede,0),IF(ESERROR(idx),">180",idx)) | D32: =LET(des_mes,(1-'Parámetros'!$B$7)^(1/12),meses,SECUENCIA(180),acum_c1,'Parámetros'!$B$6*500*(1-des_mes^meses)/(1-des_mes),acum_c2,MIN('Parámetros'!$B$15,acum_c1*'Parámetros'!$B$16),cap_total,acum_c1+acum_c2,precio_adj,120000000*(1+'Parámetros'!$B$13)^((meses-1)/12),puede,cap_total>=precio_adj,idx,COINCIDIR(VERDADERO,puede,0),IF(ESERROR(idx),">180",idx)) | E32: =LET(des_mes,(1-'Parámetros'!$B$7)^(1/12),meses,SECUENCIA(180),acum_c1,'Parámetros'!$B$6*500*(1-des_mes^meses)/(1-des_mes),acum_c2,MIN('Parámetros'!$B$15,acum_c1*'Parámetros'!$B$16),cap_total,acum_c1+acum_c2,precio_adj,150000000*(1+'Parámetros'!$B$13)^((meses-1)/12),puede,cap_total>=precio_adj,idx,COINCIDIR(VERDADERO,puede,0),IF(ESERROR(idx),">180",idx)) | F32: =LET(des_mes,(1-'Parámetros'!$B$7)^(1/12),meses,SECUENCIA(180),acum_c1,'Parámetros'!$B$6*500*(1-des_mes^meses)/(1-des_mes),acum_c2,MIN('Parámetros'!$B$15,acum_c1*'Parámetros'!$B$16),cap_total,acum_c1+acum_c2,precio_adj,200000000*(1+'Parámetros'!$B$13)^((meses-1)/12),puede,cap_total>=precio_adj,idx,COINCIDIR(VERDADERO,puede,0),IF(ESERROR(idx),">180",idx))
A33: 1000 | B33: =LET(des_mes,(1-'Parámetros'!$B$7)^(1/12),meses,SECUENCIA(180),acum_c1,'Parámetros'!$B$6*1000*(1-des_mes^meses)/(1-des_mes),acum_c2,MIN('Parámetros'!$B$15,acum_c1*'Parámetros'!$B$16),cap_total,acum_c1+acum_c2,precio_adj,80000000*(1+'Parámetros'!$B$13)^((meses-1)/12),puede,cap_total>=precio_adj,idx,COINCIDIR(VERDADERO,puede,0),IF(ESERROR(idx),">180",idx)) | C33: =LET(des_mes,(1-'Parámetros'!$B$7)^(1/12),meses,SECUENCIA(180),acum_c1,'Parámetros'!$B$6*1000*(1-des_mes^meses)/(1-des_mes),acum_c2,MIN('Parámetros'!$B$15,acum_c1*'Parámetros'!$B$16),cap_total,acum_c1+acum_c2,precio_adj,100000000*(1+'Parámetros'!$B$13)^((meses-1)/12),puede,cap_total>=precio_adj,idx,COINCIDIR(VERDADERO,puede,0),IF(ESERROR(idx),">180",idx)) | D33: =LET(des_mes,(1-'Parámetros'!$B$7)^(1/12),meses,SECUENCIA(180),acum_c1,'Parámetros'!$B$6*1000*(1-des_mes^meses)/(1-des_mes),acum_c2,MIN('Parámetros'!$B$15,acum_c1*'Parámetros'!$B$16),cap_total,acum_c1+acum_c2,precio_adj,120000000*(1+'Parámetros'!$B$13)^((meses-1)/12),puede,cap_total>=precio_adj,idx,COINCIDIR(VERDADERO,puede,0),IF(ESERROR(idx),">180",idx)) | E33: =LET(des_mes,(1-'Parámetros'!$B$7)^(1/12),meses,SECUENCIA(180),acum_c1,'Parámetros'!$B$6*1000*(1-des_mes^meses)/(1-des_mes),acum_c2,MIN('Parámetros'!$B$15,acum_c1*'Parámetros'!$B$16),cap_total,acum_c1+acum_c2,precio_adj,150000000*(1+'Parámetros'!$B$13)^((meses-1)/12),puede,cap_total>=precio_adj,idx,COINCIDIR(VERDADERO,puede,0),IF(ESERROR(idx),">180",idx)) | F33: =LET(des_mes,(1-'Parámetros'!$B$7)^(1/12),meses,SECUENCIA(180),acum_c1,'Parámetros'!$B$6*1000*(1-des_mes^meses)/(1-des_mes),acum_c2,MIN('Parámetros'!$B$15,acum_c1*'Parámetros'!$B$16),cap_total,acum_c1+acum_c2,precio_adj,200000000*(1+'Parámetros'!$B$13)^((meses-1)/12),puede,cap_total>=precio_adj,idx,COINCIDIR(VERDADERO,puede,0),IF(ESERROR(idx),">180",idx))

Sheet Dashboard
A1: FONDO MUTUALISTA DE SUELO URBANO — Dashboard de KPIs
A2: Resultados calculados automáticamente desde la hoja 'Parámetros'. Horizonte: 180 meses (15 años).
B4: IMPACTO — Terrenos y Familias
B5: Terrenos a 3 años | D5: Terrenos a 5 años | F5: Terrenos a 10 años | H5: Terrenos a 15 años
B6: ='Flujo del Fondo'!J39 | D6: ='Flujo del Fondo'!J63 | F6: ='Flujo del Fondo'!J123 | H6: ='Flujo del Fondo'!J183
B7: (mes 36) | D7: (mes 60) | F7: (mes 120) | H7: (mes 180)
B9: FAMILIAS UBICADAS EN CLT
B10: Familias ubicadas a 3 años | D10: Familias ubicadas a 5 años | F10: Familias ubicadas a 10 años | H10: Familias ubicadas a 15 años
B11: ='Flujo del Fondo'!K39 | D11: ='Flujo del Fondo'!K63 | F11: ='Flujo del Fondo'!K123 | H11: ='Flujo del Fondo'!K183
B12: (mes 36) | D12: (mes 60) | F12: (mes 120) | H12: (mes 180)
B15: CAPITAL MOVILIZADO Y APALANCAMIENTO
B16: Capital Total Movilizado | D16: Apalancamiento Total | F16: Meses hasta Primer Sorteo | H16: Costo por Familia Ubicada
B17: ='Flujo del Fondo'!I183 | D17: =IF('Flujo del Fondo'!E183=0,0,'Flujo del Fondo'!I183/'Flujo del Fondo'!E183) | F17: =LET(t,COINCIDIR(1,'Flujo del Fondo'!J4:'Flujo del Fondo'!J183,1),IF(ESERROR(t),">180",t)) | H17: =IF('Flujo del Fondo'!K183=0,0,'Flujo del Fondo'!I183/'Flujo del Fondo'!K183)
B18: Suma 3 capas (mes 180) | D18: Cap. total / Capa 1 | F18: 1er terreno adquirido | H18: Cap. total / fam. ubicadas
B21: COBERTURA DEUDA CAPA 2 (Canon / Servicio Deuda)
B22: Cobertura a 5 años | D22: Cobertura a 10 años | F22: Cobertura a 15 años | H22: Retorno exigido Capa 2
B23: =IF('Flujo del Fondo'!O63=0,">10x",'Flujo del Fondo'!M63/'Flujo del Fondo'!O63) | D23: =IF('Flujo del Fondo'!O123=0,">10x",'Flujo del Fondo'!M123/'Flujo del Fondo'!O123) | F23: =IF('Flujo del Fondo'!O183=0,">10x",'Flujo del Fondo'!M183/'Flujo del Fondo'!O183) | H23: ='Parámetros'!$B$17
B24: (mes 60) | D24: (mes 120) | F24: (mes 180) | H24: (configurado en Parámetros)
B27: COMPARACIÓN VS. SUBSIDIO DS-49
B28: Subsidio DS-49 referencial | D28: Costo por familia (CLT) | F28: Diferencia vs DS-49 | H28: Flujo Neto Acumulado 15 años
B29: =1400*'Parámetros'!$B$22 | D29: =IF('Flujo del Fondo'!K183=0,0,'Flujo del Fondo'!I183/'Flujo del Fondo'!K183) | F29: =IF('Flujo del Fondo'!K183=0,0,('Flujo del Fondo'!I183/'Flujo del Fondo'!K183)-(1400*'Parámetros'!$B$22)) | H29: ='Flujo del Fondo'!Q183
B30: 1.400 UF × valor UF | D30: Cap. total / fam. ubicadas | F30: (+ costoso / - costoso que DS-49) | H30: (positivo = autosustentable)
B35: Datos para gráficos (referencias a Flujo del Fondo)
B36: Año | C36: Acum.C1(M$) | D36: Acum.C2(M$) | E36: Acum.C3(M$) | F36: Fam.Ubic. | G36: Fam.Espera | H36: Terrenos
B37: 1 | C37: =REDONDEAR('Flujo del Fondo'!E15/1000000,1) | D37: =REDONDEAR('Flujo del Fondo'!G15/1000000,1) | E37: =REDONDEAR('Flujo del Fondo'!H15/1000000,1) | F37: ='Flujo del Fondo'!K15 | G37: ='Flujo del Fondo'!L15 | H37: ='Flujo del Fondo'!J15
B38: 2 | C38: =REDONDEAR('Flujo del Fondo'!E27/1000000,1) | D38: =REDONDEAR('Flujo del Fondo'!G27/1000000,1) | E38: =REDONDEAR('Flujo del Fondo'!H27/1000000,1) | F38: ='Flujo del Fondo'!K27 | G38: ='Flujo del Fondo'!L27 | H38: ='Flujo del Fondo'!J27
B39: 3 | C39: =REDONDEAR('Flujo del Fondo'!E39/1000000,1) | D39: =REDONDEAR('Flujo del Fondo'!G39/1000000,1) | E39: =REDONDEAR('Flujo del Fondo'!H39/1000000,1) | F39: ='Flujo del Fondo'!K39 | G39: ='Flujo del Fondo'!L39 | H39: ='Flujo del Fondo'!J39
B40: 4 | C40: =REDONDEAR('Flujo del Fondo'!E51/1000000,1) | D40: =REDONDEAR('Flujo del Fondo'!G51/1000000,1) | E40: =REDONDEAR('Flujo del Fondo'!H51/1000000,1) | F40: ='Flujo del Fondo'!K51 | G40: ='Flujo del Fondo'!L51 | H40: ='Flujo del Fondo'!J51
B41: 5 | C41: =REDONDEAR('Flujo del Fondo'!E63/1000000,1) | D41: =REDONDEAR('Flujo del Fondo'!G63/1000000,1) | E41: =REDONDEAR('Flujo del Fondo'!H63/1000000,1) | F41: ='Flujo del Fondo'!K63 | G41: ='Flujo del Fondo'!L63 | H41: ='Flujo del Fondo'!J63
B42: 6 | C42: =REDONDEAR('Flujo del Fondo'!E75/1000000,1) | D42: =REDONDEAR('Flujo del Fondo'!G75/1000000,1) | E42: =REDONDEAR('Flujo del Fondo'!H75/1000000,1) | F42: ='Flujo del Fondo'!K75 | G42: ='Flujo del Fondo'!L75 | H42: ='Flujo del Fondo'!J75
B43: 7 | C43: =REDONDEAR('Flujo del Fondo'!E87/1000000,1) | D43: =REDONDEAR('Flujo del Fondo'!G87/1000000,1) | E43: =REDONDEAR('Flujo del Fondo'!H87/1000000,1) | F43: ='Flujo del Fondo'!K87 | G43: ='Flujo del Fondo'!L87 | H43: ='Flujo del Fondo'!J87
B44: 8 | C44: =REDONDEAR('Flujo del Fondo'!E99/1000000,1) | D44: =REDONDEAR('Flujo del Fondo'!G99/1000000,1) | E44: =REDONDEAR('Flujo del Fondo'!H99/1000000,1) | F44: ='Flujo del Fondo'!K99 | G44: ='Flujo del Fondo'!L99 | H44: ='Flujo del Fondo'!J99
B45: 9 | C45: =REDONDEAR('Flujo del Fondo'!E111/1000000,1) | D45: =REDONDEAR('Flujo del Fondo'!G111/1000000,1) | E45: =REDONDEAR('Flujo del Fondo'!H111/1000000,1) | F45: ='Flujo del Fondo'!K111 | G45: ='Flujo del Fondo'!L111 | H45: ='Flujo del Fondo'!J111
B46: 10 | C46: =REDONDEAR('Flujo del Fondo'!E123/1000000,1) | D46: =REDONDEAR('Flujo del Fondo'!G123/1000000,1) | E46: =REDONDEAR('Flujo del Fondo'!H123/1000000,1) | F46: ='Flujo del Fondo'!K123 | G46: ='Flujo del Fondo'!L123 | H46: ='Flujo del Fondo'!J123
B47: 11 | C47: =REDONDEAR('Flujo del Fondo'!E135/1000000,1) | D47: =REDONDEAR('Flujo del Fondo'!G135/1000000,1) | E47: =REDONDEAR('Flujo del Fondo'!H135/1000000,1) | F47: ='Flujo del Fondo'!K135 | G47: ='Flujo del Fondo'!L135 | H47: ='Flujo del Fondo'!J135
B48: 12 | C48: =REDONDEAR('Flujo del Fondo'!E147/1000000,1) | D48: =REDONDEAR('Flujo del Fondo'!G147/1000000,1) | E48: =REDONDEAR('Flujo del Fondo'!H147/1000000,1) | F48: ='Flujo del Fondo'!K147 | G48: ='Flujo del Fondo'!L147 | H48: ='Flujo del Fondo'!J147
B49: 13 | C49: =REDONDEAR('Flujo del Fondo'!E159/1000000,1) | D49: =REDONDEAR('Flujo del Fondo'!G159/1000000,1) | E49: =REDONDEAR('Flujo del Fondo'!H159/1000000,1) | F49: ='Flujo del Fondo'!K159 | G49: ='Flujo del Fondo'!L159 | H49: ='Flujo del Fondo'!J159
B50: 14 | C50: =REDONDEAR('Flujo del Fondo'!E171/1000000,1) | D50: =REDONDEAR('Flujo del Fondo'!G171/1000000,1) | E50: =REDONDEAR('Flujo del Fondo'!H171/1000000,1) | F50: ='Flujo del Fondo'!K171 | G50: ='Flujo del Fondo'!L171 | H50: ='Flujo del Fondo'!J171
B51: 15 | C51: =REDONDEAR('Flujo del Fondo'!E183/1000000,1) | D51: =REDONDEAR('Flujo del Fondo'!G183/1000000,1) | E51: =REDONDEAR('Flujo del Fondo'!H183/1000000,1) | F51: ='Flujo del Fondo'!K183 | G51: ='Flujo del Fondo'!L183 | H51: ='Flujo del Fondo'!J183

Sheet Escenarios
A1: ESCENARIOS COMPARATIVOS — Fondo Mutualista de Suelo Urbano
A2: Los escenarios calculan KPIs directamente con sus parámetros propios. NO sobreescriben la hoja Parámetros.
A4: KPI / Indicador | B4: Escenario 1 MÍNIMO VIABLE | C4: Escenario 2 BASE | D4: Escenario 3 ESCALA
A5: ── PARÁMETROS ──
A6: Familias participantes | B6: 200 | C6: 500 | D6: 1000
A7: Cuota mensual (CLP) | B7: 30000 | C7: 30000 | D7: 35000
A8: Capital Capa 2 (CLP) | B8: 200000000 | C8: 500000000 | D8: 1500000000
A9: % familias con subsidio | B9: 0 | C9: 0.6 | D9: 0.8
A10: Descripción
A11: Descripción | B11: 200 familias, sin subsidio estatal, capital paciente 200M | C11: 500 familias, subsidio 60%, capital paciente 500M | D11: 1.000 familias, subsidio 80%, capital paciente 1.500M
A12: ── TERRENOS ADQUIRIDOS ──
A13: Terrenos a 3 años (mes 36) | B13: =LET(des_mes,(1-0.05)^(1/12),acum_c1,30000*200*(1-des_mes^36)/(1-des_mes),acum_c2,MIN(200000000,acum_c1*3),sub_por_t,25*0.0*800*38000*1.0,precio_adj,120000000*(1+0.05)^(36/12),cap_pre,acum_c1+acum_c2,terr_pre,MAX(0,ENTERO(cap_pre/precio_adj)),cap_total,acum_c1+acum_c2+terr_pre*sub_por_t,terrenos,MAX(0,ENTERO(cap_total/precio_adj)),fam_ubic,terrenos*25,fam_act,REDONDEAR(200*des_mes^36,0),fam_esp,MAX(0,fam_act-fam_ubic),canon_adj,25000*(1+0.03)^(36/12),canon_mes,fam_ubic*canon_adj,serv_deuda,IF(36<=12,0,acum_c2*0.05/12),flujo_neto,30000*fam_act+canon_mes-serv_deuda,terrenos) | C13: =LET(des_mes,(1-0.05)^(1/12),acum_c1,30000*500*(1-des_mes^36)/(1-des_mes),acum_c2,MIN(500000000,acum_c1*3),sub_por_t,25*0.6*800*38000*1.0,precio_adj,120000000*(1+0.05)^(36/12),cap_pre,acum_c1+acum_c2,terr_pre,MAX(0,ENTERO(cap_pre/precio_adj)),cap_total,acum_c1+acum_c2+terr_pre*sub_por_t,terrenos,MAX(0,ENTERO(cap_total/precio_adj)),fam_ubic,terrenos*25,fam_act,REDONDEAR(500*des_mes^36,0),fam_esp,MAX(0,fam_act-fam_ubic),canon_adj,25000*(1+0.03)^(36/12),canon_mes,fam_ubic*canon_adj,serv_deuda,IF(36<=12,0,acum_c2*0.05/12),flujo_neto,30000*fam_act+canon_mes-serv_deuda,terrenos) | D13: =LET(des_mes,(1-0.05)^(1/12),acum_c1,35000*1000*(1-des_mes^36)/(1-des_mes),acum_c2,MIN(1500000000,acum_c1*3),sub_por_t,25*0.8*800*38000*1.0,precio_adj,120000000*(1+0.05)^(36/12),cap_pre,acum_c1+acum_c2,terr_pre,MAX(0,ENTERO(cap_pre/precio_adj)),cap_total,acum_c1+acum_c2+terr_pre*sub_por_t,terrenos,MAX(0,ENTERO(cap_total/precio_adj)),fam_ubic,terrenos*25,fam_act,REDONDEAR(1000*des_mes^36,0),fam_esp,MAX(0,fam_act-fam_ubic),canon_adj,25000*(1+0.03)^(36/12),canon_mes,fam_ubic*canon_adj,serv_deuda,IF(36<=12,0,acum_c2*0.05/12),flujo_neto,35000*fam_act+canon_mes-serv_deuda,terrenos)
A14: Terrenos a 5 años (mes 60) | B14: =LET(des_mes,(1-0.05)^(1/12),acum_c1,30000*200*(1-des_mes^60)/(1-des_mes),acum_c2,MIN(200000000,acum_c1*3),sub_por_t,25*0.0*800*38000*1.0,precio_adj,120000000*(1+0.05)^(60/12),cap_pre,acum_c1+acum_c2,terr_pre,MAX(0,ENTERO(cap_pre/precio_adj)),cap_total,acum_c1+acum_c2+terr_pre*sub_por_t,terrenos,MAX(0,ENTERO(cap_total/precio_adj)),fam_ubic,terrenos*25,fam_act,REDONDEAR(200*des_mes^60,0),fam_esp,MAX(0,fam_act-fam_ubic),canon_adj,25000*(1+0.03)^(60/12),canon_mes,fam_ubic*canon_adj,serv_deuda,IF(60<=12,0,acum_c2*0.05/12),flujo_neto,30000*fam_act+canon_mes-serv_deuda,terrenos) | C14: =LET(des_mes,(1-0.05)^(1/12),acum_c1,30000*500*(1-des_mes^60)/(1-des_mes),acum_c2,MIN(500000000,acum_c1*3),sub_por_t,25*0.6*800*38000*1.0,precio_adj,120000000*(1+0.05)^(60/12),cap_pre,acum_c1+acum_c2,terr_pre,MAX(0,ENTERO(cap_pre/precio_adj)),cap_total,acum_c1+acum_c2+terr_pre*sub_por_t,terrenos,MAX(0,ENTERO(cap_total/precio_adj)),fam_ubic,terrenos*25,fam_act,REDONDEAR(500*des_mes^60,0),fam_esp,MAX(0,fam_act-fam_ubic),canon_adj,25000*(1+0.03)^(60/12),canon_mes,fam_ubic*canon_adj,serv_deuda,IF(60<=12,0,acum_c2*0.05/12),flujo_neto,30000*fam_act+canon_mes-serv_deuda,terrenos) | D14: =LET(des_mes,(1-0.05)^(1/12),acum_c1,35000*1000*(1-des_mes^60)/(1-des_mes),acum_c2,MIN(1500000000,acum_c1*3),sub_por_t,25*0.8*800*38000*1.0,precio_adj,120000000*(1+0.05)^(60/12),cap_pre,acum_c1+acum_c2,terr_pre,MAX(0,ENTERO(cap_pre/precio_adj)),cap_total,acum_c1+acum_c2+terr_pre*sub_por_t,terrenos,MAX(0,ENTERO(cap_total/precio_adj)),fam_ubic,terrenos*25,fam_act,REDONDEAR(1000*des_mes^60,0),fam_esp,MAX(0,fam_act-fam_ubic),canon_adj,25000*(1+0.03)^(60/12),canon_mes,fam_ubic*canon_adj,serv_deuda,IF(60<=12,0,acum_c2*0.05/12),flujo_neto,35000*fam_act+canon_mes-serv_deuda,terrenos)
A15: Terrenos a 10 años (mes 120) | B15: =LET(des_mes,(1-0.05)^(1/12),acum_c1,30000*200*(1-des_mes^120)/(1-des_mes),acum_c2,MIN(200000000,acum_c1*3),sub_por_t,25*0.0*800*38000*1.0,precio_adj,120000000*(1+0.05)^(120/12),cap_pre,acum_c1+acum_c2,terr_pre,MAX(0,ENTERO(cap_pre/precio_adj)),cap_total,acum_c1+acum_c2+terr_pre*sub_por_t,terrenos,MAX(0,ENTERO(cap_total/precio_adj)),fam_ubic,terrenos*25,fam_act,REDONDEAR(200*des_mes^120,0),fam_esp,MAX(0,fam_act-fam_ubic),canon_adj,25000*(1+0.03)^(120/12),canon_mes,fam_ubic*canon_adj,serv_deuda,IF(120<=12,0,acum_c2*0.05/12),flujo_neto,30000*fam_act+canon_mes-serv_deuda,terrenos) | C15: =LET(des_mes,(1-0.05)^(1/12),acum_c1,30000*500*(1-des_mes^120)/(1-des_mes),acum_c2,MIN(500000000,acum_c1*3),sub_por_t,25*0.6*800*38000*1.0,precio_adj,120000000*(1+0.05)^(120/12),cap_pre,acum_c1+acum_c2,terr_pre,MAX(0,ENTERO(cap_pre/precio_adj)),cap_total,acum_c1+acum_c2+terr_pre*sub_por_t,terrenos,MAX(0,ENTERO(cap_total/precio_adj)),fam_ubic,terrenos*25,fam_act,REDONDEAR(500*des_mes^120,0),fam_esp,MAX(0,fam_act-fam_ubic),canon_adj,25000*(1+0.03)^(120/12),canon_mes,fam_ubic*canon_adj,serv_deuda,IF(120<=12,0,acum_c2*0.05/12),flujo_neto,30000*fam_act+canon_mes-serv_deuda,terrenos) | D15: =LET(des_mes,(1-0.05)^(1/12),acum_c1,35000*1000*(1-des_mes^120)/(1-des_mes),acum_c2,MIN(1500000000,acum_c1*3),sub_por_t,25*0.8*800*38000*1.0,precio_adj,120000000*(1+0.05)^(120/12),cap_pre,acum_c1+acum_c2,terr_pre,MAX(0,ENTERO(cap_pre/precio_adj)),cap_total,acum_c1+acum_c2+terr_pre*sub_por_t,terrenos,MAX(0,ENTERO(cap_total/precio_adj)),fam_ubic,terrenos*25,fam_act,REDONDEAR(1000*des_mes^120,0),fam_esp,MAX(0,fam_act-fam_ubic),canon_adj,25000*(1+0.03)^(120/12),canon_mes,fam_ubic*canon_adj,serv_deuda,IF(120<=12,0,acum_c2*0.05/12),flujo_neto,35000*fam_act+canon_mes-serv_deuda,terrenos)
A16: Terrenos a 15 años (mes 180) | B16: =LET(des_mes,(1-0.05)^(1/12),acum_c1,30000*200*(1-des_mes^180)/(1-des_mes),acum_c2,MIN(200000000,acum_c1*3),sub_por_t,25*0.0*800*38000*1.0,precio_adj,120000000*(1+0.05)^(180/12),cap_pre,acum_c1+acum_c2,terr_pre,MAX(0,ENTERO(cap_pre/precio_adj)),cap_total,acum_c1+acum_c2+terr_pre*sub_por_t,terrenos,MAX(0,ENTERO(cap_total/precio_adj)),fam_ubic,terrenos*25,fam_act,REDONDEAR(200*des_mes^180,0),fam_esp,MAX(0,fam_act-fam_ubic),canon_adj,25000*(1+0.03)^(180/12),canon_mes,fam_ubic*canon_adj,serv_deuda,IF(180<=12,0,acum_c2*0.05/12),flujo_neto,30000*fam_act+canon_mes-serv_deuda,terrenos) | C16: =LET(des_mes,(1-0.05)^(1/12),acum_c1,30000*500*(1-des_mes^180)/(1-des_mes),acum_c2,MIN(500000000,acum_c1*3),sub_por_t,25*0.6*800*38000*1.0,precio_adj,120000000*(1+0.05)^(180/12),cap_pre,acum_c1+acum_c2,terr_pre,MAX(0,ENTERO(cap_pre/precio_adj)),cap_total,acum_c1+acum_c2+terr_pre*sub_por_t,terrenos,MAX(0,ENTERO(cap_total/precio_adj)),fam_ubic,terrenos*25,fam_act,REDONDEAR(500*des_mes^180,0),fam_esp,MAX(0,fam_act-fam_ubic),canon_adj,25000*(1+0.03)^(180/12),canon_mes,fam_ubic*canon_adj,serv_deuda,IF(180<=12,0,acum_c2*0.05/12),flujo_neto,30000*fam_act+canon_mes-serv_deuda,terrenos) | D16: =LET(des_mes,(1-0.05)^(1/12),acum_c1,35000*1000*(1-des_mes^180)/(1-des_mes),acum_c2,MIN(1500000000,acum_c1*3),sub_por_t,25*0.8*800*38000*1.0,precio_adj,120000000*(1+0.05)^(180/12),cap_pre,acum_c1+acum_c2,terr_pre,MAX(0,ENTERO(cap_pre/precio_adj)),cap_total,acum_c1+acum_c2+terr_pre*sub_por_t,terrenos,MAX(0,ENTERO(cap_total/precio_adj)),fam_ubic,terrenos*25,fam_act,REDONDEAR(1000*des_mes^180,0),fam_esp,MAX(0,fam_act-fam_ubic),canon_adj,25000*(1+0.03)^(180/12),canon_mes,fam_ubic*canon_adj,serv_deuda,IF(180<=12,0,acum_c2*0.05/12),flujo_neto,35000*fam_act+canon_mes-serv_deuda,terrenos)
A17: ── FAMILIAS UBICADAS ──
A18: Familias ubicadas a 3 años | B18: =LET(des_mes,(1-0.05)^(1/12),acum_c1,30000*200*(1-des_mes^36)/(1-des_mes),acum_c2,MIN(200000000,acum_c1*3),sub_por_t,25*0.0*800*38000*1.0,precio_adj,120000000*(1+0.05)^(36/12),cap_pre,acum_c1+acum_c2,terr_pre,MAX(0,ENTERO(cap_pre/precio_adj)),cap_total,acum_c1+acum_c2+terr_pre*sub_por_t,terrenos,MAX(0,ENTERO(cap_total/precio_adj)),fam_ubic,terrenos*25,fam_act,REDONDEAR(200*des_mes^36,0),fam_esp,MAX(0,fam_act-fam_ubic),canon_adj,25000*(1+0.03)^(36/12),canon_mes,fam_ubic*canon_adj,serv_deuda,IF(36<=12,0,acum_c2*0.05/12),flujo_neto,30000*fam_act+canon_mes-serv_deuda,fam_ubic) | C18: =LET(des_mes,(1-0.05)^(1/12),acum_c1,30000*500*(1-des_mes^36)/(1-des_mes),acum_c2,MIN(500000000,acum_c1*3),sub_por_t,25*0.6*800*38000*1.0,precio_adj,120000000*(1+0.05)^(36/12),cap_pre,acum_c1+acum_c2,terr_pre,MAX(0,ENTERO(cap_pre/precio_adj)),cap_total,acum_c1+acum_c2+terr_pre*sub_por_t,terrenos,MAX(0,ENTERO(cap_total/precio_adj)),fam_ubic,terrenos*25,fam_act,REDONDEAR(500*des_mes^36,0),fam_esp,MAX(0,fam_act-fam_ubic),canon_adj,25000*(1+0.03)^(36/12),canon_mes,fam_ubic*canon_adj,serv_deuda,IF(36<=12,0,acum_c2*0.05/12),flujo_neto,30000*fam_act+canon_mes-serv_deuda,fam_ubic) | D18: =LET(des_mes,(1-0.05)^(1/12),acum_c1,35000*1000*(1-des_mes^36)/(1-des_mes),acum_c2,MIN(1500000000,acum_c1*3),sub_por_t,25*0.8*800*38000*1.0,precio_adj,120000000*(1+0.05)^(36/12),cap_pre,acum_c1+acum_c2,terr_pre,MAX(0,ENTERO(cap_pre/precio_adj)),cap_total,acum_c1+acum_c2+terr_pre*sub_por_t,terrenos,MAX(0,ENTERO(cap_total/precio_adj)),fam_ubic,terrenos*25,fam_act,REDONDEAR(1000*des_mes^36,0),fam_esp,MAX(0,fam_act-fam_ubic),canon_adj,25000*(1+0.03)^(36/12),canon_mes,fam_ubic*canon_adj,serv_deuda,IF(36<=12,0,acum_c2*0.05/12),flujo_neto,35000*fam_act+canon_mes-serv_deuda,fam_ubic)
A19: Familias ubicadas a 5 años | B19: =LET(des_mes,(1-0.05)^(1/12),acum_c1,30000*200*(1-des_mes^60)/(1-des_mes),acum_c2,MIN(200000000,acum_c1*3),sub_por_t,25*0.0*800*38000*1.0,precio_adj,120000000*(1+0.05)^(60/12),cap_pre,acum_c1+acum_c2,terr_pre,MAX(0,ENTERO(cap_pre/precio_adj)),cap_total,acum_c1+acum_c2+terr_pre*sub_por_t,terrenos,MAX(0,ENTERO(cap_total/precio_adj)),fam_ubic,terrenos*25,fam_act,REDONDEAR(200*des_mes^60,0),fam_esp,MAX(0,fam_act-fam_ubic),canon_adj,25000*(1+0.03)^(60/12),canon_mes,fam_ubic*canon_adj,serv_deuda,IF(60<=12,0,acum_c2*0.05/12),flujo_neto,30000*fam_act+canon_mes-serv_deuda,fam_ubic) | C19: =LET(des_mes,(1-0.05)^(1/12),acum_c1,30000*500*(1-des_mes^60)/(1-des_mes),acum_c2,MIN(500000000,acum_c1*3),sub_por_t,25*0.6*800*38000*1.0,precio_adj,120000000*(1+0.05)^(60/12),cap_pre,acum_c1+acum_c2,terr_pre,MAX(0,ENTERO(cap_pre/precio_adj)),cap_total,acum_c1+acum_c2+terr_pre*sub_por_t,terrenos,MAX(0,ENTERO(cap_total/precio_adj)),fam_ubic,terrenos*25,fam_act,REDONDEAR(500*des_mes^60,0),fam_esp,MAX(0,fam_act-fam_ubic),canon_adj,25000*(1+0.03)^(60/12),canon_mes,fam_ubic*canon_adj,serv_deuda,IF(60<=12,0,acum_c2*0.05/12),flujo_neto,30000*fam_act+canon_mes-serv_deuda,fam_ubic) | D19: =LET(des_mes,(1-0.05)^(1/12),acum_c1,35000*1000*(1-des_mes^60)/(1-des_mes),acum_c2,MIN(1500000000,acum_c1*3),sub_por_t,25*0.8*800*38000*1.0,precio_adj,120000000*(1+0.05)^(60/12),cap_pre,acum_c1+acum_c2,terr_pre,MAX(0,ENTERO(cap_pre/precio_adj)),cap_total,acum_c1+acum_c2+terr_pre*sub_por_t,terrenos,MAX(0,ENTERO(cap_total/precio_adj)),fam_ubic,terrenos*25,fam_act,REDONDEAR(1000*des_mes^60,0),fam_esp,MAX(0,fam_act-fam_ubic),canon_adj,25000*(1+0.03)^(60/12),canon_mes,fam_ubic*canon_adj,serv_deuda,IF(60<=12,0,acum_c2*0.05/12),flujo_neto,35000*fam_act+canon_mes-serv_deuda,fam_ubic)
A20: Familias ubicadas a 10 años | B20: =LET(des_mes,(1-0.05)^(1/12),acum_c1,30000*200*(1-des_mes^120)/(1-des_mes),acum_c2,MIN(200000000,acum_c1*3),sub_por_t,25*0.0*800*38000*1.0,precio_adj,120000000*(1+0.05)^(120/12),cap_pre,acum_c1+acum_c2,terr_pre,MAX(0,ENTERO(cap_pre/precio_adj)),cap_total,acum_c1+acum_c2+terr_pre*sub_por_t,terrenos,MAX(0,ENTERO(cap_total/precio_adj)),fam_ubic,terrenos*25,fam_act,REDONDEAR(200*des_mes^120,0),fam_esp,MAX(0,fam_act-fam_ubic),canon_adj,25000*(1+0.03)^(120/12),canon_mes,fam_ubic*canon_adj,serv_deuda,IF(120<=12,0,acum_c2*0.05/12),flujo_neto,30000*fam_act+canon_mes-serv_deuda,fam_ubic) | C20: =LET(des_mes,(1-0.05)^(1/12),acum_c1,30000*500*(1-des_mes^120)/(1-des_mes),acum_c2,MIN(500000000,acum_c1*3),sub_por_t,25*0.6*800*38000*1.0,precio_adj,120000000*(1+0.05)^(120/12),cap_pre,acum_c1+acum_c2,terr_pre,MAX(0,ENTERO(cap_pre/precio_adj)),cap_total,acum_c1+acum_c2+terr_pre*sub_por_t,terrenos,MAX(0,ENTERO(cap_total/precio_adj)),fam_ubic,terrenos*25,fam_act,REDONDEAR(500*des_mes^120,0),fam_esp,MAX(0,fam_act-fam_ubic),canon_adj,25000*(1+0.03)^(120/12),canon_mes,fam_ubic*canon_adj,serv_deuda,IF(120<=12,0,acum_c2*0.05/12),flujo_neto,30000*fam_act+canon_mes-serv_deuda,fam_ubic) | D20: =LET(des_mes,(1-0.05)^(1/12),acum_c1,35000*1000*(1-des_mes^120)/(1-des_mes),acum_c2,MIN(1500000000,acum_c1*3),sub_por_t,25*0.8*800*38000*1.0,precio_adj,120000000*(1+0.05)^(120/12),cap_pre,acum_c1+acum_c2,terr_pre,MAX(0,ENTERO(cap_pre/precio_adj)),cap_total,acum_c1+acum_c2+terr_pre*sub_por_t,terrenos,MAX(0,ENTERO(cap_total/precio_adj)),fam_ubic,terrenos*25,fam_act,REDONDEAR(1000*des_mes^120,0),fam_esp,MAX(0,fam_act-fam_ubic),canon_adj,25000*(1+0.03)^(120/12),canon_mes,fam_ubic*canon_adj,serv_deuda,IF(120<=12,0,acum_c2*0.05/12),flujo_neto,35000*fam_act+canon_mes-serv_deuda,fam_ubic)
A21: Familias ubicadas a 15 años | B21: =LET(des_mes,(1-0.05)^(1/12),acum_c1,30000*200*(1-des_mes^180)/(1-des_mes),acum_c2,MIN(200000000,acum_c1*3),sub_por_t,25*0.0*800*38000*1.0,precio_adj,120000000*(1+0.05)^(180/12),cap_pre,acum_c1+acum_c2,terr_pre,MAX(0,ENTERO(cap_pre/precio_adj)),cap_total,acum_c1+acum_c2+terr_pre*sub_por_t,terrenos,MAX(0,ENTERO(cap_total/precio_adj)),fam_ubic,terrenos*25,fam_act,REDONDEAR(200*des_mes^180,0),fam_esp,MAX(0,fam_act-fam_ubic),canon_adj,25000*(1+0.03)^(180/12),canon_mes,fam_ubic*canon_adj,serv_deuda,IF(180<=12,0,acum_c2*0.05/12),flujo_neto,30000*fam_act+canon_mes-serv_deuda,fam_ubic) | C21: =LET(des_mes,(1-0.05)^(1/12),acum_c1,30000*500*(1-des_mes^180)/(1-des_mes),acum_c2,MIN(500000000,acum_c1*3),sub_por_t,25*0.6*800*38000*1.0,precio_adj,120000000*(1+0.05)^(180/12),cap_pre,acum_c1+acum_c2,terr_pre,MAX(0,ENTERO(cap_pre/precio_adj)),cap_total,acum_c1+acum_c2+terr_pre*sub_por_t,terrenos,MAX(0,ENTERO(cap_total/precio_adj)),fam_ubic,terrenos*25,fam_act,REDONDEAR(500*des_mes^180,0),fam_esp,MAX(0,fam_act-fam_ubic),canon_adj,25000*(1+0.03)^(180/12),canon_mes,fam_ubic*canon_adj,serv_deuda,IF(180<=12,0,acum_c2*0.05/12),flujo_neto,30000*fam_act+canon_mes-serv_deuda,fam_ubic) | D21: =LET(des_mes,(1-0.05)^(1/12),acum_c1,35000*1000*(1-des_mes^180)/(1-des_mes),acum_c2,MIN(1500000000,acum_c1*3),sub_por_t,25*0.8*800*38000*1.0,precio_adj,120000000*(1+0.05)^(180/12),cap_pre,acum_c1+acum_c2,terr_pre,MAX(0,ENTERO(cap_pre/precio_adj)),cap_total,acum_c1+acum_c2+terr_pre*sub_por_t,terrenos,MAX(0,ENTERO(cap_total/precio_adj)),fam_ubic,terrenos*25,fam_act,REDONDEAR(1000*des_mes^180,0),fam_esp,MAX(0,fam_act-fam_ubic),canon_adj,25000*(1+0.03)^(180/12),canon_mes,fam_ubic*canon_adj,serv_deuda,IF(180<=12,0,acum_c2*0.05/12),flujo_neto,35000*fam_act+canon_mes-serv_deuda,fam_ubic)
A22: ── CAPITAL ──
A23: Capital total mes 60 (CLP) | B23: =LET(des_mes,(1-0.05)^(1/12),acum_c1,30000*200*(1-des_mes^60)/(1-des_mes),acum_c2,MIN(200000000,acum_c1*3),sub_por_t,25*0.0*800*38000*1.0,precio_adj,120000000*(1+0.05)^(60/12),cap_pre,acum_c1+acum_c2,terr_pre,MAX(0,ENTERO(cap_pre/precio_adj)),cap_total,acum_c1+acum_c2+terr_pre*sub_por_t,terrenos,MAX(0,ENTERO(cap_total/precio_adj)),fam_ubic,terrenos*25,fam_act,REDONDEAR(200*des_mes^60,0),fam_esp,MAX(0,fam_act-fam_ubic),canon_adj,25000*(1+0.03)^(60/12),canon_mes,fam_ubic*canon_adj,serv_deuda,IF(60<=12,0,acum_c2*0.05/12),flujo_neto,30000*fam_act+canon_mes-serv_deuda,cap_total) | C23: =LET(des_mes,(1-0.05)^(1/12),acum_c1,30000*500*(1-des_mes^60)/(1-des_mes),acum_c2,MIN(500000000,acum_c1*3),sub_por_t,25*0.6*800*38000*1.0,precio_adj,120000000*(1+0.05)^(60/12),cap_pre,acum_c1+acum_c2,terr_pre,MAX(0,ENTERO(cap_pre/precio_adj)),cap_total,acum_c1+acum_c2+terr_pre*sub_por_t,terrenos,MAX(0,ENTERO(cap_total/precio_adj)),fam_ubic,terrenos*25,fam_act,REDONDEAR(500*des_mes^60,0),fam_esp,MAX(0,fam_act-fam_ubic),canon_adj,25000*(1+0.03)^(60/12),canon_mes,fam_ubic*canon_adj,serv_deuda,IF(60<=12,0,acum_c2*0.05/12),flujo_neto,30000*fam_act+canon_mes-serv_deuda,cap_total) | D23: =LET(des_mes,(1-0.05)^(1/12),acum_c1,35000*1000*(1-des_mes^60)/(1-des_mes),acum_c2,MIN(1500000000,acum_c1*3),sub_por_t,25*0.8*800*38000*1.0,precio_adj,120000000*(1+0.05)^(60/12),cap_pre,acum_c1+acum_c2,terr_pre,MAX(0,ENTERO(cap_pre/precio_adj)),cap_total,acum_c1+acum_c2+terr_pre*sub_por_t,terrenos,MAX(0,ENTERO(cap_total/precio_adj)),fam_ubic,terrenos*25,fam_act,REDONDEAR(1000*des_mes^60,0),fam_esp,MAX(0,fam_act-fam_ubic),canon_adj,25000*(1+0.03)^(60/12),canon_mes,fam_ubic*canon_adj,serv_deuda,IF(60<=12,0,acum_c2*0.05/12),flujo_neto,35000*fam_act+canon_mes-serv_deuda,cap_total)
A24: Capital total mes 180 (CLP) | B24: =LET(des_mes,(1-0.05)^(1/12),acum_c1,30000*200*(1-des_mes^180)/(1-des_mes),acum_c2,MIN(200000000,acum_c1*3),sub_por_t,25*0.0*800*38000*1.0,precio_adj,120000000*(1+0.05)^(180/12),cap_pre,acum_c1+acum_c2,terr_pre,MAX(0,ENTERO(cap_pre/precio_adj)),cap_total,acum_c1+acum_c2+terr_pre*sub_por_t,terrenos,MAX(0,ENTERO(cap_total/precio_adj)),fam_ubic,terrenos*25,fam_act,REDONDEAR(200*des_mes^180,0),fam_esp,MAX(0,fam_act-fam_ubic),canon_adj,25000*(1+0.03)^(180/12),canon_mes,fam_ubic*canon_adj,serv_deuda,IF(180<=12,0,acum_c2*0.05/12),flujo_neto,30000*fam_act+canon_mes-serv_deuda,cap_total) | C24: =LET(des_mes,(1-0.05)^(1/12),acum_c1,30000*500*(1-des_mes^180)/(1-des_mes),acum_c2,MIN(500000000,acum_c1*3),sub_por_t,25*0.6*800*38000*1.0,precio_adj,120000000*(1+0.05)^(180/12),cap_pre,acum_c1+acum_c2,terr_pre,MAX(0,ENTERO(cap_pre/precio_adj)),cap_total,acum_c1+acum_c2+terr_pre*sub_por_t,terrenos,MAX(0,ENTERO(cap_total/precio_adj)),fam_ubic,terrenos*25,fam_act,REDONDEAR(500*des_mes^180,0),fam_esp,MAX(0,fam_act-fam_ubic),canon_adj,25000*(1+0.03)^(180/12),canon_mes,fam_ubic*canon_adj,serv_deuda,IF(180<=12,0,acum_c2*0.05/12),flujo_neto,30000*fam_act+canon_mes-serv_deuda,cap_total) | D24: =LET(des_mes,(1-0.05)^(1/12),acum_c1,35000*1000*(1-des_mes^180)/(1-des_mes),acum_c2,MIN(1500000000,acum_c1*3),sub_por_t,25*0.8*800*38000*1.0,precio_adj,120000000*(1+0.05)^(180/12),cap_pre,acum_c1+acum_c2,terr_pre,MAX(0,ENTERO(cap_pre/precio_adj)),cap_total,acum_c1+acum_c2+terr_pre*sub_por_t,terrenos,MAX(0,ENTERO(cap_total/precio_adj)),fam_ubic,terrenos*25,fam_act,REDONDEAR(1000*des_mes^180,0),fam_esp,MAX(0,fam_act-fam_ubic),canon_adj,25000*(1+0.03)^(180/12),canon_mes,fam_ubic*canon_adj,serv_deuda,IF(180<=12,0,acum_c2*0.05/12),flujo_neto,35000*fam_act+canon_mes-serv_deuda,cap_total)
A25: ── PRIMER SORTEO ──
A26: Meses hasta 1er sorteo | B26: =LET(des_mes,(1-0.05)^(1/12),meses,SECUENCIA(180),acum_c1,30000*200*(1-des_mes^meses)/(1-des_mes),acum_c2,MIN(200000000,acum_c1*3),cap_t,acum_c1+acum_c2,precio_adj,120000000*(1+0.05)^((meses-1)/12),idx,COINCIDIR(VERDADERO,cap_t>=precio_adj,0),IF(ESERROR(idx),">180",idx)) | C26: =LET(des_mes,(1-0.05)^(1/12),meses,SECUENCIA(180),acum_c1,30000*500*(1-des_mes^meses)/(1-des_mes),acum_c2,MIN(500000000,acum_c1*3),cap_t,acum_c1+acum_c2,precio_adj,120000000*(1+0.05)^((meses-1)/12),idx,COINCIDIR(VERDADERO,cap_t>=precio_adj,0),IF(ESERROR(idx),">180",idx)) | D26: =LET(des_mes,(1-0.05)^(1/12),meses,SECUENCIA(180),acum_c1,35000*1000*(1-des_mes^meses)/(1-des_mes),acum_c2,MIN(1500000000,acum_c1*3),cap_t,acum_c1+acum_c2,precio_adj,120000000*(1+0.05)^((meses-1)/12),idx,COINCIDIR(VERDADERO,cap_t>=precio_adj,0),IF(ESERROR(idx),">180",idx))
A27: ── FLUJO NETO ──
A28: Flujo neto mensual mes 60 | B28: =LET(des_mes,(1-0.05)^(1/12),acum_c1,30000*200*(1-des_mes^60)/(1-des_mes),acum_c2,MIN(200000000,acum_c1*3),sub_por_t,25*0.0*800*38000*1.0,precio_adj,120000000*(1+0.05)^(60/12),cap_pre,acum_c1+acum_c2,terr_pre,MAX(0,ENTERO(cap_pre/precio_adj)),cap_total,acum_c1+acum_c2+terr_pre*sub_por_t,terrenos,MAX(0,ENTERO(cap_total/precio_adj)),fam_ubic,terrenos*25,fam_act,REDONDEAR(200*des_mes^60,0),fam_esp,MAX(0,fam_act-fam_ubic),canon_adj,25000*(1+0.03)^(60/12),canon_mes,fam_ubic*canon_adj,serv_deuda,IF(60<=12,0,acum_c2*0.05/12),flujo_neto,30000*fam_act+canon_mes-serv_deuda,flujo_neto) | C28: =LET(des_mes,(1-0.05)^(1/12),acum_c1,30000*500*(1-des_mes^60)/(1-des_mes),acum_c2,MIN(500000000,acum_c1*3),sub_por_t,25*0.6*800*38000*1.0,precio_adj,120000000*(1+0.05)^(60/12),cap_pre,acum_c1+acum_c2,terr_pre,MAX(0,ENTERO(cap_pre/precio_adj)),cap_total,acum_c1+acum_c2+terr_pre*sub_por_t,terrenos,MAX(0,ENTERO(cap_total/precio_adj)),fam_ubic,terrenos*25,fam_act,REDONDEAR(500*des_mes^60,0),fam_esp,MAX(0,fam_act-fam_ubic),canon_adj,25000*(1+0.03)^(60/12),canon_mes,fam_ubic*canon_adj,serv_deuda,IF(60<=12,0,acum_c2*0.05/12),flujo_neto,30000*fam_act+canon_mes-serv_deuda,flujo_neto) | D28: =LET(des_mes,(1-0.05)^(1/12),acum_c1,35000*1000*(1-des_mes^60)/(1-des_mes),acum_c2,MIN(1500000000,acum_c1*3),sub_por_t,25*0.8*800*38000*1.0,precio_adj,120000000*(1+0.05)^(60/12),cap_pre,acum_c1+acum_c2,terr_pre,MAX(0,ENTERO(cap_pre/precio_adj)),cap_total,acum_c1+acum_c2+terr_pre*sub_por_t,terrenos,MAX(0,ENTERO(cap_total/precio_adj)),fam_ubic,terrenos*25,fam_act,REDONDEAR(1000*des_mes^60,0),fam_esp,MAX(0,fam_act-fam_ubic),canon_adj,25000*(1+0.03)^(60/12),canon_mes,fam_ubic*canon_adj,serv_deuda,IF(60<=12,0,acum_c2*0.05/12),flujo_neto,35000*fam_act+canon_mes-serv_deuda,flujo_neto)
A29: Flujo neto mensual mes 120 | B29: =LET(des_mes,(1-0.05)^(1/12),acum_c1,30000*200*(1-des_mes^120)/(1-des_mes),acum_c2,MIN(200000000,acum_c1*3),sub_por_t,25*0.0*800*38000*1.0,precio_adj,120000000*(1+0.05)^(120/12),cap_pre,acum_c1+acum_c2,terr_pre,MAX(0,ENTERO(cap_pre/precio_adj)),cap_total,acum_c1+acum_c2+terr_pre*sub_por_t,terrenos,MAX(0,ENTERO(cap_total/precio_adj)),fam_ubic,terrenos*25,fam_act,REDONDEAR(200*des_mes^120,0),fam_esp,MAX(0,fam_act-fam_ubic),canon_adj,25000*(1+0.03)^(120/12),canon_mes,fam_ubic*canon_adj,serv_deuda,IF(120<=12,0,acum_c2*0.05/12),flujo_neto,30000*fam_act+canon_mes-serv_deuda,flujo_neto) | C29: =LET(des_mes,(1-0.05)^(1/12),acum_c1,30000*500*(1-des_mes^120)/(1-des_mes),acum_c2,MIN(500000000,acum_c1*3),sub_por_t,25*0.6*800*38000*1.0,precio_adj,120000000*(1+0.05)^(120/12),cap_pre,acum_c1+acum_c2,terr_pre,MAX(0,ENTERO(cap_pre/precio_adj)),cap_total,acum_c1+acum_c2+terr_pre*sub_por_t,terrenos,MAX(0,ENTERO(cap_total/precio_adj)),fam_ubic,terrenos*25,fam_act,REDONDEAR(500*des_mes^120,0),fam_esp,MAX(0,fam_act-fam_ubic),canon_adj,25000*(1+0.03)^(120/12),canon_mes,fam_ubic*canon_adj,serv_deuda,IF(120<=12,0,acum_c2*0.05/12),flujo_neto,30000*fam_act+canon_mes-serv_deuda,flujo_neto) | D29: =LET(des_mes,(1-0.05)^(1/12),acum_c1,35000*1000*(1-des_mes^120)/(1-des_mes),acum_c2,MIN(1500000000,acum_c1*3),sub_por_t,25*0.8*800*38000*1.0,precio_adj,120000000*(1+0.05)^(120/12),cap_pre,acum_c1+acum_c2,terr_pre,MAX(0,ENTERO(cap_pre/precio_adj)),cap_total,acum_c1+acum_c2+terr_pre*sub_por_t,terrenos,MAX(0,ENTERO(cap_total/precio_adj)),fam_ubic,terrenos*25,fam_act,REDONDEAR(1000*des_mes^120,0),fam_esp,MAX(0,fam_act-fam_ubic),canon_adj,25000*(1+0.03)^(120/12),canon_mes,fam_ubic*canon_adj,serv_deuda,IF(120<=12,0,acum_c2*0.05/12),flujo_neto,35000*fam_act+canon_mes-serv_deuda,flujo_neto)
A30: Flujo neto mensual mes 180 | B30: =LET(des_mes,(1-0.05)^(1/12),acum_c1,30000*200*(1-des_mes^180)/(1-des_mes),acum_c2,MIN(200000000,acum_c1*3),sub_por_t,25*0.0*800*38000*1.0,precio_adj,120000000*(1+0.05)^(180/12),cap_pre,acum_c1+acum_c2,terr_pre,MAX(0,ENTERO(cap_pre/precio_adj)),cap_total,acum_c1+acum_c2+terr_pre*sub_por_t,terrenos,MAX(0,ENTERO(cap_total/precio_adj)),fam_ubic,terrenos*25,fam_act,REDONDEAR(200*des_mes^180,0),fam_esp,MAX(0,fam_act-fam_ubic),canon_adj,25000*(1+0.03)^(180/12),canon_mes,fam_ubic*canon_adj,serv_deuda,IF(180<=12,0,acum_c2*0.05/12),flujo_neto,30000*fam_act+canon_mes-serv_deuda,flujo_neto) | C30: =LET(des_mes,(1-0.05)^(1/12),acum_c1,30000*500*(1-des_mes^180)/(1-des_mes),acum_c2,MIN(500000000,acum_c1*3),sub_por_t,25*0.6*800*38000*1.0,precio_adj,120000000*(1+0.05)^(180/12),cap_pre,acum_c1+acum_c2,terr_pre,MAX(0,ENTERO(cap_pre/precio_adj)),cap_total,acum_c1+acum_c2+terr_pre*sub_por_t,terrenos,MAX(0,ENTERO(cap_total/precio_adj)),fam_ubic,terrenos*25,fam_act,REDONDEAR(500*des_mes^180,0),fam_esp,MAX(0,fam_act-fam_ubic),canon_adj,25000*(1+0.03)^(180/12),canon_mes,fam_ubic*canon_adj,serv_deuda,IF(180<=12,0,acum_c2*0.05/12),flujo_neto,30000*fam_act+canon_mes-serv_deuda,flujo_neto) | D30: =LET(des_mes,(1-0.05)^(1/12),acum_c1,35000*1000*(1-des_mes^180)/(1-des_mes),acum_c2,MIN(1500000000,acum_c1*3),sub_por_t,25*0.8*800*38000*1.0,precio_adj,120000000*(1+0.05)^(180/12),cap_pre,acum_c1+acum_c2,terr_pre,MAX(0,ENTERO(cap_pre/precio_adj)),cap_total,acum_c1+acum_c2+terr_pre*sub_por_t,terrenos,MAX(0,ENTERO(cap_total/precio_adj)),fam_ubic,terrenos*25,fam_act,REDONDEAR(1000*des_mes^180,0),fam_esp,MAX(0,fam_act-fam_ubic),canon_adj,25000*(1+0.03)^(180/12),canon_mes,fam_ubic*canon_adj,serv_deuda,IF(180<=12,0,acum_c2*0.05/12),flujo_neto,35000*fam_act+canon_mes-serv_deuda,flujo_neto)
A31: ── COBERTURA DEUDA ──
A32: Cobertura mes 60 (canon/svc) | B32: =LET(des_mes,(1-0.05)^(1/12),acum_c1,30000*200*(1-des_mes^60)/(1-des_mes),acum_c2,MIN(200000000,acum_c1*3),sub_por_t,25*0.0*800*38000*1.0,precio_adj,120000000*(1+0.05)^(60/12),cap_pre,acum_c1+acum_c2,terr_pre,MAX(0,ENTERO(cap_pre/precio_adj)),cap_total,acum_c1+acum_c2+terr_pre*sub_por_t,terrenos,MAX(0,ENTERO(cap_total/precio_adj)),fam_ubic,terrenos*25,canon_adj,25000*(1+0.03)^(60/12),canon_mes,fam_ubic*canon_adj,serv_deuda,IF(60<=12,0,acum_c2*0.05/12),IF(serv_deuda=0,999,REDONDEAR(canon_mes/serv_deuda,2))) | C32: =LET(des_mes,(1-0.05)^(1/12),acum_c1,30000*500*(1-des_mes^60)/(1-des_mes),acum_c2,MIN(500000000,acum_c1*3),sub_por_t,25*0.6*800*38000*1.0,precio_adj,120000000*(1+0.05)^(60/12),cap_pre,acum_c1+acum_c2,terr_pre,MAX(0,ENTERO(cap_pre/precio_adj)),cap_total,acum_c1+acum_c2+terr_pre*sub_por_t,terrenos,MAX(0,ENTERO(cap_total/precio_adj)),fam_ubic,terrenos*25,canon_adj,25000*(1+0.03)^(60/12),canon_mes,fam_ubic*canon_adj,serv_deuda,IF(60<=12,0,acum_c2*0.05/12),IF(serv_deuda=0,999,REDONDEAR(canon_mes/serv_deuda,2))) | D32: =LET(des_mes,(1-0.05)^(1/12),acum_c1,35000*1000*(1-des_mes^60)/(1-des_mes),acum_c2,MIN(1500000000,acum_c1*3),sub_por_t,25*0.8*800*38000*1.0,precio_adj,120000000*(1+0.05)^(60/12),cap_pre,acum_c1+acum_c2,terr_pre,MAX(0,ENTERO(cap_pre/precio_adj)),cap_total,acum_c1+acum_c2+terr_pre*sub_por_t,terrenos,MAX(0,ENTERO(cap_total/precio_adj)),fam_ubic,terrenos*25,canon_adj,25000*(1+0.03)^(60/12),canon_mes,fam_ubic*canon_adj,serv_deuda,IF(60<=12,0,acum_c2*0.05/12),IF(serv_deuda=0,999,REDONDEAR(canon_mes/serv_deuda,2)))
A33: Cobertura mes 120 | B33: =LET(des_mes,(1-0.05)^(1/12),acum_c1,30000*200*(1-des_mes^120)/(1-des_mes),acum_c2,MIN(200000000,acum_c1*3),sub_por_t,25*0.0*800*38000*1.0,precio_adj,120000000*(1+0.05)^(120/12),cap_pre,acum_c1+acum_c2,terr_pre,MAX(0,ENTERO(cap_pre/precio_adj)),cap_total,acum_c1+acum_c2+terr_pre*sub_por_t,terrenos,MAX(0,ENTERO(cap_total/precio_adj)),fam_ubic,terrenos*25,canon_adj,25000*(1+0.03)^(120/12),canon_mes,fam_ubic*canon_adj,serv_deuda,IF(120<=12,0,acum_c2*0.05/12),IF(serv_deuda=0,999,REDONDEAR(canon_mes/serv_deuda,2))) | C33: =LET(des_mes,(1-0.05)^(1/12),acum_c1,30000*500*(1-des_mes^120)/(1-des_mes),acum_c2,MIN(500000000,acum_c1*3),sub_por_t,25*0.6*800*38000*1.0,precio_adj,120000000*(1+0.05)^(120/12),cap_pre,acum_c1+acum_c2,terr_pre,MAX(0,ENTERO(cap_pre/precio_adj)),cap_total,acum_c1+acum_c2+terr_pre*sub_por_t,terrenos,MAX(0,ENTERO(cap_total/precio_adj)),fam_ubic,terrenos*25,canon_adj,25000*(1+0.03)^(120/12),canon_mes,fam_ubic*canon_adj,serv_deuda,IF(120<=12,0,acum_c2*0.05/12),IF(serv_deuda=0,999,REDONDEAR(canon_mes/serv_deuda,2))) | D33: =LET(des_mes,(1-0.05)^(1/12),acum_c1,35000*1000*(1-des_mes^120)/(1-des_mes),acum_c2,MIN(1500000000,acum_c1*3),sub_por_t,25*0.8*800*38000*1.0,precio_adj,120000000*(1+0.05)^(120/12),cap_pre,acum_c1+acum_c2,terr_pre,MAX(0,ENTERO(cap_pre/precio_adj)),cap_total,acum_c1+acum_c2+terr_pre*sub_por_t,terrenos,MAX(0,ENTERO(cap_total/precio_adj)),fam_ubic,terrenos*25,canon_adj,25000*(1+0.03)^(120/12),canon_mes,fam_ubic*canon_adj,serv_deuda,IF(120<=12,0,acum_c2*0.05/12),IF(serv_deuda=0,999,REDONDEAR(canon_mes/serv_deuda,2)))
A34: Cobertura mes 180 | B34: =LET(des_mes,(1-0.05)^(1/12),acum_c1,30000*200*(1-des_mes^180)/(1-des_mes),acum_c2,MIN(200000000,acum_c1*3),sub_por_t,25*0.0*800*38000*1.0,precio_adj,120000000*(1+0.05)^(180/12),cap_pre,acum_c1+acum_c2,terr_pre,MAX(0,ENTERO(cap_pre/precio_adj)),cap_total,acum_c1+acum_c2+terr_pre*sub_por_t,terrenos,MAX(0,ENTERO(cap_total/precio_adj)),fam_ubic,terrenos*25,canon_adj,25000*(1+0.03)^(180/12),canon_mes,fam_ubic*canon_adj,serv_deuda,IF(180<=12,0,acum_c2*0.05/12),IF(serv_deuda=0,999,REDONDEAR(canon_mes/serv_deuda,2))) | C34: =LET(des_mes,(1-0.05)^(1/12),acum_c1,30000*500*(1-des_mes^180)/(1-des_mes),acum_c2,MIN(500000000,acum_c1*3),sub_por_t,25*0.6*800*38000*1.0,precio_adj,120000000*(1+0.05)^(180/12),cap_pre,acum_c1+acum_c2,terr_pre,MAX(0,ENTERO(cap_pre/precio_adj)),cap_total,acum_c1+acum_c2+terr_pre*sub_por_t,terrenos,MAX(0,ENTERO(cap_total/precio_adj)),fam_ubic,terrenos*25,canon_adj,25000*(1+0.03)^(180/12),canon_mes,fam_ubic*canon_adj,serv_deuda,IF(180<=12,0,acum_c2*0.05/12),IF(serv_deuda=0,999,REDONDEAR(canon_mes/serv_deuda,2))) | D34: =LET(des_mes,(1-0.05)^(1/12),acum_c1,35000*1000*(1-des_mes^180)/(1-des_mes),acum_c2,MIN(1500000000,acum_c1*3),sub_por_t,25*0.8*800*38000*1.0,precio_adj,120000000*(1+0.05)^(180/12),cap_pre,acum_c1+acum_c2,terr_pre,MAX(0,ENTERO(cap_pre/precio_adj)),cap_total,acum_c1+acum_c2+terr_pre*sub_por_t,terrenos,MAX(0,ENTERO(cap_total/precio_adj)),fam_ubic,terrenos*25,canon_adj,25000*(1+0.03)^(180/12),canon_mes,fam_ubic*canon_adj,serv_deuda,IF(180<=12,0,acum_c2*0.05/12),IF(serv_deuda=0,999,REDONDEAR(canon_mes/serv_deuda,2)))
A36: * Los KPIs se calculan con fórmulas LET directamente en cada celda. Parámetros fijos: deserción 5%, precio terreno 120M, apreciación 5%, canon 25.000 CLP, crecimiento canon 3%, ratio C2 3x, retorno C2 5%.
